Workbook

Sheet How to Use
A1: Project Pricing Workbook
A2: One tab per build platform. Same columns on every tab, so you can compare like for like.
A4: TABS
A5: Categories | B5: Master category list. Every task points to one of these by category_id.
A6: Rates | B6: Your hourly rates. Fill in the yellow cells. Every tab reads from here.
A7: WordPress / Squarespace / Shopify / WIX / PHP-HTML-CSS / React-NextJS | B7: The task libraries. Filter by Category, Responsible, or Level to build a quote.
A8: Summary | B8: Total hours and cost per platform, so you can compare platforms at a glance.
A10: COLUMNS
A11: category_id / Category | B11: Which category the task belongs to. Category name fills in automatically.
A12: Base Hours | B12: Your original hours. I did not change any of them.
A13: Responsible | B13: Who does the work: IT, Creative, Project Manager, QA Tester, or Project Coordinator.
A14: Level | B14: Level 1 = standard config and build work. Level 2 = senior, custom-coded, or higher-risk work.
A15: Rate | B15: Pulled automatically from the Rates tab using Responsible + Level.
A16: Estimated Cost | B16: Base Hours x Rate.
A17: Hours – Things to Consider | B17: What can push the hours up or down. A note only; it changes no calculation.
A19: HOW TO QUOTE A JOB
A20: Step 1 | B20: Open the tab for the platform you are building on.
A21: Step 2 | B21: Filter or highlight only the tasks that job actually needs.
A22: Step 3 | B22: Read the 'Things to Consider' notes before you commit to the hours.
A23: Step 4 | B23: Add up the Estimated Cost of the tasks you selected. The tab TOTAL is the whole library, not a quote.
A25: STILL TO ADD
A26: Difficulty sub-category | B26: Easy / Medium / Hard inside each category, so harder tasks bill more than easy ones.
A27: Discovery, PM, Docs & Training | B27: Categories 10, 11, 21 exist but have no tasks yet on any tab.
A28: Local SEO / SEO off-page / Maintenance | B28: Categories 16, 17, 23 exist but have no tasks yet on any tab.

Sheet Categories
A1: Categories
A2: Add a new category here and it becomes available to every platform tab.
A4: category_id | B4: Category | C4: Description
A5: 1 | B5: Accessibility | C5: Making the site usable for people with disabilities (WCAG/ADA compliance).
A6: 2 | B6: Backend | C6: Server-side logic, APIs, and application functionality.
A7: 3 | B7: CMS & Content Prep | C7: Setting up the CMS and preparing content so the client can manage the site.
A8: 4 | B8: Conversion Tracking | C8: Measuring and reporting the actions visitors take on the site.
A9: 5 | B9: Custom Tools | C9: Calculators, configurators, and other custom-built features.
A10: 6 | B10: Data Migration | C10: Moving content, users, and data from an old system to the new one.
A11: 7 | B11: Database | C11: Designing, building, and optimizing the database that stores project data.
A12: 8 | B12: Deployment | C12: Publishing the site or software to the live server.
A13: 9 | B13: Design | C13: Visual design, layouts, and user experience.
A14: 10 | B14: Discovery & Planning | C14: Gathering requirements, scoping the project, and planning the build.
A15: 11 | B15: Documentation & Training | C15: User guides and training so the client can run the site themselves.
A16: 12 | B16: E-Commerce | C16: Online store features, product catalog, cart, and checkout.
... A27: 25 | B27: QA & Testing | C27: Testing the site or software to find and fix bugs before launch.

Sheet Rates
A1: Hourly Rates
A2: EDIT THE YELLOW CELLS. These feed the Rate and Estimated Cost columns on every platform tab.
A3: Level 2 = senior / higher skill / higher risk. It should always be priced above Level 1.
A5: Responsible | B5: Level | C5: Lookup Key | D5: Hourly Rate
A6: IT | B6: Level 1 | C6: =A6&"|"&B6 -> IT|Level 1 | D6: 100
A7: IT | B7: Level 2 | C7: =A7&"|"&B7 -> IT|Level 2 | D7: 120
A8: Creative | B8: Level 1 | C8: =A8&"|"&B8 -> Creative|Level 1 | D8: 100
A9: Creative | B9: Level 2 | C9: =A9&"|"&B9 -> Creative|Level 2 | D9: 130
A10: Project Manager | B10: Level 1 | C10: =A10&"|"&B10 -> Project Manager|Level 1 | D10: 80
A11: Project Manager | B11: Level 2 | C11: =A11&"|"&B11 -> Project Manager|Level 2 | D11: 100
A12: QA Tester | B12: Level 1 | C12: =A12&"|"&B12 -> QA Tester|Level 1 | D12: 80
A13: QA Tester | B13: Level 2 | C13: =A13&"|"&B13 -> QA Tester|Level 2 | D13: 120
A14: Project Coordinator | B14: Level 1 | C14: =A14&"|"&B14 -> Project Coordinator|Level 1 | D14: 0
A15: Project Coordinator | B15: Level 2 | C15: =A15&"|"&B15 -> Project Coordinator|Level 2 | D15: 0
A17: These are placeholder examples only. Your edited rates were not in the file you sent, so replace these with your own numbers.

Sheet WordPress
A1: Task Pricing – WordPress
A2: Base Hours unchanged from your original sheet.
A4: id | B4: Dependencies | C4: Module | D4: Name | E4: category_id | F4: Category | G4: Description | H4: Responsible | I4: Level | J4: Rate | K4: Base Hours | L4: Estimated Cost | M4: Hours – Things to Consider
A5: 1 | C5: Homepage – Standard | D5: Hero Section | E5: 14 | F5: =IFERROR(INDEX(Categories!$B$5:$B$27,MATCH(E5,Categories!$A$5:$A$27,0)),"") -> Frontend | G5: Hero section and headline | H5: IT | I5: Level 1 | J5: =IFERROR(INDEX(Rates!$D$6:$D$15,MATCH(H5&"|"&I5,Rates!$C$6:$C$15,0)),0) -> 100 | K5: 1.5 | L5: =K5*J5 -> 150 | M5: Assumes design is already approved. Add hours if animation or video background is required.
A6: 2 | C6: Homepage – Standard | D6: Services or Product Grid | E6: 14 | F6: =IFERROR(INDEX(Categories!$B$5:$B$27,MATCH(E6,Categories!$A$5:$A$27,0)),"") -> Frontend | G6: Grid layout for displaying services, products, programs, or offerings (including nonprofit initiatives or services). | H6: IT | I6: Level 1 | J6: =IFERROR(INDEX(Rates!$D$6:$D$15,MATCH(H6&"|"&I6,Rates!$C$6:$C$15,0)),0) -> 100 | K6: 2.5 | L6: =K6*J6 -> 250 | M6: Assumes a fixed number of items. Dynamic/CPT-driven grids cost more.
A7: 3 | C7: Homepage – Standard | D7: Testimonials Slider-Dynamic | E7: 15 | F7: =IFERROR(INDEX(Categories!$B$5:$B$27,MATCH(E7,Categories!$A$5:$A$27,0)),"") -> Integration | G7: Dynamic testimonials integration via external API (e.g., review platforms), not embed-based | H7: IT | I7: Level 2 | J7: =IFERROR(INDEX(Rates!$D$6:$D$15,MATCH(H7&"|"&I7,Rates!$C$6:$C$15,0)),0) -> 120 | K7: 8 | L7: =K7*J7 -> 960 | M7: Depends on the review platform's API. Add hours if API keys, rate limits, or caching are involved.
A8: 4 | C8: Homepage – Standard | D8: Testimonials Slider- embed | E8: 15 | F8: =IFERROR(INDEX(Categories!$B$5:$B$27,MATCH(E8,Categories!$A$5:$A$27,0)),"") -> Integration | G8: Embedded testimonials using iframe or widget from external platforms. | H8: IT | I8: Level 1 | J8: =IFERROR(INDEX(Rates!$D$6:$D$15,MATCH(H8&"|"&I8,Rates!$C$6:$C$15,0)),0) -> 100 | K8: 3 | L8: =K8*J8 -> 300 | M8: Styling a third-party widget can take longer than expected if the platform limits CSS.
A9: 5 | C9: Homepage – Standard | D9: Team Preview | E9: 14 | F9: =IFERROR(INDEX(Categories!$B$5:$B$27,MATCH(E9,Categories!$A$5:$A$27,0)),"") -> Frontend | G9: Section highlighting team members, staff, or key representatives | H9: IT | I9: Level 1 | J9: =IFERROR(INDEX(Rates!$D$6:$D$15,MATCH(H9&"|"&I9,Rates!$C$6:$C$15,0)),0) -> 100 | K9: 1.5 | L9: =K9*J9 -> 150 | M9: Per-person bios and photo cropping are usually content work, not build work.
A10: 6 | C10: Homepage – Standard | D10: Footer Layout | E10: 14 | F10: =IFERROR(INDEX(Categories!$B$5:$B$27,MATCH(E10,Categories!$A$5:$A$27,0)),"") -> Frontend | G10: Structured footer with navigation and contact info | H10: IT | I10: Level 1 | J10: =IFERROR(INDEX(Rates!$D$6:$D$15,MATCH(H10&"|"&I10,Rates!$C$6:$C$15,0)),0) -> 100 | K10: 1.5 | L10: =K10*J10 -> 150 | M10: Mega-footers with multiple menus and a newsletter form run higher.
A11: 7 | C11: Homepage – Conversion | D11: Strong Hero Offer | E11: 14 | F11: =IFERROR(INDEX(Categories!$B$5:$B$27,MATCH(E11,Categories!$A$5:$A$27,0)),"") -> Frontend | G11: Strong hero offer with CTA | H11: IT | I11: Level 1 | J11: =IFERROR(INDEX(Rates!$D$6:$D$15,MATCH(H11&"|"&I11,Rates!$C$6:$C$15,0)),0) -> 100 | K11: 4 | L11: =K11*J11 -> 400 | M11: Add hours if A/B variants of the hero are required.
A12: 8 | C12: Homepage – Conversion | D12: Benefits/Features | E12: 14 | F12: =IFERROR(INDEX(Categories!$B$5:$B$27,MATCH(E12,Categories!$A$5:$A$27,0)),"") -> Frontend | G12: Highlight product/service benefits | H12: IT | I12: Level 1 | J12: =IFERROR(INDEX(Rates!$D$6:$D$15,MATCH(H12&"|"&I12,Rates!$C$6:$C$15,0)),0) -> 100 | K12: 3 | L12: =K12*J12 -> 300 | M12: Icon sourcing or custom icons may need Creative hours on top.
A13: 9 | C13: Homepage – Conversion | D13: Social Proof / Trust Badges | E13: 14 | F13: =IFERROR(INDEX(Categories!$B$5:$B$27,MATCH(E13,Categories!$A$5:$A$27,0)),"") -> Frontend | G13: Section showcasing logos, trust badges, or affiliations to build credibility, reinforce trust, and support conversion. | H13: IT | I13: Level 1 | J13: =IFERROR(INDEX(Rates!$D$6:$D$15,MATCH(H13&"|"&I13,Rates!$C$6:$C$15,0)),0) -> 100 | K13: 2 | L13: =K13*J13 -> 200 | M13: Assumes client supplies logos in usable formats. Logo cleanup is Creative time.
A14: 10 | C14: Homepage – Conversion | D14: FAQ Section | E14: 14 | F14: =IFERROR(INDEX(Categories!$B$5:$B$27,MATCH(E14,Categories!$A$5:$A$27,0)),"") -> Frontend | G14: Frequently asked questions block | H14: IT | I14: Level 1 | J14: =IFERROR(INDEX(Rates!$D$6:$D$15,MATCH(H14&"|"&I14,Rates!$C$6:$C$15,0)),0) -> 100 | K14: 2 | L14: =K14*J14 -> 200 | M14: Add a little time if FAQ schema markup is also required (see Schema Markup).
A15: 11 | C15: Homepage – Standard | D15: Pricing Tables | E15: 14 | F15: =IFERROR(INDEX(Categories!$B$5:$B$27,MATCH(E15,Categories!$A$5:$A$27,0)),"") -> Frontend | G15: Structured plans with features and comparison layout | H15: IT | I15: Level 1 | J15: =IFERROR(INDEX(Rates!$D$6:$D$15,MATCH(H15&"|"&I15,Rates!$C$6:$C$15,0)),0) -> 100 | K15: 4 | L15: =K15*J15 -> 400 | M15: Monthly/annual toggles or more than 3 plans push this higher.
A16: 12 | C16: Homepage – Standard | D16: Galleries | E16: 14 | F16: =IFERROR(INDEX(Categories!$B$5:$B$27,MATCH(E16,Categories!$A$5:$A$27,0)),"") -> Frontend | G16: Image gallery layout for showcasing media (grid, slider, or lightbox) | H16: IT | I16: Level 1 | J16: =IFERROR(INDEX(Rates!$D$6:$D$15,MATCH(H16&"|"&I16,Rates!$C$6:$C$15,0)),0) -> 100 | K16: 2 | L16: =K16*J16 -> 200 | M16: Assumes one gallery. Price per additional gallery, and add image prep time.
... A18: 14 | C18: Homepage - Standard | D18: Payment / Contribution Module | E18: 15 | F18: =IFERROR(INDEX(Categories!$B$5:$B$27,MATCH(E18,Categories!$A$5:$A$27,0)),"") -> Integration | G18: Payment or contribution functionality using plugin-based integration (e.g., Stripe/PayPal), no custom gateway. | H18: IT | I18: Level 2 | J18: =IFERROR(INDEX(Rates!$D$6:$D$15,MATCH(H18&"|"&I18,Rates!$C$6:$C$15,0)),0) -> 120 | K18: 5 | L18: =K18*J18 -> 600 | M18: Excludes merchant account setup and recurring donations. Test-mode and live-mode testing both take time.
A19: 15 | C19: Homepage - Standard | D19: Use Cases | E19: 14 | F19: =IFERROR(INDEX(Categories!$B$5:$B$27,MATCH(E19,Categories!$A$5:$A$27,0)),"") -> Frontend | G19: Real-world scenarios or examples demonstrating how offerings are used | H19: IT | I19: Level 1 | J19: =IFERROR(INDEX(Rates!$D$6:$D$15,MATCH(H19&"|"&I19,Rates!$C$6:$C$15,0)),0) -> 100 | K19: 2 | L19: =K19*J19 -> 200
A20: 16 | C20: Homepage – Multi-Industry | D20: Industry Selector | E20: 14 | F20: =IFERROR(INDEX(Categories!$B$5:$B$27,MATCH(E20,Categories!$A$5:$A$27,0)),"") -> Frontend | G20: Selector for multiple industries | H20: IT | I20: Level 2 | J20: =IFERROR(INDEX(Rates!$D$6:$D$15,MATCH(H20&"|"&I20,Rates!$C$6:$C$15,0)),0) -> 120 | K20: 8 | L20: =K20*J20 -> 960 | M20: Hours scale with the number of industries. Confirm a cap in the quote.
A21: 17 | C21: Homepage – Multi-Industry | D21: Location Selector | E21: 14 | F21: =IFERROR(INDEX(Categories!$B$5:$B$27,MATCH(E21,Categories!$A$5:$A$27,0)),"") -> Frontend | G21: Selector for multiple branches/locations | H21: IT | I21: Level 2 | J21: =IFERROR(INDEX(Rates!$D$6:$D$15,MATCH(H21&"|"&I21,Rates!$C$6:$C$15,0)),0) -> 120 | K21: 8 | L21: =K21*J21 -> 960 | M21: Hours scale with the number of locations. Confirm a cap in the quote.
A22: 18 | C22: Homepage – Multi-Industry | D22: Dynamic Content Sections | E22: 14 | F22: =IFERROR(INDEX(Categories!$B$5:$B$27,MATCH(E22,Categories!$A$5:$A$27,0)),"") -> Frontend | G22: Conditional content per audience | H22: IT | I22: Level 2 | J22: =IFERROR(INDEX(Rates!$D$6:$D$15,MATCH(H22&"|"&I22,Rates!$C$6:$C$15,0)),0) -> 120 | K22: 10 | L22: =K22*J22 -> 1200 | M22: Each extra condition/rule adds testing time, not just build time.
A23: 19 | C23: Homepage – Multi-Industry | D23: Interactive Location Finder | E23: 15 | F23: =IFERROR(INDEX(Categories!$B$5:$B$27,MATCH(E23,Categories!$A$5:$A$27,0)),"") -> Integration | G23: Map or location-based finder for offices, stores, or service areas | H23: IT | I23: Level 2 | J23: =IFERROR(INDEX(Rates!$D$6:$D$15,MATCH(H23&"|"&I23,Rates!$C$6:$C$15,0)),0) -> 120 | K23: 12 | L23: =K23*J23 -> 1440 | M23: Excludes map API billing (Google Maps is metered). Radius search and geolocation add hours.
A24: 20 | C24: Homepage – Multi-Industry | D24: Multi-Audience Messaging | E24: 14 | F24: =IFERROR(INDEX(Categories!$B$5:$B$27,MATCH(E24,Categories!$A$5:$A$27,0)),"") -> Frontend | G24: Content tailored to different audience segments or user types | H24: IT | I24: Level 2 | J24: =IFERROR(INDEX(Rates!$D$6:$D$15,MATCH(H24&"|"&I24,Rates!$C$6:$C$15,0)),0) -> 120 | K24: 12 | L24: =K24*J24 -> 1440 | M24: Content writing for each segment is separate from the build.
A25: 21 | C25: Core Page - Standard | D25: Standard Page (About, Services) | E25: 14 | F25: =IFERROR(INDEX(Categories!$B$5:$B$27,MATCH(E25,Categories!$A$5:$A$27,0)),"") -> Frontend | G25: Standard Content Page (About, Services, etc.) | H25: IT | I25: Level 1 | J25: =IFERROR(INDEX(Rates!$D$6:$D$15,MATCH(H25&"|"&I25,Rates!$C$6:$C$15,0)),0) -> 100 | K25: 8 | L25: =K25*J25 -> 800 | M25: This is per page. Multiply by page count and confirm the total in the quote.
A26: 22 | C26: Core Page - Landing Page | D26: Conversion Page | E26: 14 | F26: =IFERROR(INDEX(Categories!$B$5:$B$27,MATCH(E26,Categories!$A$5:$A$27,0)),"") -> Frontend | G26: Conversion-focused landing page designed to drive specific user actions (e.g., lead generation or sales), including structured sections such as hero, benefits, social proof, and strong CTAs using a reusable layout. | H26: IT | I26: Level 1 | J26: =IFERROR(INDEX(Rates!$D$6:$D$15,MATCH(H26&"|"&I26,Rates!$C$6:$C$15,0)),0) -> 100 | K26: 8 | L26: =K26*J26 -> 800 | M26: Per page. Second and later landing pages using the same layout should be cheaper.
A27: 23 | C27: Core Page - Contact Page | D27: Form or contact details page | E27: 14 | F27: =IFERROR(INDEX(Categories!$B$5:$B$27,MATCH(E27,Categories!$A$5:$A$27,0)),"") -> Frontend | G27: Contact page including form setup and/or business contact details, with clear layout, validation, and user-friendly structure for inquiries or lead capture. | H27: IT | I27: Level 1 | J27: =IFERROR(INDEX(Rates!$D$6:$D$15,MATCH(H27&"|"&I27,Rates!$C$6:$C$15,0)),0) -> 100 | K27: 6 | L27: =K27*J27 -> 600 | M27: Includes one form. Map embed and multi-location contact info may add time.
A28: 24 | C28: Core Page - Detail Pages | D28: Detail Template | E28: 14 | F28: =IFERROR(INDEX(Categories!$B$5:$B$27,MATCH(E28,Categories!$A$5:$A$27,0)),"") -> Frontend | G28: Template-based detail page for individual content (e.g., blog posts or service pages), structured for readability, SEO, and consistent layout | H28: IT | I28: Level 1 | J28: =IFERROR(INDEX(Rates!$D$6:$D$15,MATCH(H28&"|"&I28,Rates!$C$6:$C$15,0)),0) -> 100 | K28: 6 | L28: =K28*J28 -> 600 | M28: Per template. Each additional content type usually needs its own template.
A29: 25 | C29: Homepage – Standard | D29: Forms Spam Protection (reCAPTCHA) | E29: 18 | F29: =IFERROR(INDEX(Categories!$B$5:$B$27,MATCH(E29,Categories!$A$5:$A$27,0)),"") -> Performance & Security | G29: Implement and configure reCAPTCHA (v2/v3) on all forms to prevent spam submissions. | H29: IT | I29: Level 1 | J29: =IFERROR(INDEX(Rates!$D$6:$D$15,MATCH(H29&"|"&I29,Rates!$C$6:$C$15,0)),0) -> 100 | K29: 1 | L29: =K29*J29 -> 100 | M29: Covers all forms at once. Honeypot or alternative spam tools may be quicker or slower.
A30: 26 | C30: Homepage – Advanced Dynamic | D30: Custom-Coded Blocks | E30: 14 | F30: =IFERROR(INDEX(Categories!$B$5:$B$27,MATCH(E30,Categories!$A$5:$A$27,0)),"") -> Frontend | G30: Custom reusable blocks | H30: IT | I30: Level 2 | J30: =IFERROR(INDEX(Rates!$D$6:$D$15,MATCH(H30&"|"&I30,Rates!$C$6:$C$15,0)),0) -> 120 | K30: 15 | L30: =K30*J30 -> 1800 | M30: Hours depend heavily on how many blocks. Define the block count in the quote.
A31: 27 | C31: Homepage – Advanced Dynamic | D31: Search Bar with Filters | E31: 14 | F31: =IFERROR(INDEX(Categories!$B$5:$B$27,MATCH(E31,Categories!$A$5:$A$27,0)),"") -> Frontend | G31: Advanced search and filter functionality | H31: IT | I31: Level 2 | J31: =IFERROR(INDEX(Rates!$D$6:$D$15,MATCH(H31&"|"&I31,Rates!$C$6:$C$15,0)),0) -> 120 | K31: 18 | L31: =K31*J31 -> 2160 | M31: AJAX filtering, large datasets, and combined filters all add significant time.
... A45: 41 | C45: Forms – Multi-Step | D45: Submission Handling | E45: 2 | F45: =IFERROR(INDEX(Categories!$B$5:$B$27,MATCH(E45,Categories!$A$5:$A$27,0)),"") -> Backend | G45: Store and process multi-step submissions | H45: IT | I45: Level 2 | J45: =IFERROR(INDEX(Rates!$D$6:$D$15,MATCH(H45&"|"&I45,Rates!$C$6:$C$15,0)),0) -> 120 | K45: 2 | L45: =K45*J45 -> 240 | M45: Partial-save and resume functionality would add substantially.
A46: 42 | B46: 37-40: Form Setup | C46: Forms – CRM Integration | D46: CRM API Setup | E46: 15 | F46: =IFERROR(INDEX(Categories!$B$5:$B$27,MATCH(E46,Categories!$A$5:$A$27,0)),"") -> Integration | G46: Connect form submissions to CRM | H46: IT | I46: Level 2 | J46: =IFERROR(INDEX(Rates!$D$6:$D$15,MATCH(H46&"|"&I46,Rates!$C$6:$C$15,0)),0) -> 120 | K46: 4 | L46: =K46*J46 -> 480 | M46: Assumes client provides CRM access and credentials. Delays here are common.
A47: 43 | B47: 37-40: Form Setup | C47: Forms – CRM Integration | D47: Data Mapping | E47: 15 | F47: =IFERROR(INDEX(Categories!$B$5:$B$27,MATCH(E47,Categories!$A$5:$A$27,0)),"") -> Integration | G47: Map form fields to CRM fields | H47: IT | I47: Level 2 | J47: =IFERROR(INDEX(Rates!$D$6:$D$15,MATCH(H47&"|"&I47,Rates!$C$6:$C$15,0)),0) -> 120 | K47: 2 | L47: =K47*J47 -> 240 | M47: Hours rise with field count and custom CRM objects.
A48: 44 | B48: 37-40: Form Setup | C48: Forms – CRM Integration | D48: Error Handling & Logging | E48: 15 | F48: =IFERROR(INDEX(Categories!$B$5:$B$27,MATCH(E48,Categories!$A$5:$A$27,0)),"") -> Integration | G48: Handle API errors and log submissions | H48: IT | I48: Level 2 | J48: =IFERROR(INDEX(Rates!$D$6:$D$15,MATCH(H48&"|"&I48,Rates!$C$6:$C$15,0)),0) -> 120 | K48: 2 | L48: =K48*J48 -> 240 | M48: Retry logic and admin alerts would add hours.
A49: 45 | C49: Integrations | D49: Appointment System | E49: 15 | F49: =IFERROR(INDEX(Categories!$B$5:$B$27,MATCH(E49,Categories!$A$5:$A$27,0)),"") -> Integration | G49: Booking and scheduling system. Plugin-based booking system (no custom development) | H49: IT | I49: Level 1 | J49: =IFERROR(INDEX(Rates!$D$6:$D$15,MATCH(H49&"|"&I49,Rates!$C$6:$C$15,0)),0) -> 100 | K49: 3 | L49: =K49*J49 -> 300 | M49: Excludes staff schedules, services, and availability data entry. That is Coordinator time.
A50: 46 | C50: Integrations | D50: Live Chat Integration | E50: 15 | F50: =IFERROR(INDEX(Categories!$B$5:$B$27,MATCH(E50,Categories!$A$5:$A$27,0)),"") -> Integration | G50: Embed live chat widget | H50: IT | I50: Level 1 | J50: =IFERROR(INDEX(Rates!$D$6:$D$15,MATCH(H50&"|"&I50,Rates!$C$6:$C$15,0)),0) -> 100 | K50: 2 | L50: =K50*J50 -> 200 | M50: Duplicate of task 36. Pick one and remove the other.
A51: 47 | C51: Integrations | D51: API Integration Basic | E51: 15 | F51: =IFERROR(INDEX(Categories!$B$5:$B$27,MATCH(E51,Categories!$A$5:$A$27,0)),"") -> Integration | G51: Simple API Integration | H51: IT | I51: Level 2 | J51: =IFERROR(INDEX(Rates!$D$6:$D$15,MATCH(H51&"|"&I51,Rates!$C$6:$C$15,0)),0) -> 120 | K51: 12 | L51: =K51*J51 -> 1440 | M51: Define 'basic' in writing: read-only, one endpoint, documented API.
A52: 48 | C52: Integrations | D52: API Integration Complex | E52: 15 | F52: =IFERROR(INDEX(Categories!$B$5:$B$27,MATCH(E52,Categories!$A$5:$A$27,0)),"") -> Integration | G52: Complex API Integration | H52: IT | I52: Level 2 | J52: =IFERROR(INDEX(Rates!$D$6:$D$15,MATCH(H52&"|"&I52,Rates!$C$6:$C$15,0)),0) -> 120 | K52: 25 | L52: =K52*J52 -> 3000 | M52: High overrun risk. Consider quoting a discovery block first, then the build.
A53: 49 | C53: Integrations | D53: Zapier Workflows | E53: 15 | F53: =IFERROR(INDEX(Categories!$B$5:$B$27,MATCH(E53,Categories!$A$5:$A$27,0)),"") -> Integration | G53: Automate workflows with Zapier | H53: IT | I53: Level 1 | J53: =IFERROR(INDEX(Rates!$D$6:$D$15,MATCH(H53&"|"&I53,Rates!$C$6:$C$15,0)),0) -> 100 | K53: 6 | L53: =K53*J53 -> 600 | M53: Priced per set of workflows. Note how many Zaps are included. Excludes Zapier subscription.
A54: 50 | C54: Integrations | D54: Accessibility (ADA) Basic | E54: 1 | F54: =IFERROR(INDEX(Categories!$B$5:$B$27,MATCH(E54,Categories!$A$5:$A$27,0)),"") -> Accessibility | G54: Essential fixes for usability (alt text, contrast, basic keyboard support) | H54: IT | I54: Level 1 | J54: =IFERROR(INDEX(Rates!$D$6:$D$15,MATCH(H54&"|"&I54,Rates!$C$6:$C$15,0)),0) -> 100 | K54: 6 | L54: =K54*J54 -> 600 | M54: Scales with page count. Alt text writing may be Creative or Coordinator time.
A55: 51 | C55: Integrations | D55: Accessibility (ADA) Strict Compliance | E55: 1 | F55: =IFERROR(INDEX(Categories!$B$5:$B$27,MATCH(E55,Categories!$A$5:$A$27,0)),"") -> Accessibility | G55: Full WCAG compliance with complete support and thorough testing | H55: IT | I55: Level 2 | J55: =IFERROR(INDEX(Rates!$D$6:$D$15,MATCH(H55&"|"&I55,Rates!$C$6:$C$15,0)),0) -> 120 | K55: 25 | L55: =K55*J55 -> 3000 | M55: Excludes third-party audit or certification. Never guarantee legal compliance in the quote.
A56: 52 | C56: Member Login | D56: Basic Login System | E56: 2 | F56: =IFERROR(INDEX(Categories!$B$5:$B$27,MATCH(E56,Categories!$A$5:$A$27,0)),"") -> Backend | G56: User login and registration | H56: IT | I56: Level 2 | J56: =IFERROR(INDEX(Rates!$D$6:$D$15,MATCH(H56&"|"&I56,Rates!$C$6:$C$15,0)),0) -> 120 | K56: 10 | L56: =K56*J56 -> 1200 | M56: Email verification, password reset, and security hardening should be confirmed as in or out.
A57: 53 | C57: Member Login | D57: Profile Management | E57: 2 | F57: =IFERROR(INDEX(Categories!$B$5:$B$27,MATCH(E57,Categories!$A$5:$A$27,0)),"") -> Backend | G57: Basic profile editing and updates | H57: IT | I57: Level 2 | J57: =IFERROR(INDEX(Rates!$D$6:$D$15,MATCH(H57&"|"&I57,Rates!$C$6:$C$15,0)),0) -> 120 | K57: 10 | L57: =K57*J57 -> 1200 | M57: Custom profile fields and avatar uploads add hours.
A58: 54 | C58: Member Login | D58: Role-Based Content | E58: 2 | F58: =IFERROR(INDEX(Categories!$B$5:$B$27,MATCH(E58,Categories!$A$5:$A$27,0)),"") -> Backend | G58: Restrict content based on user roles | H58: IT | I58: Level 2 | J58: =IFERROR(INDEX(Rates!$D$6:$D$15,MATCH(H58&"|"&I58,Rates!$C$6:$C$15,0)),0) -> 120 | K58: 12 | L58: =K58*J58 -> 1440 | M58: Hours scale with the number of roles and restriction rules.
A59: 55 | C59: Member Login | D59: Document Portal Setup | E59: 2 | F59: =IFERROR(INDEX(Categories!$B$5:$B$27,MATCH(E59,Categories!$A$5:$A$27,0)),"") -> Backend | G59: Portal for uploading and accessing documents. Plugin-based solution (no custom-built portal) | H59: IT | I59: Level 2 | J59: =IFERROR(INDEX(Rates!$D$6:$D$15,MATCH(H59&"|"&I59,Rates!$C$6:$C$15,0)),0) -> 120 | K59: 20 | L59: =K59*J59 -> 2400 | M59: Excludes uploading the client's actual documents. That is Coordinator time.
A60: 56 | C60: E-Commerce | D60: Product Template | E60: 12 | F60: =IFERROR(INDEX(Categories!$B$5:$B$27,MATCH(E60,Categories!$A$5:$A$27,0)),"") -> E-Commerce | G60: Product page template | H60: IT | I60: Level 1 | J60: =IFERROR(INDEX(Rates!$D$6:$D$15,MATCH(H60&"|"&I60,Rates!$C$6:$C$15,0)),0) -> 100 | K60: 7 | L60: =K60*J60 -> 700 | M60: One template. Variable and simple products may need different treatments.
A61: 57 | C61: E-Commerce | D61: Featured Products | E61: 12 | F61: =IFERROR(INDEX(Categories!$B$5:$B$27,MATCH(E61,Categories!$A$5:$A$27,0)),"") -> E-Commerce | G61: Homepage products | H61: IT | I61: Level 1 | J61: =IFERROR(INDEX(Rates!$D$6:$D$15,MATCH(H61&"|"&I61,Rates!$C$6:$C$15,0)),0) -> 100 | K61: 6 | L61: =K61*J61 -> 600
A62: 58 | C62: E-Commerce | D62: Sales Banners | E62: 12 | F62: =IFERROR(INDEX(Categories!$B$5:$B$27,MATCH(E62,Categories!$A$5:$A$27,0)),"") -> E-Commerce | G62: Promo banners | H62: Creative | I62: Level 1 | J62: =IFERROR(INDEX(Rates!$D$6:$D$15,MATCH(H62&"|"&I62,Rates!$C$6:$C$15,0)),0) -> 100 | K62: 5 | L62: =K62*J62 -> 500 | M62: Banner artwork per campaign is recurring work worth a maintenance line item.
A63: 59 | C63: E-Commerce | D63: Dynamic Product Feeds | E63: 12 | F63: =IFERROR(INDEX(Categories!$B$5:$B$27,MATCH(E63,Categories!$A$5:$A$27,0)),"") -> E-Commerce | G63: Product listings | H63: IT | I63: Level 2 | J63: =IFERROR(INDEX(Rates!$D$6:$D$15,MATCH(H63&"|"&I63,Rates!$C$6:$C$15,0)),0) -> 120 | K63: 8 | L63: =K63*J63 -> 960 | M63: Feeds to Google Merchant Center or Meta have their own spec requirements.
A64: 60 | C64: E-Commerce | D64: Category Highlights | E64: 12 | F64: =IFERROR(INDEX(Categories!$B$5:$B$27,MATCH(E64,Categories!$A$5:$A$27,0)),"") -> E-Commerce | G64: Product categories | H64: IT | I64: Level 1 | J64: =IFERROR(INDEX(Rates!$D$6:$D$15,MATCH(H64&"|"&I64,Rates!$C$6:$C$15,0)),0) -> 100 | K64: 6 | L64: =K64*J64 -> 600
A65: 61 | C65: E-Commerce | D65: Customer Reviews | E65: 12 | F65: =IFERROR(INDEX(Categories!$B$5:$B$27,MATCH(E65,Categories!$A$5:$A$27,0)),"") -> E-Commerce | G65: Reviews | H65: IT | I65: Level 1 | J65: =IFERROR(INDEX(Rates!$D$6:$D$15,MATCH(H65&"|"&I65,Rates!$C$6:$C$15,0)),0) -> 100 | K65: 6 | L65: =K65*J65 -> 600 | M65: Plugin-based. Importing existing reviews would be extra.
A66: 62 | C66: E-Commerce | D66: Personalization Blocks | E66: 12 | F66: =IFERROR(INDEX(Categories!$B$5:$B$27,MATCH(E66,Categories!$A$5:$A$27,0)),"") -> E-Commerce | G66: Recommendations | H66: IT | I66: Level 2 | J66: =IFERROR(INDEX(Rates!$D$6:$D$15,MATCH(H66&"|"&I66,Rates!$C$6:$C$15,0)),0) -> 120 | K66: 6 | L66: =K66*J66 -> 720 | M66: Rule-based vs. algorithmic recommendations are very different scopes.
A67: 63 | C67: E-Commerce | D67: Cart Functionality | E67: 12 | F67: =IFERROR(INDEX(Categories!$B$5:$B$27,MATCH(E67,Categories!$A$5:$A$27,0)),"") -> E-Commerce | G67: Add to cart | H67: IT | I67: Level 1 | J67: =IFERROR(INDEX(Rates!$D$6:$D$15,MATCH(H67&"|"&I67,Rates!$C$6:$C$15,0)),0) -> 100 | K67: 5 | L67: =K67*J67 -> 500 | M67: AJAX cart and mini-cart customization add hours.
A68: 64 | C68: E-Commerce | D68: Checkout Flow | E68: 12 | F68: =IFERROR(INDEX(Categories!$B$5:$B$27,MATCH(E68,Categories!$A$5:$A$27,0)),"") -> E-Commerce | G68: Checkout page | H68: IT | I68: Level 2 | J68: =IFERROR(INDEX(Rates!$D$6:$D$15,MATCH(H68&"|"&I68,Rates!$C$6:$C$15,0)),0) -> 120 | K68: 8 | L68: =K68*J68 -> 960 | M68: One-page checkout, custom fields, and guest checkout rules all add time.
A69: 65 | C69: E-Commerce | D69: Shipping Rules | E69: 12 | F69: =IFERROR(INDEX(Categories!$B$5:$B$27,MATCH(E69,Categories!$A$5:$A$27,0)),"") -> E-Commerce | G69: Shipping setup | H69: IT | I69: Level 1 | J69: =IFERROR(INDEX(Rates!$D$6:$D$15,MATCH(H69&"|"&I69,Rates!$C$6:$C$15,0)),0) -> 100 | K69: 6 | L69: =K69*J69 -> 600 | M69: Live carrier rates (UPS/FedEx/USPS) are more work than flat-rate zones.
A70: 66 | C70: E-Commerce | D70: Payment Gateway Integration | E70: 12 | F70: =IFERROR(INDEX(Categories!$B$5:$B$27,MATCH(E70,Categories!$A$5:$A$27,0)),"") -> E-Commerce | G70: Stripe/PayPal | H70: IT | I70: Level 2 | J70: =IFERROR(INDEX(Rates!$D$6:$D$15,MATCH(H70&"|"&I70,Rates!$C$6:$C$15,0)),0) -> 120 | K70: 5 | L70: =K70*J70 -> 600 | M70: Excludes merchant account approval. Client delays here are common.
A71: 67 | C71: E-Commerce | D71: Tax Calculator | E71: 12 | F71: =IFERROR(INDEX(Categories!$B$5:$B$27,MATCH(E71,Categories!$A$5:$A$27,0)),"") -> E-Commerce | G71: Tax logic | H71: IT | I71: Level 1 | J71: =IFERROR(INDEX(Rates!$D$6:$D$15,MATCH(H71&"|"&I71,Rates!$C$6:$C$15,0)),0) -> 100 | K71: 4 | L71: =K71*J71 -> 400 | M71: Multi-state or international tax (Avalara/TaxJar) is a bigger scope.
A72: 68 | C72: E-Commerce | D72: Product Variations Bsic Set-up | E72: 12 | F72: =IFERROR(INDEX(Categories!$B$5:$B$27,MATCH(E72,Categories!$A$5:$A$27,0)),"") -> E-Commerce | G72: Configure product variations (size, color, attributes) using WooCommerce native options | H72: IT | I72: Level 1 | J72: =IFERROR(INDEX(Rates!$D$6:$D$15,MATCH(H72&"|"&I72,Rates!$C$6:$C$15,0)),0) -> 100 | K72: 3 | L72: =K72*J72 -> 300 | M72: Typo in name: 'Bsic' should be 'Basic'. This is setup only, not per-product entry.
A73: 69 | C73: E-Commerce | D73: Per product w/ variations | E73: 12 | F73: =IFERROR(INDEX(Categories!$B$5:$B$27,MATCH(E73,Categories!$A$5:$A$27,0)),"") -> E-Commerce | G73: Per product w/ variations, need to multiply how many products with variations | H73: Project Coordinator | I73: Level 1 | J73: =IFERROR(INDEX(Rates!$D$6:$D$15,MATCH(H73&"|"&I73,Rates!$C$6:$C$15,0)),0) -> 0 | K73: 0.5 | L73: =K73*J73 -> 0 | M73: Multiply by product count. Get the exact count from the client before quoting.
A74: 70 | C74: E-Commerce | D74: Advanced Product Options (Plugin) | E74: 12 | F74: =IFERROR(INDEX(Categories!$B$5:$B$27,MATCH(E74,Categories!$A$5:$A$27,0)),"") -> E-Commerce | G74: Add custom product fields/options using plugin (no custom build) | H74: IT | I74: Level 1 | J74: =IFERROR(INDEX(Rates!$D$6:$D$15,MATCH(H74&"|"&I74,Rates!$C$6:$C$15,0)),0) -> 100 | K74: 6 | L74: =K74*J74 -> 600 | M74: Excludes the plugin license cost.
A75: 71 | C75: E-Commerce | D75: Product Add-Ons (Conditional Logic) | E75: 12 | F75: =IFERROR(INDEX(Categories!$B$5:$B$27,MATCH(E75,Categories!$A$5:$A$27,0)),"") -> E-Commerce | G75: Product add-ons with conditional logic using plugin (e.g., extras, upgrades) | H75: IT | I75: Level 2 | J75: =IFERROR(INDEX(Rates!$D$6:$D$15,MATCH(H75&"|"&I75,Rates!$C$6:$C$15,0)),0) -> 120 | K75: 8 | L75: =K75*J75 -> 960 | M75: Rule count drives hours. Pricing logic errors are expensive, so add QA time.
A76: 72 | C76: E-Commerce | D76: Subscriptions Setup | E76: 12 | F76: =IFERROR(INDEX(Categories!$B$5:$B$27,MATCH(E76,Categories!$A$5:$A$27,0)),"") -> E-Commerce | G76: Setup recurring payments using WooCommerce Subscriptions plugin | H76: IT | I76: Level 2 | J76: =IFERROR(INDEX(Rates!$D$6:$D$15,MATCH(H76&"|"&I76,Rates!$C$6:$C$15,0)),0) -> 120 | K76: 6 | L76: =K76*J76 -> 720 | M76: Excludes plugin license. Failed-payment and renewal testing takes real time.
... A79: 75 | C79: E-Commerce | D79: Product Bundles / Packages | E79: 12 | F79: =IFERROR(INDEX(Categories!$B$5:$B$27,MATCH(E79,Categories!$A$5:$A$27,0)),"") -> E-Commerce | G79: Create bundled or grouped products using plugin | H79: IT | I79: Level 1 | J79: =IFERROR(INDEX(Rates!$D$6:$D$15,MATCH(H79&"|"&I79,Rates!$C$6:$C$15,0)),0) -> 100 | K79: 6 | L79: =K79*J79 -> 600 | M79: Excludes plugin license and per-bundle data entry.
A80: 76 | C80: E-Commerce | D80: Wishlist Functionality | E80: 12 | F80: =IFERROR(INDEX(Categories!$B$5:$B$27,MATCH(E80,Categories!$A$5:$A$27,0)),"") -> E-Commerce | G80: Add wishlist feature via plugin | H80: IT | I80: Level 1 | J80: =IFERROR(INDEX(Rates!$D$6:$D$15,MATCH(H80&"|"&I80,Rates!$C$6:$C$15,0)),0) -> 100 | K80: 4 | L80: =K80*J80 -> 400
A81: 77 | C81: E-Commerce | D81: Product Filtering (Advanced) | E81: 12 | F81: =IFERROR(INDEX(Categories!$B$5:$B$27,MATCH(E81,Categories!$A$5:$A$27,0)),"") -> E-Commerce | G81: Advanced filters (price, attributes, categories) using plugin | H81: IT | I81: Level 2 | J81: =IFERROR(INDEX(Rates!$D$6:$D$15,MATCH(H81&"|"&I81,Rates!$C$6:$C$15,0)),0) -> 120 | K81: 6 | L81: =K81*J81 -> 720 | M81: Large catalogs may need performance work on top of this.
A82: 78 | C82: Configurator – Basic 2D | D82: Color Change Feature | E82: 5 | F82: =IFERROR(INDEX(Categories!$B$5:$B$27,MATCH(E82,Categories!$A$5:$A$27,0)),"") -> Custom Tools | G82: Allow users to change product colors | H82: IT | I82: Level 2 | J82: =IFERROR(INDEX(Rates!$D$6:$D$15,MATCH(H82&"|"&I82,Rates!$C$6:$C$15,0)),0) -> 120 | K82: 15 | L82: =K82*J82 -> 1800 | M82: Asset preparation per color is separate. Confirm who supplies the assets.
A83: 79 | C83: Configurator – Basic 2D | D83: Shape Options | E83: 5 | F83: =IFERROR(INDEX(Categories!$B$5:$B$27,MATCH(E83,Categories!$A$5:$A$27,0)),"") -> Custom Tools | G83: Simple shape selection and preview | H83: IT | I83: Level 2 | J83: =IFERROR(INDEX(Rates!$D$6:$D$15,MATCH(H83&"|"&I83,Rates!$C$6:$C$15,0)),0) -> 120 | K83: 20 | L83: =K83*J83 -> 2400 | M83: Hours scale with the number of shapes.
A84: 80 | C84: Configurator – Basic 2D | D84: Static Preview Rendering | E84: 5 | F84: =IFERROR(INDEX(Categories!$B$5:$B$27,MATCH(E84,Categories!$A$5:$A$27,0)),"") -> Custom Tools | G84: Generate static preview images | H84: IT | I84: Level 2 | J84: =IFERROR(INDEX(Rates!$D$6:$D$15,MATCH(H84&"|"&I84,Rates!$C$6:$C$15,0)),0) -> 120 | K84: 30 | L84: =K84*J84 -> 3600 | M84: Server-side rendering has hosting and performance implications worth pricing in.
A85: 81 | C85: Configurator – Advanced 2D | D85: Pattern Library | E85: 5 | F85: =IFERROR(INDEX(Categories!$B$5:$B$27,MATCH(E85,Categories!$A$5:$A$27,0)),"") -> Custom Tools | G85: Apply patterns to product surfaces | H85: IT | I85: Level 2 | J85: =IFERROR(INDEX(Rates!$D$6:$D$15,MATCH(H85&"|"&I85,Rates!$C$6:$C$15,0)),0) -> 120 | K85: 30 | L85: =K85*J85 -> 3600 | M85: Pattern asset creation is Creative time and should be quoted separately.
A86: 82 | C86: Configurator – Advanced 2D | D86: Upload & Download Assets | E86: 5 | F86: =IFERROR(INDEX(Categories!$B$5:$B$27,MATCH(E86,Categories!$A$5:$A$27,0)),"") -> Custom Tools | G86: Allow users to upload images and download previews | H86: IT | I86: Level 2 | J86: =IFERROR(INDEX(Rates!$D$6:$D$15,MATCH(H86&"|"&I86,Rates!$C$6:$C$15,0)),0) -> 120 | K86: 30 | L86: =K86*J86 -> 3600 | M86: File validation, size limits, and storage costs all need to be defined.
A87: 83 | C87: Configurator – Advanced 2D | D87: Screenshot Capture | E87: 5 | F87: =IFERROR(INDEX(Categories!$B$5:$B$27,MATCH(E87,Categories!$A$5:$A$27,0)),"") -> Custom Tools | G87: Enable screenshot capture of designs | H87: IT | I87: Level 2 | J87: =IFERROR(INDEX(Rates!$D$6:$D$15,MATCH(H87&"|"&I87,Rates!$C$6:$C$15,0)),0) -> 120 | K87: 40 | L87: =K87*J87 -> 4800 | M87: Cross-browser behavior varies a lot here. Budget extra QA.
A88: 84 | C88: Configurator – 3D WebGL | D88: Camera Controls | E88: 5 | F88: =IFERROR(INDEX(Categories!$B$5:$B$27,MATCH(E88,Categories!$A$5:$A$27,0)),"") -> Custom Tools | G88: Interactive camera movement and zoom | H88: IT | I88: Level 2 | J88: =IFERROR(INDEX(Rates!$D$6:$D$15,MATCH(H88&"|"&I88,Rates!$C$6:$C$15,0)),0) -> 120 | K88: 40 | L88: =K88*J88 -> 4800 | M88: Mobile performance is the main risk on all WebGL work.
A89: 85 | C89: Configurator – 3D WebGL | D89: 3D Asset Integration | E89: 5 | F89: =IFERROR(INDEX(Categories!$B$5:$B$27,MATCH(E89,Categories!$A$5:$A$27,0)),"") -> Custom Tools | G89: Import and render 3D models | H89: IT | I89: Level 2 | J89: =IFERROR(INDEX(Rates!$D$6:$D$15,MATCH(H89&"|"&I89,Rates!$C$6:$C$15,0)),0) -> 120 | K89: 50 | L89: =K89*J89 -> 6000 | M89: Excludes 3D modeling itself. Confirm the client supplies optimized models.
A90: 86 | C90: Configurator – 3D WebGL | D90: Real-Time Rendering | E90: 5 | F90: =IFERROR(INDEX(Categories!$B$5:$B$27,MATCH(E90,Categories!$A$5:$A$27,0)),"") -> Custom Tools | G90: Real-time rendering of product visuals | H90: IT | I90: Level 2 | J90: =IFERROR(INDEX(Rates!$D$6:$D$15,MATCH(H90&"|"&I90,Rates!$C$6:$C$15,0)),0) -> 120 | K90: 55 | L90: =K90*J90 -> 6600 | M90: Highest technical risk item in the list. Consider a paid discovery phase first.
A91: 87 | C91: Configurator – Full Builder | D91: Court/Template Setup | E91: 5 | F91: =IFERROR(INDEX(Categories!$B$5:$B$27,MATCH(E91,Categories!$A$5:$A$27,0)),"") -> Custom Tools | G91: Custom templates for courts or products | H91: IT | I91: Level 2 | J91: =IFERROR(INDEX(Rates!$D$6:$D$15,MATCH(H91&"|"&I91,Rates!$C$6:$C$15,0)),0) -> 120 | K91: 80 | L91: =K91*J91 -> 9600 | M91: 80-hour items should be split into phases with milestone billing.
A92: 88 | C92: Configurator – Full Builder | D92: Measurement Tools | E92: 5 | F92: =IFERROR(INDEX(Categories!$B$5:$B$27,MATCH(E92,Categories!$A$5:$A$27,0)),"") -> Custom Tools | G92: Tools for measuring dimensions | H92: IT | I92: Level 2 | J92: =IFERROR(INDEX(Rates!$D$6:$D$15,MATCH(H92&"|"&I92,Rates!$C$6:$C$15,0)),0) -> 120 | K92: 80 | L92: =K92*J92 -> 9600 | M92: Unit conversion and accuracy requirements need to be written down.
... A96: 92 | C96: Configurator – Features | D96: Size Calculator | E96: 5 | F96: =IFERROR(INDEX(Categories!$B$5:$B$27,MATCH(E96,Categories!$A$5:$A$27,0)),"") -> Custom Tools | G96: Calculate product sizes dynamically | H96: IT | I96: Level 2 | J96: =IFERROR(INDEX(Rates!$D$6:$D$15,MATCH(H96&"|"&I96,Rates!$C$6:$C$15,0)),0) -> 120 | K96: 15 | L96: =K96*J96 -> 1800 | M96: Formula complexity comes from the client. Get it in writing first.
A97: 93 | C97: Configurator – Features | D97: Shareable Link | E97: 5 | F97: =IFERROR(INDEX(Categories!$B$5:$B$27,MATCH(E97,Categories!$A$5:$A$27,0)),"") -> Custom Tools | G97: Generate shareable links for designs | H97: IT | I97: Level 2 | J97: =IFERROR(INDEX(Rates!$D$6:$D$15,MATCH(H97&"|"&I97,Rates!$C$6:$C$15,0)),0) -> 120 | K97: 12 | L97: =K97*J97 -> 1440
A98: 94 | C98: Configurator – Features | D98: Admin Dashboard | E98: 5 | F98: =IFERROR(INDEX(Categories!$B$5:$B$27,MATCH(E98,Categories!$A$5:$A$27,0)),"") -> Custom Tools | G98: Admin dashboard for managing designs and users | H98: IT | I98: Level 2 | J98: =IFERROR(INDEX(Rates!$D$6:$D$15,MATCH(H98&"|"&I98,Rates!$C$6:$C$15,0)),0) -> 120 | K98: 44 | L98: =K98*J98 -> 5280 | M98: Reporting and export features can easily double this. Scope tightly.
A99: 95 | C99: Performance & Security | D99: SSL Configuration | E99: 18 | F99: =IFERROR(INDEX(Categories!$B$5:$B$27,MATCH(E99,Categories!$A$5:$A$27,0)),"") -> Performance & Security | G99: Setup SSL certificate | H99: IT | I99: Level 1 | J99: =IFERROR(INDEX(Rates!$D$6:$D$15,MATCH(H99&"|"&I99,Rates!$C$6:$C$15,0)),0) -> 100 | K99: 1 | L99: =K99*J99 -> 100 | M99: Assumes host provides free SSL. Custom or wildcard certs take longer.
A100: 96 | C100: Performance & Security | D100: Caching & Speed Optimization | E100: 18 | F100: =IFERROR(INDEX(Categories!$B$5:$B$27,MATCH(E100,Categories!$A$5:$A$27,0)),"") -> Performance & Security | G100: Basic performance optimization using caching, image compression, and plugin configuration (no advanced code-level optimization) | H100: IT | I100: Level 2 | J100: =IFERROR(INDEX(Rates!$D$6:$D$15,MATCH(H100&"|"&I100,Rates!$C$6:$C$15,0)),0) -> 120 | K100: 8 | L100: =K100*J100 -> 960 | M100: Excludes code-level fixes. Overlaps with task 111. Check you are not billing twice.
A101: 97 | C101: Performance & Security | D101: Backup & Versioning | E101: 18 | F101: =IFERROR(INDEX(Categories!$B$5:$B$27,MATCH(E101,Categories!$A$5:$A$27,0)),"") -> Performance & Security | G101: Setup backups and version control | H101: IT | I101: Level 1 | J101: =IFERROR(INDEX(Rates!$D$6:$D$15,MATCH(H101&"|"&I101,Rates!$C$6:$C$15,0)),0) -> 100 | K101: 2 | L101: =K101*J101 -> 200 | M101: This is setup only. Ongoing backup monitoring belongs in Maintenance & Support.
A102: 98 | C102: Analytics & Tracking | D102: GA4 Setup | E102: 4 | F102: =IFERROR(INDEX(Categories!$B$5:$B$27,MATCH(E102,Categories!$A$5:$A$27,0)),"") -> Conversion Tracking | G102: Configure Google Analytics 4 tracking | H102: IT | I102: Level 1 | J102: =IFERROR(INDEX(Rates!$D$6:$D$15,MATCH(H102&"|"&I102,Rates!$C$6:$C$15,0)),0) -> 100 | K102: 2 | L102: =K102*J102 -> 200 | M102: Assumes client already has a Google account. Access delays are common.
A103: 99 | C103: Analytics & Tracking | D103: GTM Setup | E103: 4 | F103: =IFERROR(INDEX(Categories!$B$5:$B$27,MATCH(E103,Categories!$A$5:$A$27,0)),"") -> Conversion Tracking | G103: Install and configure Google Tag Manager | H103: IT | I103: Level 1 | J103: =IFERROR(INDEX(Rates!$D$6:$D$15,MATCH(H103&"|"&I103,Rates!$C$6:$C$15,0)),0) -> 100 | K103: 3 | L103: =K103*J103 -> 300 | M103: Tag count drives hours. Note how many tags are included.
A104: 100 | C104: Analytics & Tracking | D104: Heatmaps | E104: 4 | F104: =IFERROR(INDEX(Categories!$B$5:$B$27,MATCH(E104,Categories!$A$5:$A$27,0)),"") -> Conversion Tracking | G104: Integrate heatmap tool for user behavior analysis | H104: IT | I104: Level 1 | J104: =IFERROR(INDEX(Rates!$D$6:$D$15,MATCH(H104&"|"&I104,Rates!$C$6:$C$15,0)),0) -> 100 | K104: 1 | L104: =K104*J104 -> 100 | M104: Excludes the heatmap tool subscription and any reporting/analysis.
A105: 101 | C105: Blog Setup | D105: Blog Listing Page | E105: 22 | F105: =IFERROR(INDEX(Categories!$B$5:$B$27,MATCH(E105,Categories!$A$5:$A$27,0)),"") -> SEO & Content | G105: Main blog page with article previews | H105: IT | I105: Level 1 | J105: =IFERROR(INDEX(Rates!$D$6:$D$15,MATCH(H105&"|"&I105,Rates!$C$6:$C$15,0)),0) -> 100 | K105: 2 | L105: =K105*J105 -> 200 | M105: Category filtering and pagination styling may add time.
A106: 102 | C106: Blog Setup | D106: Single Article Template | E106: 22 | F106: =IFERROR(INDEX(Categories!$B$5:$B$27,MATCH(E106,Categories!$A$5:$A$27,0)),"") -> SEO & Content | G106: Template for individual blog posts | H106: IT | I106: Level 1 | J106: =IFERROR(INDEX(Rates!$D$6:$D$15,MATCH(H106&"|"&I106,Rates!$C$6:$C$15,0)),0) -> 100 | K106: 2 | L106: =K106*J106 -> 200 | M106: Related posts, author boxes, and share buttons add time.
A107: 103 | C107: Blog Setup | D107: Lead Capture Integration | E107: 22 | F107: =IFERROR(INDEX(Categories!$B$5:$B$27,MATCH(E107,Categories!$A$5:$A$27,0)),"") -> SEO & Content | G107: Form for newsletter or lead capture | H107: IT | I107: Level 1 | J107: =IFERROR(INDEX(Rates!$D$6:$D$15,MATCH(H107&"|"&I107,Rates!$C$6:$C$15,0)),0) -> 100 | K107: 2 | L107: =K107*J107 -> 200 | M107: Email platform connection (Mailchimp etc.) may need integration hours.
A108: 104 | C108: SEO & Content | D108: SEO Tools Setup | E108: 22 | F108: =IFERROR(INDEX(Categories!$B$5:$B$27,MATCH(E108,Categories!$A$5:$A$27,0)),"") -> SEO & Content | G108: Install and configure SEO plugins/tools | H108: IT | I108: Level 1 | J108: =IFERROR(INDEX(Rates!$D$6:$D$15,MATCH(H108&"|"&I108,Rates!$C$6:$C$15,0)),0) -> 100 | K108: 3 | L108: =K108*J108 -> 300 | M108: Excludes keyword research and strategy, which are separate services.
A109: 105 | C109: SEO & Content | D109: Schema Markup | E109: 24 | F109: =IFERROR(INDEX(Categories!$B$5:$B$27,MATCH(E109,Categories!$A$5:$A$27,0)),"") -> SEO on-page | G109: Add structured data/schema for SEO | H109: IT | I109: Level 2 | J109: =IFERROR(INDEX(Rates!$D$6:$D$15,MATCH(H109&"|"&I109,Rates!$C$6:$C$15,0)),0) -> 120 | K109: 3 | L109: =K109*J109 -> 360 | M109: Per schema type. Product, LocalBusiness, and FAQ schema each take their own time.
A110: 106 | C110: SEO & Content | D110: Sitemap Generation | E110: 24 | F110: =IFERROR(INDEX(Categories!$B$5:$B$27,MATCH(E110,Categories!$A$5:$A$27,0)),"") -> SEO on-page | G110: Generate XML sitemap | H110: IT | I110: Level 1 | J110: =IFERROR(INDEX(Rates!$D$6:$D$15,MATCH(H110&"|"&I110,Rates!$C$6:$C$15,0)),0) -> 100 | K110: 1 | L110: =K110*J110 -> 100
A111: 107 | C111: SEO & Content | D111: Robots.txt Setup | E111: 24 | F111: =IFERROR(INDEX(Categories!$B$5:$B$27,MATCH(E111,Categories!$A$5:$A$27,0)),"") -> SEO on-page | G111: Configure robots.txt for crawling rules | H111: IT | I111: Level 1 | J111: =IFERROR(INDEX(Rates!$D$6:$D$15,MATCH(H111&"|"&I111,Rates!$C$6:$C$15,0)),0) -> 100 | K111: 1 | L111: =K111*J111 -> 100
A112: 108 | C112: SEO & Content | D112: Copywriting – Improve Existing Content | E112: 22 | F112: =IFERROR(INDEX(Categories!$B$5:$B$27,MATCH(E112,Categories!$A$5:$A$27,0)),"") -> SEO & Content | G112: Edit and optimize current content | H112: Creative | I112: Level 1 | J112: =IFERROR(INDEX(Rates!$D$6:$D$15,MATCH(H112&"|"&I112,Rates!$C$6:$C$15,0)),0) -> 100 | K112: 3 | L112: =K112*J112 -> 300 | M112: Per page. Define how many revision rounds are included.
A113: 109 | C113: SEO & Content | D113: Copywriting – New Content (per 800 words) | E113: 22 | F113: =IFERROR(INDEX(Categories!$B$5:$B$27,MATCH(E113,Categories!$A$5:$A$27,0)),"") -> SEO & Content | G113: Write new copy for a page (800 words) | H113: Creative | I113: Level 2 | J113: =IFERROR(INDEX(Rates!$D$6:$D$15,MATCH(H113&"|"&I113,Rates!$C$6:$C$15,0)),0) -> 130 | K113: 6 | L113: =K113*J113 -> 780 | M113: Per 800 words. Technical or highly specialized topics should bill higher.
A114: 110 | C114: SEO & Content | D114: Setup of URL redirects (301) | E114: 24 | F114: =IFERROR(INDEX(Categories!$B$5:$B$27,MATCH(E114,Categories!$A$5:$A$27,0)),"") -> SEO on-page | G114: Setup of URL redirects (301) to maintain SEO and handle URL changes | H114: IT | I114: Level 1 | J114: =IFERROR(INDEX(Rates!$D$6:$D$15,MATCH(H114&"|"&I114,Rates!$C$6:$C$15,0)),0) -> 100 | K114: 2 | L114: =K114*J114 -> 200 | M114: Assumes a modest redirect count. Large migrations need a mapping exercise first.
A115: 111 | C115: SEO & Content | D115: Performance Core Web Vitals Optimization | E115: 18 | F115: =IFERROR(INDEX(Categories!$B$5:$B$27,MATCH(E115,Categories!$A$5:$A$27,0)),"") -> Performance & Security | G115: Optimize site for LCP, CLS, and INP by improving loading speed, reducing layout shifts, optimizing assets, and ensuring smooth interactivity. | H115: IT | I115: Level 2 | J115: =IFERROR(INDEX(Rates!$D$6:$D$15,MATCH(H115&"|"&I115,Rates!$C$6:$C$15,0)),0) -> 120 | K115: 6 | L115: =K115*J115 -> 720 | M115: Overlaps with task 96. Results depend on hosting quality, so avoid guaranteeing a score.
A116: 112 | C116: Analytics & Tracking | D116: Moderate Conversion tracking | E116: 4 | F116: =IFERROR(INDEX(Categories!$B$5:$B$27,MATCH(E116,Categories!$A$5:$A$27,0)),"") -> Conversion Tracking | G116: Moderate (multiple events + testing + GA4 setup) Limit up to 8 events to configure and test. | H116: IT | I116: Level 2 | J116: =IFERROR(INDEX(Rates!$D$6:$D$15,MATCH(H116&"|"&I116,Rates!$C$6:$C$15,0)),0) -> 120 | K116: 8 | L116: =K116*J116 -> 960 | M116: Capped at 8 events. Price extra events individually.
A117: 113 | C117: Analytics & Tracking | D117: Basic conversion | E117: 4 | F117: =IFERROR(INDEX(Categories!$B$5:$B$27,MATCH(E117,Categories!$A$5:$A$27,0)),"") -> Conversion Tracking | G117: Basic conversion tracking for forms (submission events only, no advanced tracking) | H117: IT | I117: Level 1 | J117: =IFERROR(INDEX(Rates!$D$6:$D$15,MATCH(H117&"|"&I117,Rates!$C$6:$C$15,0)),0) -> 100 | K117: 6 | L117: =K117*J117 -> 600 | M117: Overlaps with task 112. These should be either/or, not both.
A118: 114 | C118: Environment Setup | D118: Hosting Setup & Configuration | E118: 13 | F118: =IFERROR(INDEX(Categories!$B$5:$B$27,MATCH(E118,Categories!$A$5:$A$27,0)),"") -> Environment Setup | G118: Provision and configure a WordPress-ready hosting environment, including server setup, PHP and MySQL configuration, and domain connection. Configure performance settings (caching, memory limits), implement security best practices (firewall, SSL readiness, access controls), and ensure the environment is optimized for reliability, speed, and scalability. | H118: IT | I118: Level 2 | J118: =IFERROR(INDEX(Rates!$D$6:$D$15,MATCH(H118&"|"&I118,Rates!$C$6:$C$15,0)),0) -> 120 | K118: 3 | L118: =K118*J118 -> 360 | M118: Excludes the hosting cost itself. Managed hosting is faster than a raw VPS.
A119: 115 | C119: Environment Setup | D119: WordPress Installation & Base Config | E119: 13 | F119: =IFERROR(INDEX(Categories!$B$5:$B$27,MATCH(E119,Categories!$A$5:$A$27,0)),"") -> Environment Setup | G119: Install WordPress, configure core settings (permalinks, timezone, security basics), and prepare a clean foundation. | H119: IT | I119: Level 1 | J119: =IFERROR(INDEX(Rates!$D$6:$D$15,MATCH(H119&"|"&I119,Rates!$C$6:$C$15,0)),0) -> 100 | K119: 2 | L119: =K119*J119 -> 200
A120: 116 | B120: 108: WordPress Installation | C120: Environment Setup | D120: Theme Setup (base theme / builder setup) | E120: 13 | F120: =IFERROR(INDEX(Categories!$B$5:$B$27,MATCH(E120,Categories!$A$5:$A$27,0)),"") -> Environment Setup | G120: Install and configure theme or page builder, including global styles, layout settings, and reusable components. | H120: IT | I120: Level 1 | J120: =IFERROR(INDEX(Rates!$D$6:$D$15,MATCH(H120&"|"&I120,Rates!$C$6:$C$15,0)),0) -> 100 | K120: 3 | L120: =K120*J120 -> 300 | M120: Dependency says '108' but WordPress Installation is task 115. Fix the reference.
...

Sheet Squarespace
A1: Task Pricing – Squarespace
A2: Base Hours unchanged. category_id has been remapped to the new Categories list.
A4: id | B4: Dependencies | C4: Module | D4: Name | E4: category_id | F4: Category | G4: Description | H4: Responsible | I4: Level | J4: Rate | K4: Base Hours | L4: Estimated Cost | M4: Hours – Things to Consider
A5: 1 | C5: Homepage – Standard | D5: Hero Section | E5: 14 | F5: =IFERROR(INDEX(Categories!$B$5:$B$27,MATCH(E5,Categories!$A$5:$A$27,0)),"") -> Frontend | G5: Hero section and headline | H5: IT | I5: Level 1 | J5: =IFERROR(INDEX(Rates!$D$6:$D$15,MATCH(H5&"|"&I5,Rates!$C$6:$C$15,0)),0) -> 100 | K5: 2 | L5: =K5*J5 -> 200
A6: 2 | C6: Homepage – Standard | D6: Services or Product Grid | E6: 14 | F6: =IFERROR(INDEX(Categories!$B$5:$B$27,MATCH(E6,Categories!$A$5:$A$27,0)),"") -> Frontend | G6: Grid layout using Squarespace sections or summary blocks | H6: IT | I6: Level 1 | J6: =IFERROR(INDEX(Rates!$D$6:$D$15,MATCH(H6&"|"&I6,Rates!$C$6:$C$15,0)),0) -> 100 | K6: 3 | L6: =K6*J6 -> 300 | M6: Assumes a fixed number of items. Dynamic, data-driven grids cost more.
A7: 3 | C7: Homepage – Standard | D7: Testimonials (Embed) | E7: 15 | F7: =IFERROR(INDEX(Categories!$B$5:$B$27,MATCH(E7,Categories!$A$5:$A$27,0)),"") -> Integration | G7: Testimonials via embed block or native content | H7: IT | I7: Level 1 | J7: =IFERROR(INDEX(Rates!$D$6:$D$15,MATCH(H7&"|"&I7,Rates!$C$6:$C$15,0)),0) -> 100 | K7: 3 | L7: =K7*J7 -> 300 | M7: Styling a third-party widget can take longer than expected if the platform limits CSS.
A8: 4 | C8: Homepage – Standard | D8: Team Preview | E8: 14 | F8: =IFERROR(INDEX(Categories!$B$5:$B$27,MATCH(E8,Categories!$A$5:$A$27,0)),"") -> Frontend | G8: Team member section using image + text blocks | H8: IT | I8: Level 1 | J8: =IFERROR(INDEX(Rates!$D$6:$D$15,MATCH(H8&"|"&I8,Rates!$C$6:$C$15,0)),0) -> 100 | K8: 1.5 | L8: =K8*J8 -> 150 | M8: Bios and photo cropping are content work, not build work.
A9: 5 | C9: Homepage – Standard | D9: Footer Layout | E9: 14 | F9: =IFERROR(INDEX(Categories!$B$5:$B$27,MATCH(E9,Categories!$A$5:$A$27,0)),"") -> Frontend | G9: Footer navigation, contact, social links | H9: IT | I9: Level 1 | J9: =IFERROR(INDEX(Rates!$D$6:$D$15,MATCH(H9&"|"&I9,Rates!$C$6:$C$15,0)),0) -> 100 | K9: 1.5 | L9: =K9*J9 -> 150 | M9: Mega-footers with multiple menus and a newsletter form run higher.
A10: 6 | C10: Homepage – Conversion | D10: Strong Hero Offer | E10: 14 | F10: =IFERROR(INDEX(Categories!$B$5:$B$27,MATCH(E10,Categories!$A$5:$A$27,0)),"") -> Frontend | G10: Hero with CTA using Squarespace buttons | H10: IT | I10: Level 1 | J10: =IFERROR(INDEX(Rates!$D$6:$D$15,MATCH(H10&"|"&I10,Rates!$C$6:$C$15,0)),0) -> 100 | K10: 4 | L10: =K10*J10 -> 400
A11: 7 | C11: Homepage – Conversion | D11: Benefits/Features | E11: 14 | F11: =IFERROR(INDEX(Categories!$B$5:$B$27,MATCH(E11,Categories!$A$5:$A$27,0)),"") -> Frontend | G11: Feature sections using layout blocks | H11: IT | I11: Level 1 | J11: =IFERROR(INDEX(Rates!$D$6:$D$15,MATCH(H11&"|"&I11,Rates!$C$6:$C$15,0)),0) -> 100 | K11: 3 | L11: =K11*J11 -> 300 | M11: Icon sourcing or custom icons may need Creative hours on top.
A12: 8 | C12: Homepage – Conversion | D12: Social Proof / Trust Badges | E12: 14 | F12: =IFERROR(INDEX(Categories!$B$5:$B$27,MATCH(E12,Categories!$A$5:$A$27,0)),"") -> Frontend | G12: Logos or badges using image blocks | H12: IT | I12: Level 1 | J12: =IFERROR(INDEX(Rates!$D$6:$D$15,MATCH(H12&"|"&I12,Rates!$C$6:$C$15,0)),0) -> 100 | K12: 2 | L12: =K12*J12 -> 200 | M12: Assumes client supplies logos in usable formats. Logo cleanup is Creative time.
A13: 9 | C13: Homepage – Conversion | D13: FAQ Section | E13: 14 | F13: =IFERROR(INDEX(Categories!$B$5:$B$27,MATCH(E13,Categories!$A$5:$A$27,0)),"") -> Frontend | G13: Collapsible FAQ blocks | H13: IT | I13: Level 1 | J13: =IFERROR(INDEX(Rates!$D$6:$D$15,MATCH(H13&"|"&I13,Rates!$C$6:$C$15,0)),0) -> 100 | K13: 2 | L13: =K13*J13 -> 200 | M13: Add a little time if FAQ schema markup is also required.
A14: 10 | C14: Homepage – Standard | D14: Pricing Tables | E14: 14 | F14: =IFERROR(INDEX(Categories!$B$5:$B$27,MATCH(E14,Categories!$A$5:$A$27,0)),"") -> Frontend | G14: Pricing using columns/layout blocks | H14: IT | I14: Level 1 | J14: =IFERROR(INDEX(Rates!$D$6:$D$15,MATCH(H14&"|"&I14,Rates!$C$6:$C$15,0)),0) -> 100 | K14: 4 | L14: =K14*J14 -> 400 | M14: No native pricing table. Built manually, so more than 3 plans adds time.
A15: 11 | C15: Homepage – Standard | D15: Galleries | E15: 14 | F15: =IFERROR(INDEX(Categories!$B$5:$B$27,MATCH(E15,Categories!$A$5:$A$27,0)),"") -> Frontend | G15: Gallery block (grid/slider/lightbox) | H15: IT | I15: Level 1 | J15: =IFERROR(INDEX(Rates!$D$6:$D$15,MATCH(H15&"|"&I15,Rates!$C$6:$C$15,0)),0) -> 100 | K15: 2 | L15: =K15*J15 -> 200 | M15: Per gallery. Image prep is billed separately.
A16: 12 | C16: Homepage – Standard | D16: Video Embeds | E16: 14 | F16: =IFERROR(INDEX(Categories!$B$5:$B$27,MATCH(E16,Categories!$A$5:$A$27,0)),"") -> Frontend | G16: Video block (YouTube/Vimeo) | H16: IT | I16: Level 1 | J16: =IFERROR(INDEX(Rates!$D$6:$D$15,MATCH(H16&"|"&I16,Rates!$C$6:$C$15,0)),0) -> 100 | K16: 1 | L16: =K16*J16 -> 100 | M16: Self-hosted video or custom players are a different, larger scope.
A17: 13 | C17: Homepage – Standard | D17: Donations / Payments | E17: 15 | F17: =IFERROR(INDEX(Categories!$B$5:$B$27,MATCH(E17,Categories!$A$5:$A$27,0)),"") -> Integration | G17: Squarespace Payments or Stripe integration | H17: IT | I17: Level 1 | J17: =IFERROR(INDEX(Rates!$D$6:$D$15,MATCH(H17&"|"&I17,Rates!$C$6:$C$15,0)),0) -> 100 | K17: 4 | L17: =K17*J17 -> 400 | M17: Excludes merchant account approval. Client delays here are common.
A18: 14 | C18: Homepage – Standard | D18: Use Cases | E18: 14 | F18: =IFERROR(INDEX(Categories!$B$5:$B$27,MATCH(E18,Categories!$A$5:$A$27,0)),"") -> Frontend | G18: Content sections for use cases | H18: IT | I18: Level 1 | J18: =IFERROR(INDEX(Rates!$D$6:$D$15,MATCH(H18&"|"&I18,Rates!$C$6:$C$15,0)),0) -> 100 | K18: 2 | L18: =K18*J18 -> 200
A19: 15 | C19: Homepage – Standard | D19: Forms Spam Protection | E19: 18 | F19: =IFERROR(INDEX(Categories!$B$5:$B$27,MATCH(E19,Categories!$A$5:$A$27,0)),"") -> Performance & Security | G19: Basic spam protection (Squarespace built-in) | H19: IT | I19: Level 1 | J19: =IFERROR(INDEX(Rates!$D$6:$D$15,MATCH(H19&"|"&I19,Rates!$C$6:$C$15,0)),0) -> 100 | K19: 1 | L19: =K19*J19 -> 100 | M19: Built-in only. You have far less control than on WordPress.
A20: 16 | C20: Homepage – Creative | D20: Full-Screen Visuals | E20: 14 | F20: =IFERROR(INDEX(Categories!$B$5:$B$27,MATCH(E20,Categories!$A$5:$A$27,0)),"") -> Frontend | G20: Full-width image sections | H20: Creative | I20: Level 1 | J20: =IFERROR(INDEX(Rates!$D$6:$D$15,MATCH(H20&"|"&I20,Rates!$C$6:$C$15,0)),0) -> 100 | K20: 6 | L20: =K20*J20 -> 600 | M20: Image sourcing, licensing, and retouching may be billed separately.
A21: 17 | C21: Homepage – Creative | D21: Parallax Effects | E21: 14 | F21: =IFERROR(INDEX(Categories!$B$5:$B$27,MATCH(E21,Categories!$A$5:$A$27,0)),"") -> Frontend | G21: Built-in scroll effects (limited vs WP) | H21: IT | I21: Level 2 | J21: =IFERROR(INDEX(Rates!$D$6:$D$15,MATCH(H21&"|"&I21,Rates!$C$6:$C$15,0)),0) -> 120 | K21: 3 | L21: =K21*J21 -> 360 | M21: Native effects only. Custom parallax needs code injection and a Business plan.
A22: 18 | C22: Homepage – Creative | D22: Hover Animations | E22: 14 | F22: =IFERROR(INDEX(Categories!$B$5:$B$27,MATCH(E22,Categories!$A$5:$A$27,0)),"") -> Frontend | G22: Basic hover effects (native styles) | H22: IT | I22: Level 1 | J22: =IFERROR(INDEX(Rates!$D$6:$D$15,MATCH(H22&"|"&I22,Rates!$C$6:$C$15,0)),0) -> 100 | K22: 2 | L22: =K22*J22 -> 200 | M22: Needs a touch-device fallback, which is easy to forget in the estimate.
A23: 19 | C23: Homepage – Creative | D23: Creative Layouts | E23: 14 | F23: =IFERROR(INDEX(Categories!$B$5:$B$27,MATCH(E23,Categories!$A$5:$A$27,0)),"") -> Frontend | G23: Custom section layouts using fluid engine | H23: IT | I23: Level 1 | J23: =IFERROR(INDEX(Rates!$D$6:$D$15,MATCH(H23&"|"&I23,Rates!$C$6:$C$15,0)),0) -> 100 | K23: 4 | L23: =K23*J23 -> 400 | M23: Fluid Engine desktop and mobile layouts are built separately.
A24: 20 | C24: Homepage – Creative | D24: Portfolio Preview | E24: 14 | F24: =IFERROR(INDEX(Categories!$B$5:$B$27,MATCH(E24,Categories!$A$5:$A$27,0)),"") -> Frontend | G24: Portfolio/gallery collection preview | H24: IT | I24: Level 1 | J24: =IFERROR(INDEX(Rates!$D$6:$D$15,MATCH(H24&"|"&I24,Rates!$C$6:$C$15,0)),0) -> 100 | K24: 4 | L24: =K24*J24 -> 400 | M24: Filtering by category adds hours.
A25: 21 | C25: Homepage – Conversion | D25: Lead Capture Form | E25: 14 | F25: =IFERROR(INDEX(Categories!$B$5:$B$27,MATCH(E25,Categories!$A$5:$A$27,0)),"") -> Frontend | G25: Squarespace form block | H25: IT | I25: Level 1 | J25: =IFERROR(INDEX(Rates!$D$6:$D$15,MATCH(H25&"|"&I25,Rates!$C$6:$C$15,0)),0) -> 100 | K25: 2 | L25: =K25*J25 -> 200 | M25: CRM connection is billed separately.
A26: 22 | C26: Integrations | D26: Live Chat Integration | E26: 15 | F26: =IFERROR(INDEX(Categories!$B$5:$B$27,MATCH(E26,Categories!$A$5:$A$27,0)),"") -> Integration | G26: Embed third-party chat (Intercom, etc.) | H26: IT | I26: Level 1 | J26: =IFERROR(INDEX(Rates!$D$6:$D$15,MATCH(H26&"|"&I26,Rates!$C$6:$C$15,0)),0) -> 100 | K26: 2 | L26: =K26*J26 -> 200 | M26: Requires a Business plan for code injection.
A27: 23 | C27: Integrations | D27: Appointment Scheduling | E27: 15 | F27: =IFERROR(INDEX(Categories!$B$5:$B$27,MATCH(E27,Categories!$A$5:$A$27,0)),"") -> Integration | G27: Squarespace Scheduling or embed tool | H27: IT | I27: Level 1 | J27: =IFERROR(INDEX(Rates!$D$6:$D$15,MATCH(H27&"|"&I27,Rates!$C$6:$C$15,0)),0) -> 100 | K27: 3 | L27: =K27*J27 -> 300 | M27: Excludes the Acuity subscription and entering services or availability.
A28: 24 | C28: Integrations | D28: Zapier Workflows | E28: 15 | F28: =IFERROR(INDEX(Categories!$B$5:$B$27,MATCH(E28,Categories!$A$5:$A$27,0)),"") -> Integration | G28: Zapier connection via form/email triggers | H28: IT | I28: Level 1 | J28: =IFERROR(INDEX(Rates!$D$6:$D$15,MATCH(H28&"|"&I28,Rates!$C$6:$C$15,0)),0) -> 100 | K28: 4 | L28: =K28*J28 -> 400 | M28: Note how many Zaps are included. Excludes the Zapier subscription.
A29: 25 | C29: Integrations | D29: Basic API / Embed Integration | E29: 15 | F29: =IFERROR(INDEX(Categories!$B$5:$B$27,MATCH(E29,Categories!$A$5:$A$27,0)),"") -> Integration | G29: Embed external tools via code block | H29: IT | I29: Level 2 | J29: =IFERROR(INDEX(Rates!$D$6:$D$15,MATCH(H29&"|"&I29,Rates!$C$6:$C$15,0)),0) -> 120 | K29: 6 | L29: =K29*J29 -> 720 | M29: Requires a Business plan for code injection.
A30: 26 | C30: Core Page - Standard | D30: Standard Page (About, Services) | E30: 14 | F30: =IFERROR(INDEX(Categories!$B$5:$B$27,MATCH(E30,Categories!$A$5:$A$27,0)),"") -> Frontend | G30: Basic pages using sections | H30: IT | I30: Level 1 | J30: =IFERROR(INDEX(Rates!$D$6:$D$15,MATCH(H30&"|"&I30,Rates!$C$6:$C$15,0)),0) -> 100 | K30: 6 | L30: =K30*J30 -> 600 | M30: Per page. Multiply by page count and confirm the total in the quote.
... A32: 28 | C32: Core Page - Contact Page | D32: Contact Page | E32: 14 | F32: =IFERROR(INDEX(Categories!$B$5:$B$27,MATCH(E32,Categories!$A$5:$A$27,0)),"") -> Frontend | G32: Form + contact info layout | H32: IT | I32: Level 1 | J32: =IFERROR(INDEX(Rates!$D$6:$D$15,MATCH(H32&"|"&I32,Rates!$C$6:$C$15,0)),0) -> 100 | K32: 5 | L32: =K32*J32 -> 500 | M32: Includes one form. Map embed and multi-location info may add time.
A33: 29 | C33: Core Page - Detail Page | D33: Blog/Service Detail | E33: 14 | F33: =IFERROR(INDEX(Categories!$B$5:$B$27,MATCH(E33,Categories!$A$5:$A$27,0)),"") -> Frontend | G33: Blog or collection item template | H33: IT | I33: Level 1 | J33: =IFERROR(INDEX(Rates!$D$6:$D$15,MATCH(H33&"|"&I33,Rates!$C$6:$C$15,0)),0) -> 100 | K33: 5 | L33: =K33*J33 -> 500
A34: 30 | C34: Forms – Standard | D34: Standard Form Setup | E34: 14 | F34: =IFERROR(INDEX(Categories!$B$5:$B$27,MATCH(E34,Categories!$A$5:$A$27,0)),"") -> Frontend | G34: Form with fields + email notifications | H34: IT | I34: Level 1 | J34: =IFERROR(INDEX(Rates!$D$6:$D$15,MATCH(H34&"|"&I34,Rates!$C$6:$C$15,0)),0) -> 100 | K34: 2 | L34: =K34*J34 -> 200 | M34: Priced per form. Confirm the form count before quoting.
A35: 31 | C35: Forms – Advanced | D35: Storage & Notifications | E35: 14 | F35: =IFERROR(INDEX(Categories!$B$5:$B$27,MATCH(E35,Categories!$A$5:$A$27,0)),"") -> Frontend | G35: Form submissions stored + email | H35: IT | I35: Level 1 | J35: =IFERROR(INDEX(Rates!$D$6:$D$15,MATCH(H35&"|"&I35,Rates!$C$6:$C$15,0)),0) -> 100 | K35: 2 | L35: =K35*J35 -> 200
A36: 32 | C36: Members Area | D36: Members Area Setup | E36: 2 | F36: =IFERROR(INDEX(Categories!$B$5:$B$27,MATCH(E36,Categories!$A$5:$A$27,0)),"") -> Backend | G36: Squarespace Member Areas setup | H36: IT | I36: Level 1 | J36: =IFERROR(INDEX(Rates!$D$6:$D$15,MATCH(H36&"|"&I36,Rates!$C$6:$C$15,0)),0) -> 100 | K36: 6 | L36: =K36*J36 -> 600 | M36: Requires the paid Member Areas add-on.
A37: 33 | C37: Members Area | D37: Basic Access Control | E37: 2 | F37: =IFERROR(INDEX(Categories!$B$5:$B$27,MATCH(E37,Categories!$A$5:$A$27,0)),"") -> Backend | G37: Restrict pages/content | H37: IT | I37: Level 1 | J37: =IFERROR(INDEX(Rates!$D$6:$D$15,MATCH(H37&"|"&I37,Rates!$C$6:$C$15,0)),0) -> 100 | K37: 4 | L37: =K37*J37 -> 400 | M37: Far less flexible than WordPress roles. Set expectations.
A38: 34 | C38: E-Commerce | D38: Product Listings | E38: 12 | F38: =IFERROR(INDEX(Categories!$B$5:$B$27,MATCH(E38,Categories!$A$5:$A$27,0)),"") -> E-Commerce | G38: Product collection setup | H38: IT | I38: Level 1 | J38: =IFERROR(INDEX(Rates!$D$6:$D$15,MATCH(H38&"|"&I38,Rates!$C$6:$C$15,0)),0) -> 100 | K38: 5 | L38: =K38*J38 -> 500 | M38: Setup only. Per-product data entry is separate and often underestimated.
A39: 35 | C39: E-Commerce | D39: Product Detail Page | E39: 12 | F39: =IFERROR(INDEX(Categories!$B$5:$B$27,MATCH(E39,Categories!$A$5:$A$27,0)),"") -> E-Commerce | G39: Product page layout | H39: IT | I39: Level 1 | J39: =IFERROR(INDEX(Rates!$D$6:$D$15,MATCH(H39&"|"&I39,Rates!$C$6:$C$15,0)),0) -> 100 | K39: 5 | L39: =K39*J39 -> 500
A40: 36 | C40: E-Commerce | D40: Cart Functionality | E40: 12 | F40: =IFERROR(INDEX(Categories!$B$5:$B$27,MATCH(E40,Categories!$A$5:$A$27,0)),"") -> E-Commerce | G40: Built-in cart | H40: IT | I40: Level 1 | J40: =IFERROR(INDEX(Rates!$D$6:$D$15,MATCH(H40&"|"&I40,Rates!$C$6:$C$15,0)),0) -> 100 | K40: 3 | L40: =K40*J40 -> 300 | M40: Mini-cart and AJAX cart customization add hours.
A41: 37 | C41: E-Commerce | D41: Checkout Flow | E41: 12 | F41: =IFERROR(INDEX(Categories!$B$5:$B$27,MATCH(E41,Categories!$A$5:$A$27,0)),"") -> E-Commerce | G41: Native checkout | H41: IT | I41: Level 1 | J41: =IFERROR(INDEX(Rates!$D$6:$D$15,MATCH(H41&"|"&I41,Rates!$C$6:$C$15,0)),0) -> 100 | K41: 4 | L41: =K41*J41 -> 400 | M41: Native checkout is largely locked. Limited custom fields.
A42: 38 | C42: E-Commerce | D42: Payments Setup | E42: 12 | F42: =IFERROR(INDEX(Categories!$B$5:$B$27,MATCH(E42,Categories!$A$5:$A$27,0)),"") -> E-Commerce | G42: Stripe/PayPal via Squarespace | H42: IT | I42: Level 1 | J42: =IFERROR(INDEX(Rates!$D$6:$D$15,MATCH(H42&"|"&I42,Rates!$C$6:$C$15,0)),0) -> 100 | K42: 3 | L42: =K42*J42 -> 300 | M42: Excludes merchant account approval. Client delays are common.
A43: 39 | C43: E-Commerce | D43: Shipping Setup | E43: 12 | F43: =IFERROR(INDEX(Categories!$B$5:$B$27,MATCH(E43,Categories!$A$5:$A$27,0)),"") -> E-Commerce | G43: Shipping rules config | H43: IT | I43: Level 1 | J43: =IFERROR(INDEX(Rates!$D$6:$D$15,MATCH(H43&"|"&I43,Rates!$C$6:$C$15,0)),0) -> 100 | K43: 4 | L43: =K43*J43 -> 400 | M43: Live carrier rates are more work than flat-rate zones.
A44: 40 | C44: E-Commerce | D44: Tax Setup | E44: 12 | F44: =IFERROR(INDEX(Categories!$B$5:$B$27,MATCH(E44,Categories!$A$5:$A$27,0)),"") -> E-Commerce | G44: Tax configuration | H44: IT | I44: Level 1 | J44: =IFERROR(INDEX(Rates!$D$6:$D$15,MATCH(H44&"|"&I44,Rates!$C$6:$C$15,0)),0) -> 100 | K44: 3 | L44: =K44*J44 -> 300 | M44: Multi-state or international tax is a bigger scope.
A45: 41 | C45: E-Commerce | D45: Featured Products Section | E45: 12 | F45: =IFERROR(INDEX(Categories!$B$5:$B$27,MATCH(E45,Categories!$A$5:$A$27,0)),"") -> E-Commerce | G45: Product blocks on homepage | H45: IT | I45: Level 1 | J45: =IFERROR(INDEX(Rates!$D$6:$D$15,MATCH(H45&"|"&I45,Rates!$C$6:$C$15,0)),0) -> 100 | K45: 4 | L45: =K45*J45 -> 400
A46: 42 | C46: E-Commerce | D46: Promotional Banners | E46: 12 | F46: =IFERROR(INDEX(Categories!$B$5:$B$27,MATCH(E46,Categories!$A$5:$A$27,0)),"") -> E-Commerce | G46: Sales banners using sections | H46: Creative | I46: Level 1 | J46: =IFERROR(INDEX(Rates!$D$6:$D$15,MATCH(H46&"|"&I46,Rates!$C$6:$C$15,0)),0) -> 100 | K46: 3 | L46: =K46*J46 -> 300 | M46: Recurring campaign artwork is worth a separate maintenance line item.
A47: 43 | C47: E-Commerce | D47: Category Navigation | E47: 12 | F47: =IFERROR(INDEX(Categories!$B$5:$B$27,MATCH(E47,Categories!$A$5:$A$27,0)),"") -> E-Commerce | G47: Product category organization | H47: IT | I47: Level 1 | J47: =IFERROR(INDEX(Rates!$D$6:$D$15,MATCH(H47&"|"&I47,Rates!$C$6:$C$15,0)),0) -> 100 | K47: 4 | L47: =K47*J47 -> 400
A48: 44 | C48: E-Commerce | D48: Customer Reviews (Basic) | E48: 12 | F48: =IFERROR(INDEX(Categories!$B$5:$B$27,MATCH(E48,Categories!$A$5:$A$27,0)),"") -> E-Commerce | G48: Manual or embed-based reviews | H48: IT | I48: Level 1 | J48: =IFERROR(INDEX(Rates!$D$6:$D$15,MATCH(H48&"|"&I48,Rates!$C$6:$C$15,0)),0) -> 100 | K48: 3 | L48: =K48*J48 -> 300 | M48: Importing existing reviews would be extra.
A49: 45 | C49: Analytics & Tracking | D49: GA4 Setup | E49: 4 | F49: =IFERROR(INDEX(Categories!$B$5:$B$27,MATCH(E49,Categories!$A$5:$A$27,0)),"") -> Conversion Tracking | G49: Google Analytics integration | H49: IT | I49: Level 1 | J49: =IFERROR(INDEX(Rates!$D$6:$D$15,MATCH(H49&"|"&I49,Rates!$C$6:$C$15,0)),0) -> 100 | K49: 2 | L49: =K49*J49 -> 200 | M49: Assumes client already has a Google account. Access delays are common.
A50: 46 | C50: Analytics & Tracking | D50: GTM Setup | E50: 4 | F50: =IFERROR(INDEX(Categories!$B$5:$B$27,MATCH(E50,Categories!$A$5:$A$27,0)),"") -> Conversion Tracking | G50: Tag Manager install | H50: IT | I50: Level 1 | J50: =IFERROR(INDEX(Rates!$D$6:$D$15,MATCH(H50&"|"&I50,Rates!$C$6:$C$15,0)),0) -> 100 | K50: 3 | L50: =K50*J50 -> 300 | M50: Requires a Business plan for code injection.
A51: 47 | C51: Analytics & Tracking | D51: Basic Conversion Tracking | E51: 4 | F51: =IFERROR(INDEX(Categories!$B$5:$B$27,MATCH(E51,Categories!$A$5:$A$27,0)),"") -> Conversion Tracking | G51: Form + button tracking | H51: IT | I51: Level 1 | J51: =IFERROR(INDEX(Rates!$D$6:$D$15,MATCH(H51&"|"&I51,Rates!$C$6:$C$15,0)),0) -> 100 | K51: 4 | L51: =K51*J51 -> 400 | M51: Event tracking is harder here than on WordPress. This may be thin.
A52: 48 | C52: Analytics & Tracking | D52: Heatmaps | E52: 4 | F52: =IFERROR(INDEX(Categories!$B$5:$B$27,MATCH(E52,Categories!$A$5:$A$27,0)),"") -> Conversion Tracking | G52: Hotjar or similar via embed | H52: IT | I52: Level 1 | J52: =IFERROR(INDEX(Rates!$D$6:$D$15,MATCH(H52&"|"&I52,Rates!$C$6:$C$15,0)),0) -> 100 | K52: 1 | L52: =K52*J52 -> 100 | M52: Excludes the heatmap tool subscription and any reporting or analysis.
A53: 49 | C53: Blog Setup | D53: Blog Page Setup | E53: 22 | F53: =IFERROR(INDEX(Categories!$B$5:$B$27,MATCH(E53,Categories!$A$5:$A$27,0)),"") -> SEO & Content | G53: Blog index page | H53: IT | I53: Level 1 | J53: =IFERROR(INDEX(Rates!$D$6:$D$15,MATCH(H53&"|"&I53,Rates!$C$6:$C$15,0)),0) -> 100 | K53: 2 | L53: =K53*J53 -> 200 | M53: Category filtering and pagination styling may add time.
A54: 50 | C54: Blog Setup | D54: Blog Post Template | E54: 22 | F54: =IFERROR(INDEX(Categories!$B$5:$B$27,MATCH(E54,Categories!$A$5:$A$27,0)),"") -> SEO & Content | G54: Default post layout | H54: IT | I54: Level 1 | J54: =IFERROR(INDEX(Rates!$D$6:$D$15,MATCH(H54&"|"&I54,Rates!$C$6:$C$15,0)),0) -> 100 | K54: 2 | L54: =K54*J54 -> 200 | M54: Related posts, author boxes, and share buttons add time.
A55: 51 | C55: Blog Setup | D55: Blog Lead Capture | E55: 22 | F55: =IFERROR(INDEX(Categories!$B$5:$B$27,MATCH(E55,Categories!$A$5:$A$27,0)),"") -> SEO & Content | G55: Newsletter form | H55: IT | I55: Level 1 | J55: =IFERROR(INDEX(Rates!$D$6:$D$15,MATCH(H55&"|"&I55,Rates!$C$6:$C$15,0)),0) -> 100 | K55: 2 | L55: =K55*J55 -> 200 | M55: Email platform connection (Mailchimp etc.) may need integration hours.
A56: 52 | C56: SEO & Content | D56: On-Page SEO Setup | E56: 24 | F56: =IFERROR(INDEX(Categories!$B$5:$B$27,MATCH(E56,Categories!$A$5:$A$27,0)),"") -> SEO on-page | G56: Titles, meta, descriptions | H56: IT | I56: Level 1 | J56: =IFERROR(INDEX(Rates!$D$6:$D$15,MATCH(H56&"|"&I56,Rates!$C$6:$C$15,0)),0) -> 100 | K56: 3 | L56: =K56*J56 -> 300 | M56: Per page or per batch. Define how many pages are covered.
A57: 53 | C57: SEO & Content | D57: Sitemap (Auto) | E57: 24 | F57: =IFERROR(INDEX(Categories!$B$5:$B$27,MATCH(E57,Categories!$A$5:$A$27,0)),"") -> SEO on-page | G57: Auto-generated by Squarespace | H57: IT | I57: Level 1 | J57: =IFERROR(INDEX(Rates!$D$6:$D$15,MATCH(H57&"|"&I57,Rates!$C$6:$C$15,0)),0) -> 100 | K57: 0 | L57: =K57*J57 -> 0 | M57: Zero hours. Keep it as an 'included free' talking point or delete the row.
A58: 54 | C58: SEO & Content | D58: Robots.txt (Basic) | E58: 24 | F58: =IFERROR(INDEX(Categories!$B$5:$B$27,MATCH(E58,Categories!$A$5:$A$27,0)),"") -> SEO on-page | G58: Limited configuration | H58: IT | I58: Level 1 | J58: =IFERROR(INDEX(Rates!$D$6:$D$15,MATCH(H58&"|"&I58,Rates!$C$6:$C$15,0)),0) -> 100 | K58: 1 | L58: =K58*J58 -> 100 | M58: Squarespace barely allows edits here. Set client expectations.
A59: 55 | C59: SEO & Content | D59: URL Redirects | E59: 24 | F59: =IFERROR(INDEX(Categories!$B$5:$B$27,MATCH(E59,Categories!$A$5:$A$27,0)),"") -> SEO on-page | G59: Built-in redirect manager | H59: IT | I59: Level 1 | J59: =IFERROR(INDEX(Rates!$D$6:$D$15,MATCH(H59&"|"&I59,Rates!$C$6:$C$15,0)),0) -> 100 | K59: 2 | L59: =K59*J59 -> 200 | M59: Large migrations need a URL mapping exercise first.
... A64: 60 | C64: Environment Setup | D64: Squarespace Site Setup | E64: 13 | F64: =IFERROR(INDEX(Categories!$B$5:$B$27,MATCH(E64,Categories!$A$5:$A$27,0)),"") -> Environment Setup | G64: Create site, basic config | H64: IT | I64: Level 1 | J64: =IFERROR(INDEX(Rates!$D$6:$D$15,MATCH(H64&"|"&I64,Rates!$C$6:$C$15,0)),0) -> 100 | K64: 2 | L64: =K64*J64 -> 200 | M64: Excludes the Squarespace subscription.
A65: 61 | C65: Environment Setup | D65: Template & Styles Setup | E65: 13 | F65: =IFERROR(INDEX(Categories!$B$5:$B$27,MATCH(E65,Categories!$A$5:$A$27,0)),"") -> Environment Setup | G65: Fonts, colors, global styles | H65: IT | I65: Level 1 | J65: =IFERROR(INDEX(Rates!$D$6:$D$15,MATCH(H65&"|"&I65,Rates!$C$6:$C$15,0)),0) -> 100 | K65: 3 | L65: =K65*J65 -> 300
A66: 62 | C66: Environment Setup | D66: Domain Connection | E66: 13 | F66: =IFERROR(INDEX(Categories!$B$5:$B$27,MATCH(E66,Categories!$A$5:$A$27,0)),"") -> Environment Setup | G66: Connect domain | H66: IT | I66: Level 1 | J66: =IFERROR(INDEX(Rates!$D$6:$D$15,MATCH(H66&"|"&I66,Rates!$C$6:$C$15,0)),0) -> 100 | K66: 2 | L66: =K66*J66 -> 200 | M66: DNS propagation affects the schedule but is not billable work.
A67: 63 | C67: Deployment | D67: Content Migration (Manual) | E67: 6 | F67: =IFERROR(INDEX(Categories!$B$5:$B$27,MATCH(E67,Categories!$A$5:$A$27,0)),"") -> Data Migration | G67: Copy content into Squarespace | H67: Project Coordinator | I67: Level 1 | J67: =IFERROR(INDEX(Rates!$D$6:$D$15,MATCH(H67&"|"&I67,Rates!$C$6:$C$15,0)),0) -> 0 | K67: 5 | L67: =K67*J67 -> 0 | M67: Biggest variable in the list. Quote a range or audit the old site first.
A68: 64 | C68: Deployment | D68: Pre-Launch QA | E68: 25 | F68: =IFERROR(INDEX(Categories!$B$5:$B$27,MATCH(E68,Categories!$A$5:$A$27,0)),"") -> QA & Testing | G68: Responsive + functionality checks | H68: QA Tester | I68: Level 1 | J68: =IFERROR(INDEX(Rates!$D$6:$D$15,MATCH(H68&"|"&I68,Rates!$C$6:$C$15,0)),0) -> 80 | K68: 3 | L68: =K68*J68 -> 240 | M68: Scales with page count and feature count. Thin for a large site.
A69: 65 | C69: Deployment | D69: Launch Site | E69: 8 | F69: =IFERROR(INDEX(Categories!$B$5:$B$27,MATCH(E69,Categories!$A$5:$A$27,0)),"") -> Deployment | G69: Go live + domain switch | H69: IT | I69: Level 1 | J69: =IFERROR(INDEX(Rates!$D$6:$D$15,MATCH(H69&"|"&I69,Rates!$C$6:$C$15,0)),0) -> 100 | K69: 2 | L69: =K69*J69 -> 200 | M69: Schedule a rollback window. Launch-day issues are normal.
A70: 66 | C70: Deployment | D70: Post-Launch QA | E70: 25 | F70: =IFERROR(INDEX(Categories!$B$5:$B$27,MATCH(E70,Categories!$A$5:$A$27,0)),"") -> QA & Testing | G70: Fix issues after launch | H70: QA Tester | I70: Level 1 | J70: =IFERROR(INDEX(Rates!$D$6:$D$15,MATCH(H70&"|"&I70,Rates!$C$6:$C$15,0)),0) -> 80 | K70: 3 | L70: =K70*J70 -> 240 | M70: Define a support window, or this becomes unlimited free work.
A71: 67 | C71: Deployment | D71: Tracking Verification | E71: 4 | F71: =IFERROR(INDEX(Categories!$B$5:$B$27,MATCH(E71,Categories!$A$5:$A$27,0)),"") -> Conversion Tracking | G71: Confirm analytics + events | H71: QA Tester | I71: Level 1 | J71: =IFERROR(INDEX(Rates!$D$6:$D$15,MATCH(H71&"|"&I71,Rates!$C$6:$C$15,0)),0) -> 80 | K71: 2 | L71: =K71*J71 -> 160
D73: TOTAL | K73: =SUM(K5:K71) -> 209 | L73: =SUM(L5:L71) -> 20600 | M73: Whole library total, not a project quote. Quote only the tasks a job needs.

Sheet Shopify
A1: Task Pricing – Shopify
A2: Base Hours unchanged. category_id has been remapped to the new Categories list.
A4: id | B4: Dependencies | C4: Module | D4: Name | E4: category_id | F4: Category | G4: Description | H4: Responsible | I4: Level | J4: Rate | K4: Base Hours | L4: Estimated Cost | M4: Hours – Things to Consider
A5: 1 | C5: Homepage – Standard | D5: Hero Section | E5: 14 | F5: =IFERROR(INDEX(Categories!$B$5:$B$27,MATCH(E5,Categories!$A$5:$A$27,0)),"") -> Frontend | G5: Hero section and headline | H5: IT | I5: Level 1 | J5: =IFERROR(INDEX(Rates!$D$6:$D$15,MATCH(H5&"|"&I5,Rates!$C$6:$C$15,0)),0) -> 100 | K5: 2 | L5: =K5*J5 -> 200
A6: 2 | C6: Homepage – Standard | D6: Services or Product Grid | E6: 14 | F6: =IFERROR(INDEX(Categories!$B$5:$B$27,MATCH(E6,Categories!$A$5:$A$27,0)),"") -> Frontend | G6: Product/collection grid using Shopify sections | H6: IT | I6: Level 1 | J6: =IFERROR(INDEX(Rates!$D$6:$D$15,MATCH(H6&"|"&I6,Rates!$C$6:$C$15,0)),0) -> 100 | K6: 3 | L6: =K6*J6 -> 300 | M6: Assumes a fixed number of items. Dynamic, data-driven grids cost more.
A7: 3 | C7: Homepage – Standard | D7: Testimonials | E7: 15 | F7: =IFERROR(INDEX(Categories!$B$5:$B$27,MATCH(E7,Categories!$A$5:$A$27,0)),"") -> Integration | G7: Testimonials via theme section or app | H7: IT | I7: Level 1 | J7: =IFERROR(INDEX(Rates!$D$6:$D$15,MATCH(H7&"|"&I7,Rates!$C$6:$C$15,0)),0) -> 100 | K7: 3 | L7: =K7*J7 -> 300 | M7: Styling a third-party widget or app can take longer than expected.
A8: 4 | C8: Homepage – Standard | D8: Team Preview | E8: 14 | F8: =IFERROR(INDEX(Categories!$B$5:$B$27,MATCH(E8,Categories!$A$5:$A$27,0)),"") -> Frontend | G8: Team section using content blocks | H8: IT | I8: Level 1 | J8: =IFERROR(INDEX(Rates!$D$6:$D$15,MATCH(H8&"|"&I8,Rates!$C$6:$C$15,0)),0) -> 100 | K8: 2 | L8: =K8*J8 -> 200 | M8: Bios and photo cropping are content work, not build work.
A9: 5 | C9: Homepage – Standard | D9: Footer Layout | E9: 14 | F9: =IFERROR(INDEX(Categories!$B$5:$B$27,MATCH(E9,Categories!$A$5:$A$27,0)),"") -> Frontend | G9: Footer with navigation, contact, socials | H9: IT | I9: Level 1 | J9: =IFERROR(INDEX(Rates!$D$6:$D$15,MATCH(H9&"|"&I9,Rates!$C$6:$C$15,0)),0) -> 100 | K9: 2 | L9: =K9*J9 -> 200 | M9: Mega-footers with multiple menus and a newsletter form run higher.
A10: 6 | C10: Homepage – Conversion | D10: Strong Hero Offer | E10: 14 | F10: =IFERROR(INDEX(Categories!$B$5:$B$27,MATCH(E10,Categories!$A$5:$A$27,0)),"") -> Frontend | G10: Hero with CTA | H10: IT | I10: Level 1 | J10: =IFERROR(INDEX(Rates!$D$6:$D$15,MATCH(H10&"|"&I10,Rates!$C$6:$C$15,0)),0) -> 100 | K10: 4 | L10: =K10*J10 -> 400
A11: 7 | C11: Homepage – Conversion | D11: Benefits/Features | E11: 14 | F11: =IFERROR(INDEX(Categories!$B$5:$B$27,MATCH(E11,Categories!$A$5:$A$27,0)),"") -> Frontend | G11: Features/benefits sections | H11: IT | I11: Level 1 | J11: =IFERROR(INDEX(Rates!$D$6:$D$15,MATCH(H11&"|"&I11,Rates!$C$6:$C$15,0)),0) -> 100 | K11: 3 | L11: =K11*J11 -> 300 | M11: Icon sourcing or custom icons may need Creative hours on top.
A12: 8 | C12: Homepage – Conversion | D12: Social Proof / Trust Badges | E12: 14 | F12: =IFERROR(INDEX(Categories!$B$5:$B$27,MATCH(E12,Categories!$A$5:$A$27,0)),"") -> Frontend | G12: Logos, reviews, trust badges | H12: IT | I12: Level 1 | J12: =IFERROR(INDEX(Rates!$D$6:$D$15,MATCH(H12&"|"&I12,Rates!$C$6:$C$15,0)),0) -> 100 | K12: 2 | L12: =K12*J12 -> 200 | M12: Assumes client supplies logos in usable formats. Logo cleanup is Creative time.
A13: 9 | C13: Homepage – Conversion | D13: FAQ Section | E13: 14 | F13: =IFERROR(INDEX(Categories!$B$5:$B$27,MATCH(E13,Categories!$A$5:$A$27,0)),"") -> Frontend | G13: Accordion FAQ | H13: IT | I13: Level 1 | J13: =IFERROR(INDEX(Rates!$D$6:$D$15,MATCH(H13&"|"&I13,Rates!$C$6:$C$15,0)),0) -> 100 | K13: 2 | L13: =K13*J13 -> 200 | M13: Add a little time if FAQ schema markup is also required.
A14: 10 | C14: Homepage – Conversion | D14: Pricing Tables | E14: 14 | F14: =IFERROR(INDEX(Categories!$B$5:$B$27,MATCH(E14,Categories!$A$5:$A$27,0)),"") -> Frontend | G14: Subscription or pricing layouts | H14: IT | I14: Level 1 | J14: =IFERROR(INDEX(Rates!$D$6:$D$15,MATCH(H14&"|"&I14,Rates!$C$6:$C$15,0)),0) -> 100 | K14: 4 | L14: =K14*J14 -> 400 | M14: Monthly/annual toggles or more than 3 plans push this higher.
A15: 11 | C15: Homepage – E-Commerce | D15: Featured Products | E15: 12 | F15: =IFERROR(INDEX(Categories!$B$5:$B$27,MATCH(E15,Categories!$A$5:$A$27,0)),"") -> E-Commerce | G15: Featured products section | H15: IT | I15: Level 1 | J15: =IFERROR(INDEX(Rates!$D$6:$D$15,MATCH(H15&"|"&I15,Rates!$C$6:$C$15,0)),0) -> 100 | K15: 4 | L15: =K15*J15 -> 400
A16: 12 | C16: Homepage – E-Commerce | D16: Sales Banners | E16: 12 | F16: =IFERROR(INDEX(Categories!$B$5:$B$27,MATCH(E16,Categories!$A$5:$A$27,0)),"") -> E-Commerce | G16: Promo banners | H16: Creative | I16: Level 1 | J16: =IFERROR(INDEX(Rates!$D$6:$D$15,MATCH(H16&"|"&I16,Rates!$C$6:$C$15,0)),0) -> 100 | K16: 3 | L16: =K16*J16 -> 300 | M16: Recurring campaign artwork is worth a separate maintenance line item.
A17: 13 | C17: Homepage – E-Commerce | D17: Dynamic Product Feeds | E17: 12 | F17: =IFERROR(INDEX(Categories!$B$5:$B$27,MATCH(E17,Categories!$A$5:$A$27,0)),"") -> E-Commerce | G17: Collections + filters | H17: IT | I17: Level 1 | J17: =IFERROR(INDEX(Rates!$D$6:$D$15,MATCH(H17&"|"&I17,Rates!$C$6:$C$15,0)),0) -> 100 | K17: 6 | L17: =K17*J17 -> 600 | M17: Feeds to Google Merchant Center or Meta have their own spec requirements.
A18: 14 | C18: Homepage – E-Commerce | D18: Category Highlights | E18: 12 | F18: =IFERROR(INDEX(Categories!$B$5:$B$27,MATCH(E18,Categories!$A$5:$A$27,0)),"") -> E-Commerce | G18: Collection highlights | H18: IT | I18: Level 1 | J18: =IFERROR(INDEX(Rates!$D$6:$D$15,MATCH(H18&"|"&I18,Rates!$C$6:$C$15,0)),0) -> 100 | K18: 4 | L18: =K18*J18 -> 400
A19: 15 | C19: Homepage – E-Commerce | D19: Customer Reviews | E19: 12 | F19: =IFERROR(INDEX(Categories!$B$5:$B$27,MATCH(E19,Categories!$A$5:$A$27,0)),"") -> E-Commerce | G19: Product reviews via app | H19: IT | I19: Level 1 | J19: =IFERROR(INDEX(Rates!$D$6:$D$15,MATCH(H19&"|"&I19,Rates!$C$6:$C$15,0)),0) -> 100 | K19: 5 | L19: =K19*J19 -> 500 | M19: Excludes the review app subscription.
A20: 16 | C20: Homepage – E-Commerce | D20: Personalization Blocks | E20: 12 | F20: =IFERROR(INDEX(Categories!$B$5:$B$27,MATCH(E20,Categories!$A$5:$A$27,0)),"") -> E-Commerce | G20: Recommended products (apps) | H20: IT | I20: Level 2 | J20: =IFERROR(INDEX(Rates!$D$6:$D$15,MATCH(H20&"|"&I20,Rates!$C$6:$C$15,0)),0) -> 120 | K20: 6 | L20: =K20*J20 -> 720 | M20: Excludes the recommendation app subscription.
A21: 17 | C21: Homepage – Creative | D21: Full-Screen Visuals | E21: 14 | F21: =IFERROR(INDEX(Categories!$B$5:$B$27,MATCH(E21,Categories!$A$5:$A$27,0)),"") -> Frontend | G21: Image-heavy layouts | H21: Creative | I21: Level 1 | J21: =IFERROR(INDEX(Rates!$D$6:$D$15,MATCH(H21&"|"&I21,Rates!$C$6:$C$15,0)),0) -> 100 | K21: 5 | L21: =K21*J21 -> 500 | M21: Image sourcing, licensing, and retouching may be billed separately.
A22: 18 | C22: Homepage – Creative | D22: Parallax Effects | E22: 14 | F22: =IFERROR(INDEX(Categories!$B$5:$B$27,MATCH(E22,Categories!$A$5:$A$27,0)),"") -> Frontend | G22: Theme-based effects | H22: IT | I22: Level 2 | J22: =IFERROR(INDEX(Rates!$D$6:$D$15,MATCH(H22&"|"&I22,Rates!$C$6:$C$15,0)),0) -> 120 | K22: 3 | L22: =K22*J22 -> 360 | M22: Theme-dependent. A theme without support needs custom code.
A23: 19 | C23: Homepage – Creative | D23: Hover Animations | E23: 14 | F23: =IFERROR(INDEX(Categories!$B$5:$B$27,MATCH(E23,Categories!$A$5:$A$27,0)),"") -> Frontend | G23: Theme/custom CSS | H23: IT | I23: Level 1 | J23: =IFERROR(INDEX(Rates!$D$6:$D$15,MATCH(H23&"|"&I23,Rates!$C$6:$C$15,0)),0) -> 100 | K23: 3 | L23: =K23*J23 -> 300 | M23: Needs a touch-device fallback, which is easy to forget in the estimate.
A24: 20 | C24: Homepage – Creative | D24: Creative Layouts | E24: 14 | F24: =IFERROR(INDEX(Categories!$B$5:$B$27,MATCH(E24,Categories!$A$5:$A$27,0)),"") -> Frontend | G24: Custom sections or Liquid edits | H24: IT | I24: Level 1 | J24: =IFERROR(INDEX(Rates!$D$6:$D$15,MATCH(H24&"|"&I24,Rates!$C$6:$C$15,0)),0) -> 100 | K24: 5 | L24: =K24*J24 -> 500 | M24: Liquid edits mean theme-update risk later. Note that in the quote.
A25: 21 | C25: Homepage – Conversion | D25: Lead Capture Form | E25: 14 | F25: =IFERROR(INDEX(Categories!$B$5:$B$27,MATCH(E25,Categories!$A$5:$A$27,0)),"") -> Frontend | G25: Form or email signup | H25: IT | I25: Level 1 | J25: =IFERROR(INDEX(Rates!$D$6:$D$15,MATCH(H25&"|"&I25,Rates!$C$6:$C$15,0)),0) -> 100 | K25: 2 | L25: =K25*J25 -> 200 | M25: CRM connection is billed separately.
A26: 22 | C26: Homepage – Conversion | D26: Forms Spam Protection | E26: 18 | F26: =IFERROR(INDEX(Categories!$B$5:$B$27,MATCH(E26,Categories!$A$5:$A$27,0)),"") -> Performance & Security | G26: Basic spam protection | H26: IT | I26: Level 1 | J26: =IFERROR(INDEX(Rates!$D$6:$D$15,MATCH(H26&"|"&I26,Rates!$C$6:$C$15,0)),0) -> 100 | K26: 1 | L26: =K26*J26 -> 100 | M26: Covers all forms at once.
A27: 23 | C27: Core Page - Standard | D27: Standard Page (About, Services) | E27: 14 | F27: =IFERROR(INDEX(Categories!$B$5:$B$27,MATCH(E27,Categories!$A$5:$A$27,0)),"") -> Frontend | G27: Content pages | H27: IT | I27: Level 1 | J27: =IFERROR(INDEX(Rates!$D$6:$D$15,MATCH(H27&"|"&I27,Rates!$C$6:$C$15,0)),0) -> 100 | K27: 6 | L27: =K27*J27 -> 600 | M27: Per page. Multiply by page count and confirm the total in the quote.
A28: 24 | C28: Core Page - Landing Page | D28: Landing Page | E28: 14 | F28: =IFERROR(INDEX(Categories!$B$5:$B$27,MATCH(E28,Categories!$A$5:$A$27,0)),"") -> Frontend | G28: Conversion-focused layout | H28: IT | I28: Level 1 | J28: =IFERROR(INDEX(Rates!$D$6:$D$15,MATCH(H28&"|"&I28,Rates!$C$6:$C$15,0)),0) -> 100 | K28: 8 | L28: =K28*J28 -> 800 | M28: Per page. Second and later pages using the same layout should be cheaper.
A29: 25 | C29: Core Page - Contact Page | D29: Contact Page | E29: 14 | F29: =IFERROR(INDEX(Categories!$B$5:$B$27,MATCH(E29,Categories!$A$5:$A$27,0)),"") -> Frontend | G29: Contact form + info | H29: IT | I29: Level 1 | J29: =IFERROR(INDEX(Rates!$D$6:$D$15,MATCH(H29&"|"&I29,Rates!$C$6:$C$15,0)),0) -> 100 | K29: 5 | L29: =K29*J29 -> 500 | M29: Includes one form. Map embed and multi-location info may add time.
A30: 26 | C30: Core Page - Blog Detail | D30: Blog Post Template | E30: 22 | F30: =IFERROR(INDEX(Categories!$B$5:$B$27,MATCH(E30,Categories!$A$5:$A$27,0)),"") -> SEO & Content | G30: Shopify blog template | H30: IT | I30: Level 1 | J30: =IFERROR(INDEX(Rates!$D$6:$D$15,MATCH(H30&"|"&I30,Rates!$C$6:$C$15,0)),0) -> 100 | K30: 4 | L30: =K30*J30 -> 400 | M30: Related posts, author boxes, and share buttons add time.
... A38: 34 | C38: Integrations | D38: Accessibility (Basic) | E38: 1 | F38: =IFERROR(INDEX(Categories!$B$5:$B$27,MATCH(E38,Categories!$A$5:$A$27,0)),"") -> Accessibility | G38: Theme adjustments | H38: IT | I38: Level 1 | J38: =IFERROR(INDEX(Rates!$D$6:$D$15,MATCH(H38&"|"&I38,Rates!$C$6:$C$15,0)),0) -> 100 | K38: 5 | L38: =K38*J38 -> 500 | M38: Scales with page count. Never guarantee legal compliance.
A39: 35 | C39: Members / Accounts | D39: Customer Accounts | E39: 2 | F39: =IFERROR(INDEX(Categories!$B$5:$B$27,MATCH(E39,Categories!$A$5:$A$27,0)),"") -> Backend | G39: Shopify customer accounts | H39: IT | I39: Level 1 | J39: =IFERROR(INDEX(Rates!$D$6:$D$15,MATCH(H39&"|"&I39,Rates!$C$6:$C$15,0)),0) -> 100 | K39: 4 | L39: =K39*J39 -> 400
A40: 36 | C40: Members / Accounts | D40: Profile Management | E40: 2 | F40: =IFERROR(INDEX(Categories!$B$5:$B$27,MATCH(E40,Categories!$A$5:$A$27,0)),"") -> Backend | G40: Account editing | H40: IT | I40: Level 1 | J40: =IFERROR(INDEX(Rates!$D$6:$D$15,MATCH(H40&"|"&I40,Rates!$C$6:$C$15,0)),0) -> 100 | K40: 4 | L40: =K40*J40 -> 400 | M40: Custom profile fields and avatar uploads add hours.
A41: 37 | C41: Members / Accounts | D41: Restricted Content | E41: 2 | F41: =IFERROR(INDEX(Categories!$B$5:$B$27,MATCH(E41,Categories!$A$5:$A$27,0)),"") -> Backend | G41: Apps or Liquid logic | H41: IT | I41: Level 1 | J41: =IFERROR(INDEX(Rates!$D$6:$D$15,MATCH(H41&"|"&I41,Rates!$C$6:$C$15,0)),0) -> 100 | K41: 6 | L41: =K41*J41 -> 600 | M41: Needs an app or Liquid workarounds. Shopify is not built for this.
A42: 38 | C42: E-Commerce Core | D42: Product Template | E42: 12 | F42: =IFERROR(INDEX(Categories!$B$5:$B$27,MATCH(E42,Categories!$A$5:$A$27,0)),"") -> E-Commerce | G42: Product page template | H42: IT | I42: Level 1 | J42: =IFERROR(INDEX(Rates!$D$6:$D$15,MATCH(H42&"|"&I42,Rates!$C$6:$C$15,0)),0) -> 100 | K42: 6 | L42: =K42*J42 -> 600 | M42: One template. Simple and variable products may need different treatments.
A43: 39 | C43: E-Commerce Core | D43: Cart Functionality | E43: 12 | F43: =IFERROR(INDEX(Categories!$B$5:$B$27,MATCH(E43,Categories!$A$5:$A$27,0)),"") -> E-Commerce | G43: Built-in cart | H43: IT | I43: Level 1 | J43: =IFERROR(INDEX(Rates!$D$6:$D$15,MATCH(H43&"|"&I43,Rates!$C$6:$C$15,0)),0) -> 100 | K43: 4 | L43: =K43*J43 -> 400 | M43: Mini-cart and AJAX cart customization add hours.
A44: 40 | C44: E-Commerce Core | D44: Checkout Flow | E44: 12 | F44: =IFERROR(INDEX(Categories!$B$5:$B$27,MATCH(E44,Categories!$A$5:$A$27,0)),"") -> E-Commerce | G44: Shopify checkout (limited customization) | H44: IT | I44: Level 1 | J44: =IFERROR(INDEX(Rates!$D$6:$D$15,MATCH(H44&"|"&I44,Rates!$C$6:$C$15,0)),0) -> 100 | K44: 4 | L44: =K44*J44 -> 400 | M44: Checkout is locked unless the client is on Shopify Plus. Set expectations early.
A45: 41 | C45: E-Commerce Core | D45: Shipping Rules | E45: 12 | F45: =IFERROR(INDEX(Categories!$B$5:$B$27,MATCH(E45,Categories!$A$5:$A$27,0)),"") -> E-Commerce | G45: Shipping setup | H45: IT | I45: Level 1 | J45: =IFERROR(INDEX(Rates!$D$6:$D$15,MATCH(H45&"|"&I45,Rates!$C$6:$C$15,0)),0) -> 100 | K45: 4 | L45: =K45*J45 -> 400 | M45: Live carrier rates are more work than flat-rate zones.
A46: 42 | C46: E-Commerce Core | D46: Payment Gateway Integration | E46: 12 | F46: =IFERROR(INDEX(Categories!$B$5:$B$27,MATCH(E46,Categories!$A$5:$A$27,0)),"") -> E-Commerce | G46: Shopify Payments / PayPal | H46: IT | I46: Level 1 | J46: =IFERROR(INDEX(Rates!$D$6:$D$15,MATCH(H46&"|"&I46,Rates!$C$6:$C$15,0)),0) -> 100 | K46: 3 | L46: =K46*J46 -> 300 | M46: Excludes merchant account approval. Client delays are common.
A47: 43 | C47: E-Commerce Core | D47: Tax Calculator | E47: 12 | F47: =IFERROR(INDEX(Categories!$B$5:$B$27,MATCH(E47,Categories!$A$5:$A$27,0)),"") -> E-Commerce | G47: Built-in taxes | H47: IT | I47: Level 1 | J47: =IFERROR(INDEX(Rates!$D$6:$D$15,MATCH(H47&"|"&I47,Rates!$C$6:$C$15,0)),0) -> 100 | K47: 2 | L47: =K47*J47 -> 200 | M47: Built-in. Multi-jurisdiction tax may need Avalara or similar.
A48: 44 | C48: Advanced E-Commerce | D48: Product Options / Variants | E48: 12 | F48: =IFERROR(INDEX(Categories!$B$5:$B$27,MATCH(E48,Categories!$A$5:$A$27,0)),"") -> E-Commerce | G48: Variants or apps | H48: IT | I48: Level 1 | J48: =IFERROR(INDEX(Rates!$D$6:$D$15,MATCH(H48&"|"&I48,Rates!$C$6:$C$15,0)),0) -> 100 | K48: 6 | L48: =K48*J48 -> 600 | M48: Setup only, not per-product entry. Multiply by product count separately.
A49: 45 | C49: Advanced E-Commerce | D49: Product Customizer (Basic) | E49: 5 | F49: =IFERROR(INDEX(Categories!$B$5:$B$27,MATCH(E49,Categories!$A$5:$A$27,0)),"") -> Custom Tools | G49: Product customization apps | H49: IT | I49: Level 2 | J49: =IFERROR(INDEX(Rates!$D$6:$D$15,MATCH(H49&"|"&I49,Rates!$C$6:$C$15,0)),0) -> 120 | K49: 12 | L49: =K49*J49 -> 1440 | M49: Excludes the app subscription. App limits often force scope changes.
A50: 46 | C50: Advanced E-Commerce | D50: Product Customizer (Advanced) | E50: 5 | F50: =IFERROR(INDEX(Categories!$B$5:$B$27,MATCH(E50,Categories!$A$5:$A$27,0)),"") -> Custom Tools | G50: Advanced configurator apps | H50: IT | I50: Level 2 | J50: =IFERROR(INDEX(Rates!$D$6:$D$15,MATCH(H50&"|"&I50,Rates!$C$6:$C$15,0)),0) -> 120 | K50: 25 | L50: =K50*J50 -> 3000 | M50: Excludes the app subscription. High risk, scope tightly.
A51: 47 | C51: Advanced E-Commerce | D51: Subscriptions | E51: 12 | F51: =IFERROR(INDEX(Categories!$B$5:$B$27,MATCH(E51,Categories!$A$5:$A$27,0)),"") -> E-Commerce | G51: Subscription apps | H51: IT | I51: Level 1 | J51: =IFERROR(INDEX(Rates!$D$6:$D$15,MATCH(H51&"|"&I51,Rates!$C$6:$C$15,0)),0) -> 100 | K51: 6 | L51: =K51*J51 -> 600 | M51: Excludes the subscription app cost.
... A57: 53 | C57: Blog | D57: Blog Setup | E57: 22 | F57: =IFERROR(INDEX(Categories!$B$5:$B$27,MATCH(E57,Categories!$A$5:$A$27,0)),"") -> SEO & Content | G57: Blog listing | H57: IT | I57: Level 1 | J57: =IFERROR(INDEX(Rates!$D$6:$D$15,MATCH(H57&"|"&I57,Rates!$C$6:$C$15,0)),0) -> 100 | K57: 2 | L57: =K57*J57 -> 200 | M57: Category filtering and pagination styling may add time.
A58: 54 | C58: Blog | D58: Single Post Template | E58: 22 | F58: =IFERROR(INDEX(Categories!$B$5:$B$27,MATCH(E58,Categories!$A$5:$A$27,0)),"") -> SEO & Content | G58: Default template | H58: IT | I58: Level 1 | J58: =IFERROR(INDEX(Rates!$D$6:$D$15,MATCH(H58&"|"&I58,Rates!$C$6:$C$15,0)),0) -> 100 | K58: 1 | L58: =K58*J58 -> 100
A59: 55 | C59: Blog | D59: Lead Capture Integration | E59: 22 | F59: =IFERROR(INDEX(Categories!$B$5:$B$27,MATCH(E59,Categories!$A$5:$A$27,0)),"") -> SEO & Content | G59: Email signup | H59: IT | I59: Level 1 | J59: =IFERROR(INDEX(Rates!$D$6:$D$15,MATCH(H59&"|"&I59,Rates!$C$6:$C$15,0)),0) -> 100 | K59: 2 | L59: =K59*J59 -> 200 | M59: Email platform connection (Mailchimp etc.) may need integration hours.
A60: 56 | C60: SEO | D60: Basic SEO Setup | E60: 22 | F60: =IFERROR(INDEX(Categories!$B$5:$B$27,MATCH(E60,Categories!$A$5:$A$27,0)),"") -> SEO & Content | G60: Titles + meta | H60: IT | I60: Level 1 | J60: =IFERROR(INDEX(Rates!$D$6:$D$15,MATCH(H60&"|"&I60,Rates!$C$6:$C$15,0)),0) -> 100 | K60: 2 | L60: =K60*J60 -> 200 | M60: Excludes keyword research and strategy, which are separate services.
A61: 57 | C61: SEO | D61: Schema (Basic) | E61: 24 | F61: =IFERROR(INDEX(Categories!$B$5:$B$27,MATCH(E61,Categories!$A$5:$A$27,0)),"") -> SEO on-page | G61: Theme/app-based schema | H61: IT | I61: Level 1 | J61: =IFERROR(INDEX(Rates!$D$6:$D$15,MATCH(H61&"|"&I61,Rates!$C$6:$C$15,0)),0) -> 100 | K61: 2 | L61: =K61*J61 -> 200 | M61: Per schema type. Platform tools limit how far you can go.
A62: 58 | C62: SEO | D62: Sitemap (Auto) | E62: 24 | F62: =IFERROR(INDEX(Categories!$B$5:$B$27,MATCH(E62,Categories!$A$5:$A$27,0)),"") -> SEO on-page | G62: Auto-generated | H62: IT | I62: Level 1 | J62: =IFERROR(INDEX(Rates!$D$6:$D$15,MATCH(H62&"|"&I62,Rates!$C$6:$C$15,0)),0) -> 100 | K62: 0 | L62: =K62*J62 -> 0 | M62: Zero hours. Keep it as an 'included free' talking point or delete the row.
A63: 59 | C63: SEO | D63: URL Redirects | E63: 24 | F63: =IFERROR(INDEX(Categories!$B$5:$B$27,MATCH(E63,Categories!$A$5:$A$27,0)),"") -> SEO on-page | G63: Redirects setup | H63: IT | I63: Level 1 | J63: =IFERROR(INDEX(Rates!$D$6:$D$15,MATCH(H63&"|"&I63,Rates!$C$6:$C$15,0)),0) -> 100 | K63: 2 | L63: =K63*J63 -> 200 | M63: Large migrations need a URL mapping exercise first.
A64: 60 | C64: SEO | D64: Content Optimization | E64: 22 | F64: =IFERROR(INDEX(Categories!$B$5:$B$27,MATCH(E64,Categories!$A$5:$A$27,0)),"") -> SEO & Content | G64: On-page SEO | H64: Creative | I64: Level 1 | J64: =IFERROR(INDEX(Rates!$D$6:$D$15,MATCH(H64&"|"&I64,Rates!$C$6:$C$15,0)),0) -> 100 | K64: 3 | L64: =K64*J64 -> 300 | M64: Per page. Define how many revision rounds are included.
A65: 61 | C65: Environment Setup | D65: Shopify Store Setup | E65: 13 | F65: =IFERROR(INDEX(Categories!$B$5:$B$27,MATCH(E65,Categories!$A$5:$A$27,0)),"") -> Environment Setup | G65: Create store | H65: IT | I65: Level 1 | J65: =IFERROR(INDEX(Rates!$D$6:$D$15,MATCH(H65&"|"&I65,Rates!$C$6:$C$15,0)),0) -> 100 | K65: 2 | L65: =K65*J65 -> 200 | M65: Excludes the Shopify subscription and transaction fees.
A66: 62 | C66: Environment Setup | D66: Theme Setup & Customization | E66: 13 | F66: =IFERROR(INDEX(Categories!$B$5:$B$27,MATCH(E66,Categories!$A$5:$A$27,0)),"") -> Environment Setup | G66: Theme + sections + styling | H66: IT | I66: Level 1 | J66: =IFERROR(INDEX(Rates!$D$6:$D$15,MATCH(H66&"|"&I66,Rates!$C$6:$C$15,0)),0) -> 100 | K66: 5 | L66: =K66*J66 -> 500 | M66: Premium theme cost is separate. Theme quality varies a lot.
A67: 63 | C67: Environment Setup | D67: Domain Setup | E67: 13 | F67: =IFERROR(INDEX(Categories!$B$5:$B$27,MATCH(E67,Categories!$A$5:$A$27,0)),"") -> Environment Setup | G67: Connect domain | H67: IT | I67: Level 1 | J67: =IFERROR(INDEX(Rates!$D$6:$D$15,MATCH(H67&"|"&I67,Rates!$C$6:$C$15,0)),0) -> 100 | K67: 2 | L67: =K67*J67 -> 200 | M67: DNS propagation affects the schedule but is not billable work.
A68: 64 | C68: Content Entry | D68: Content Upload | E68: 3 | F68: =IFERROR(INDEX(Categories!$B$5:$B$27,MATCH(E68,Categories!$A$5:$A$27,0)),"") -> CMS & Content Prep | G68: Add content/products | H68: Project Coordinator | I68: Level 1 | J68: =IFERROR(INDEX(Rates!$D$6:$D$15,MATCH(H68&"|"&I68,Rates!$C$6:$C$15,0)),0) -> 0 | K68: 3 | L68: =K68*J68 -> 0 | M68: Per page or per batch, and often badly underestimated. Assumes final content from the client.
A69: 65 | C69: Content Entry | D69: Media Optimization | E69: 3 | F69: =IFERROR(INDEX(Categories!$B$5:$B$27,MATCH(E69,Categories!$A$5:$A$27,0)),"") -> CMS & Content Prep | G69: Image optimization | H69: IT | I69: Level 1 | J69: =IFERROR(INDEX(Rates!$D$6:$D$15,MATCH(H69&"|"&I69,Rates!$C$6:$C$15,0)),0) -> 100 | K69: 2 | L69: =K69*J69 -> 200 | M69: Scales with image count. A large gallery or catalog needs more.
A70: 66 | C70: Pre-Launch QA | D70: QA Review | E70: 25 | F70: =IFERROR(INDEX(Categories!$B$5:$B$27,MATCH(E70,Categories!$A$5:$A$27,0)),"") -> QA & Testing | G70: Test store, checkout, responsiveness | H70: QA Tester | I70: Level 1 | J70: =IFERROR(INDEX(Rates!$D$6:$D$15,MATCH(H70&"|"&I70,Rates!$C$6:$C$15,0)),0) -> 80 | K70: 4 | L70: =K70*J70 -> 320 | M70: Scales with page count and feature count. Thin for a large site.
... A72: 68 | C72: Post-Launch | D72: QA Fixes | E72: 25 | F72: =IFERROR(INDEX(Categories!$B$5:$B$27,MATCH(E72,Categories!$A$5:$A$27,0)),"") -> QA & Testing | G72: Bug fixes | H72: QA Tester | I72: Level 1 | J72: =IFERROR(INDEX(Rates!$D$6:$D$15,MATCH(H72&"|"&I72,Rates!$C$6:$C$15,0)),0) -> 80 | K72: 4 | L72: =K72*J72 -> 320 | M72: Define a support window, or this becomes unlimited free work.
A73: 69 | C73: Post-Launch | D73: Tracking Verification | E73: 4 | F73: =IFERROR(INDEX(Categories!$B$5:$B$27,MATCH(E73,Categories!$A$5:$A$27,0)),"") -> Conversion Tracking | G73: Verify analytics | H73: QA Tester | I73: Level 1 | J73: =IFERROR(INDEX(Rates!$D$6:$D$15,MATCH(H73&"|"&I73,Rates!$C$6:$C$15,0)),0) -> 80 | K73: 2 | L73: =K73*J73 -> 160
D75: TOTAL | K75: =SUM(K5:K73) -> 295 | L75: =SUM(L5:L73) -> 30520 | M75: Whole library total, not a project quote. Quote only the tasks a job needs.

Sheet WIX
A1: Task Pricing – WIX
A2: Base Hours unchanged. category_id has been remapped to the new Categories list.
A4: id | B4: Dependencies | C4: Module | D4: Name | E4: category_id | F4: Category | G4: Description | H4: Responsible | I4: Level | J4: Rate | K4: Base Hours | L4: Estimated Cost | M4: Hours – Things to Consider
A5: 1 | C5: Homepage – Standard | D5: Hero Section | E5: 14 | F5: =IFERROR(INDEX(Categories!$B$5:$B$27,MATCH(E5,Categories!$A$5:$A$27,0)),"") -> Frontend | G5: Hero section and headline | H5: IT | I5: Level 1 | J5: =IFERROR(INDEX(Rates!$D$6:$D$15,MATCH(H5&"|"&I5,Rates!$C$6:$C$15,0)),0) -> 100 | K5: 2 | L5: =K5*J5 -> 200
A6: 2 | C6: Homepage – Standard | D6: Services or Product Grid | E6: 14 | F6: =IFERROR(INDEX(Categories!$B$5:$B$27,MATCH(E6,Categories!$A$5:$A$27,0)),"") -> Frontend | G6: Grid using Wix repeater/layout tools | H6: IT | I6: Level 1 | J6: =IFERROR(INDEX(Rates!$D$6:$D$15,MATCH(H6&"|"&I6,Rates!$C$6:$C$15,0)),0) -> 100 | K6: 3 | L6: =K6*J6 -> 300 | M6: Assumes a fixed number of items. Dynamic, data-driven grids cost more.
A7: 3 | C7: Homepage – Standard | D7: Testimonials | E7: 15 | F7: =IFERROR(INDEX(Categories!$B$5:$B$27,MATCH(E7,Categories!$A$5:$A$27,0)),"") -> Integration | G7: Testimonials via sections or apps | H7: IT | I7: Level 1 | J7: =IFERROR(INDEX(Rates!$D$6:$D$15,MATCH(H7&"|"&I7,Rates!$C$6:$C$15,0)),0) -> 100 | K7: 3 | L7: =K7*J7 -> 300 | M7: Styling a third-party widget or app can take longer than expected.
A8: 4 | C8: Homepage – Standard | D8: Team Preview | E8: 14 | F8: =IFERROR(INDEX(Categories!$B$5:$B$27,MATCH(E8,Categories!$A$5:$A$27,0)),"") -> Frontend | G8: Team section using repeaters | H8: IT | I8: Level 1 | J8: =IFERROR(INDEX(Rates!$D$6:$D$15,MATCH(H8&"|"&I8,Rates!$C$6:$C$15,0)),0) -> 100 | K8: 2 | L8: =K8*J8 -> 200 | M8: Bios and photo cropping are content work, not build work.
A9: 5 | C9: Homepage – Standard | D9: Footer Layout | E9: 14 | F9: =IFERROR(INDEX(Categories!$B$5:$B$27,MATCH(E9,Categories!$A$5:$A$27,0)),"") -> Frontend | G9: Footer with nav, contact, socials | H9: IT | I9: Level 1 | J9: =IFERROR(INDEX(Rates!$D$6:$D$15,MATCH(H9&"|"&I9,Rates!$C$6:$C$15,0)),0) -> 100 | K9: 2 | L9: =K9*J9 -> 200 | M9: Mega-footers with multiple menus and a newsletter form run higher.
A10: 6 | C10: Homepage – Conversion | D10: Strong Hero Offer | E10: 14 | F10: =IFERROR(INDEX(Categories!$B$5:$B$27,MATCH(E10,Categories!$A$5:$A$27,0)),"") -> Frontend | G10: Hero with CTA | H10: IT | I10: Level 1 | J10: =IFERROR(INDEX(Rates!$D$6:$D$15,MATCH(H10&"|"&I10,Rates!$C$6:$C$15,0)),0) -> 100 | K10: 4 | L10: =K10*J10 -> 400
A11: 7 | C11: Homepage – Conversion | D11: Benefits/Features | E11: 14 | F11: =IFERROR(INDEX(Categories!$B$5:$B$27,MATCH(E11,Categories!$A$5:$A$27,0)),"") -> Frontend | G11: Content sections | H11: IT | I11: Level 1 | J11: =IFERROR(INDEX(Rates!$D$6:$D$15,MATCH(H11&"|"&I11,Rates!$C$6:$C$15,0)),0) -> 100 | K11: 3 | L11: =K11*J11 -> 300 | M11: Icon sourcing or custom icons may need Creative hours on top.
A12: 8 | C12: Homepage – Conversion | D12: Social Proof / Trust Badges | E12: 14 | F12: =IFERROR(INDEX(Categories!$B$5:$B$27,MATCH(E12,Categories!$A$5:$A$27,0)),"") -> Frontend | G12: Logos/reviews | H12: IT | I12: Level 1 | J12: =IFERROR(INDEX(Rates!$D$6:$D$15,MATCH(H12&"|"&I12,Rates!$C$6:$C$15,0)),0) -> 100 | K12: 2 | L12: =K12*J12 -> 200 | M12: Assumes client supplies logos in usable formats. Logo cleanup is Creative time.
A13: 9 | C13: Homepage – Conversion | D13: FAQ Section | E13: 14 | F13: =IFERROR(INDEX(Categories!$B$5:$B$27,MATCH(E13,Categories!$A$5:$A$27,0)),"") -> Frontend | G13: Collapsible FAQ | H13: IT | I13: Level 1 | J13: =IFERROR(INDEX(Rates!$D$6:$D$15,MATCH(H13&"|"&I13,Rates!$C$6:$C$15,0)),0) -> 100 | K13: 2 | L13: =K13*J13 -> 200 | M13: Add a little time if FAQ schema markup is also required.
A14: 10 | C14: Homepage – Standard | D14: Pricing Tables | E14: 14 | F14: =IFERROR(INDEX(Categories!$B$5:$B$27,MATCH(E14,Categories!$A$5:$A$27,0)),"") -> Frontend | G14: Pricing layout sections | H14: IT | I14: Level 1 | J14: =IFERROR(INDEX(Rates!$D$6:$D$15,MATCH(H14&"|"&I14,Rates!$C$6:$C$15,0)),0) -> 100 | K14: 4 | L14: =K14*J14 -> 400 | M14: Monthly/annual toggles or more than 3 plans push this higher.
A15: 11 | C15: Homepage – Standard | D15: Galleries | E15: 14 | F15: =IFERROR(INDEX(Categories!$B$5:$B$27,MATCH(E15,Categories!$A$5:$A$27,0)),"") -> Frontend | G15: Wix gallery | H15: IT | I15: Level 1 | J15: =IFERROR(INDEX(Rates!$D$6:$D$15,MATCH(H15&"|"&I15,Rates!$C$6:$C$15,0)),0) -> 100 | K15: 2 | L15: =K15*J15 -> 200 | M15: Per gallery. Image prep is billed separately.
A16: 12 | C16: Homepage – Standard | D16: Video Embeds | E16: 14 | F16: =IFERROR(INDEX(Categories!$B$5:$B$27,MATCH(E16,Categories!$A$5:$A$27,0)),"") -> Frontend | G16: Video blocks | H16: IT | I16: Level 1 | J16: =IFERROR(INDEX(Rates!$D$6:$D$15,MATCH(H16&"|"&I16,Rates!$C$6:$C$15,0)),0) -> 100 | K16: 1 | L16: =K16*J16 -> 100 | M16: Self-hosted video or custom players are a different, larger scope.
A17: 13 | C17: Homepage – Standard | D17: Payments / Donations | E17: 15 | F17: =IFERROR(INDEX(Categories!$B$5:$B$27,MATCH(E17,Categories!$A$5:$A$27,0)),"") -> Integration | G17: Wix Payments / Stripe / PayPal | H17: IT | I17: Level 1 | J17: =IFERROR(INDEX(Rates!$D$6:$D$15,MATCH(H17&"|"&I17,Rates!$C$6:$C$15,0)),0) -> 100 | K17: 4 | L17: =K17*J17 -> 400 | M17: Excludes merchant account approval. Client delays here are common.
A18: 14 | C18: Homepage – Standard | D18: Use Cases | E18: 14 | F18: =IFERROR(INDEX(Categories!$B$5:$B$27,MATCH(E18,Categories!$A$5:$A$27,0)),"") -> Frontend | G18: Content sections | H18: IT | I18: Level 1 | J18: =IFERROR(INDEX(Rates!$D$6:$D$15,MATCH(H18&"|"&I18,Rates!$C$6:$C$15,0)),0) -> 100 | K18: 2 | L18: =K18*J18 -> 200
A19: 15 | C19: Homepage – Standard | D19: Map / Location Section | E19: 15 | F19: =IFERROR(INDEX(Categories!$B$5:$B$27,MATCH(E19,Categories!$A$5:$A$27,0)),"") -> Integration | G19: Wix map embed | H19: IT | I19: Level 1 | J19: =IFERROR(INDEX(Rates!$D$6:$D$15,MATCH(H19&"|"&I19,Rates!$C$6:$C$15,0)),0) -> 100 | K19: 2 | L19: =K19*J19 -> 200
A20: 16 | C20: Homepage – Creative | D20: Full-Screen Visuals | E20: 14 | F20: =IFERROR(INDEX(Categories!$B$5:$B$27,MATCH(E20,Categories!$A$5:$A$27,0)),"") -> Frontend | G20: Image-heavy sections | H20: Creative | I20: Level 1 | J20: =IFERROR(INDEX(Rates!$D$6:$D$15,MATCH(H20&"|"&I20,Rates!$C$6:$C$15,0)),0) -> 100 | K20: 5 | L20: =K20*J20 -> 500 | M20: Image sourcing, licensing, and retouching may be billed separately.
A21: 17 | C21: Homepage – Creative | D21: Parallax Effects | E21: 14 | F21: =IFERROR(INDEX(Categories!$B$5:$B$27,MATCH(E21,Categories!$A$5:$A$27,0)),"") -> Frontend | G21: Built-in scroll effects | H21: IT | I21: Level 2 | J21: =IFERROR(INDEX(Rates!$D$6:$D$15,MATCH(H21&"|"&I21,Rates!$C$6:$C$15,0)),0) -> 120 | K21: 3 | L21: =K21*J21 -> 360 | M21: Built-in scroll effects only. Limited compared to WordPress.
A22: 18 | C22: Homepage – Creative | D22: Hover Animations | E22: 14 | F22: =IFERROR(INDEX(Categories!$B$5:$B$27,MATCH(E22,Categories!$A$5:$A$27,0)),"") -> Frontend | G22: Basic interactions | H22: IT | I22: Level 1 | J22: =IFERROR(INDEX(Rates!$D$6:$D$15,MATCH(H22&"|"&I22,Rates!$C$6:$C$15,0)),0) -> 100 | K22: 3 | L22: =K22*J22 -> 300 | M22: Needs a touch-device fallback, which is easy to forget in the estimate.
A23: 19 | C23: Homepage – Creative | D23: Creative Layouts | E23: 14 | F23: =IFERROR(INDEX(Categories!$B$5:$B$27,MATCH(E23,Categories!$A$5:$A$27,0)),"") -> Frontend | G23: Flexible editor layouts | H23: IT | I23: Level 1 | J23: =IFERROR(INDEX(Rates!$D$6:$D$15,MATCH(H23&"|"&I23,Rates!$C$6:$C$15,0)),0) -> 100 | K23: 5 | L23: =K23*J23 -> 500 | M23: Responsive behavior on non-standard layouts is where the hours go.
A24: 20 | C24: Homepage – Conversion | D24: Lead Capture Form | E24: 14 | F24: =IFERROR(INDEX(Categories!$B$5:$B$27,MATCH(E24,Categories!$A$5:$A$27,0)),"") -> Frontend | G24: Wix Forms | H24: IT | I24: Level 1 | J24: =IFERROR(INDEX(Rates!$D$6:$D$15,MATCH(H24&"|"&I24,Rates!$C$6:$C$15,0)),0) -> 100 | K24: 2 | L24: =K24*J24 -> 200 | M24: CRM connection is billed separately.
A25: 21 | C25: Homepage – Conversion | D25: Forms Spam Protection | E25: 18 | F25: =IFERROR(INDEX(Categories!$B$5:$B$27,MATCH(E25,Categories!$A$5:$A$27,0)),"") -> Performance & Security | G25: Built-in spam protection | H25: IT | I25: Level 1 | J25: =IFERROR(INDEX(Rates!$D$6:$D$15,MATCH(H25&"|"&I25,Rates!$C$6:$C$15,0)),0) -> 100 | K25: 1 | L25: =K25*J25 -> 100 | M25: Covers all forms at once.
A26: 22 | C26: Core Page - Standard | D26: Standard Page (About, Services) | E26: 14 | F26: =IFERROR(INDEX(Categories!$B$5:$B$27,MATCH(E26,Categories!$A$5:$A$27,0)),"") -> Frontend | G26: Content pages | H26: IT | I26: Level 1 | J26: =IFERROR(INDEX(Rates!$D$6:$D$15,MATCH(H26&"|"&I26,Rates!$C$6:$C$15,0)),0) -> 100 | K26: 6 | L26: =K26*J26 -> 600 | M26: Per page. Multiply by page count and confirm the total in the quote.
A27: 23 | C27: Core Page - Landing Page | D27: Landing Page | E27: 14 | F27: =IFERROR(INDEX(Categories!$B$5:$B$27,MATCH(E27,Categories!$A$5:$A$27,0)),"") -> Frontend | G27: Conversion-focused layout | H27: IT | I27: Level 1 | J27: =IFERROR(INDEX(Rates!$D$6:$D$15,MATCH(H27&"|"&I27,Rates!$C$6:$C$15,0)),0) -> 100 | K27: 7 | L27: =K27*J27 -> 700 | M27: Per page. Second and later pages using the same layout should be cheaper.
A28: 24 | C28: Core Page - Contact Page | D28: Contact Page | E28: 14 | F28: =IFERROR(INDEX(Categories!$B$5:$B$27,MATCH(E28,Categories!$A$5:$A$27,0)),"") -> Frontend | G28: Form + contact info | H28: IT | I28: Level 1 | J28: =IFERROR(INDEX(Rates!$D$6:$D$15,MATCH(H28&"|"&I28,Rates!$C$6:$C$15,0)),0) -> 100 | K28: 5 | L28: =K28*J28 -> 500 | M28: Includes one form. Map embed and multi-location info may add time.
A29: 25 | C29: Core Page - Blog Detail | D29: Blog Post Template | E29: 22 | F29: =IFERROR(INDEX(Categories!$B$5:$B$27,MATCH(E29,Categories!$A$5:$A$27,0)),"") -> SEO & Content | G29: Wix blog | H29: IT | I29: Level 1 | J29: =IFERROR(INDEX(Rates!$D$6:$D$15,MATCH(H29&"|"&I29,Rates!$C$6:$C$15,0)),0) -> 100 | K29: 4 | L29: =K29*J29 -> 400 | M29: Related posts, author boxes, and share buttons add time.
A30: 26 | C30: Forms – Standard | D30: Form Setup | E30: 14 | F30: =IFERROR(INDEX(Categories!$B$5:$B$27,MATCH(E30,Categories!$A$5:$A$27,0)),"") -> Frontend | G30: Wix form setup + notifications | H30: IT | I30: Level 1 | J30: =IFERROR(INDEX(Rates!$D$6:$D$15,MATCH(H30&"|"&I30,Rates!$C$6:$C$15,0)),0) -> 100 | K30: 3 | L30: =K30*J30 -> 300 | M30: Priced per form. Confirm the form count before quoting.
A31: 27 | C31: Forms – Multi-Step | D31: Multi-Step Form | E31: 14 | F31: =IFERROR(INDEX(Categories!$B$5:$B$27,MATCH(E31,Categories!$A$5:$A$27,0)),"") -> Frontend | G31: Wix forms or apps (limited logic) | H31: IT | I31: Level 1 | J31: =IFERROR(INDEX(Rates!$D$6:$D$15,MATCH(H31&"|"&I31,Rates!$C$6:$C$15,0)),0) -> 100 | K31: 6 | L31: =K31*J31 -> 600 | M31: Step count drives hours. Note the assumed number of steps.
... A40: 36 | C40: Members Area | D40: Restricted Content | E40: 2 | F40: =IFERROR(INDEX(Categories!$B$5:$B$27,MATCH(E40,Categories!$A$5:$A$27,0)),"") -> Backend | G40: Gated pages/content | H40: IT | I40: Level 1 | J40: =IFERROR(INDEX(Rates!$D$6:$D$15,MATCH(H40&"|"&I40,Rates!$C$6:$C$15,0)),0) -> 100 | K40: 6 | L40: =K40*J40 -> 600 | M40: Hours scale with the number of roles and restriction rules.
A41: 37 | C41: E-Commerce | D41: Featured Products | E41: 12 | F41: =IFERROR(INDEX(Categories!$B$5:$B$27,MATCH(E41,Categories!$A$5:$A$27,0)),"") -> E-Commerce | G41: Product showcase | H41: IT | I41: Level 1 | J41: =IFERROR(INDEX(Rates!$D$6:$D$15,MATCH(H41&"|"&I41,Rates!$C$6:$C$15,0)),0) -> 100 | K41: 4 | L41: =K41*J41 -> 400
A42: 38 | C42: E-Commerce | D42: Sales Banners | E42: 12 | F42: =IFERROR(INDEX(Categories!$B$5:$B$27,MATCH(E42,Categories!$A$5:$A$27,0)),"") -> E-Commerce | G42: Promo banners | H42: Creative | I42: Level 1 | J42: =IFERROR(INDEX(Rates!$D$6:$D$15,MATCH(H42&"|"&I42,Rates!$C$6:$C$15,0)),0) -> 100 | K42: 3 | L42: =K42*J42 -> 300 | M42: Recurring campaign artwork is worth a separate maintenance line item.
A43: 39 | C43: E-Commerce | D43: Product Listings | E43: 12 | F43: =IFERROR(INDEX(Categories!$B$5:$B$27,MATCH(E43,Categories!$A$5:$A$27,0)),"") -> E-Commerce | G43: Wix Stores pages | H43: IT | I43: Level 1 | J43: =IFERROR(INDEX(Rates!$D$6:$D$15,MATCH(H43&"|"&I43,Rates!$C$6:$C$15,0)),0) -> 100 | K43: 5 | L43: =K43*J43 -> 500 | M43: Setup only. Per-product data entry is separate and often underestimated.
A44: 40 | C44: E-Commerce | D44: Category Pages | E44: 12 | F44: =IFERROR(INDEX(Categories!$B$5:$B$27,MATCH(E44,Categories!$A$5:$A$27,0)),"") -> E-Commerce | G44: Collections/categories | H44: IT | I44: Level 1 | J44: =IFERROR(INDEX(Rates!$D$6:$D$15,MATCH(H44&"|"&I44,Rates!$C$6:$C$15,0)),0) -> 100 | K44: 4 | L44: =K44*J44 -> 400
A45: 41 | C45: E-Commerce | D45: Product Detail Page | E45: 12 | F45: =IFERROR(INDEX(Categories!$B$5:$B$27,MATCH(E45,Categories!$A$5:$A$27,0)),"") -> E-Commerce | G45: Product page | H45: IT | I45: Level 1 | J45: =IFERROR(INDEX(Rates!$D$6:$D$15,MATCH(H45&"|"&I45,Rates!$C$6:$C$15,0)),0) -> 100 | K45: 5 | L45: =K45*J45 -> 500
A46: 42 | C46: E-Commerce | D46: Cart & Checkout | E46: 12 | F46: =IFERROR(INDEX(Categories!$B$5:$B$27,MATCH(E46,Categories!$A$5:$A$27,0)),"") -> E-Commerce | G46: Built-in checkout | H46: IT | I46: Level 1 | J46: =IFERROR(INDEX(Rates!$D$6:$D$15,MATCH(H46&"|"&I46,Rates!$C$6:$C$15,0)),0) -> 100 | K46: 4 | L46: =K46*J46 -> 400 | M46: Custom fields and guest checkout rules add time.
A47: 43 | C47: E-Commerce | D47: Payments Setup | E47: 12 | F47: =IFERROR(INDEX(Categories!$B$5:$B$27,MATCH(E47,Categories!$A$5:$A$27,0)),"") -> E-Commerce | G47: Wix Payments / Stripe | H47: IT | I47: Level 1 | J47: =IFERROR(INDEX(Rates!$D$6:$D$15,MATCH(H47&"|"&I47,Rates!$C$6:$C$15,0)),0) -> 100 | K47: 3 | L47: =K47*J47 -> 300 | M47: Excludes merchant account approval. Client delays are common.
A48: 44 | C48: E-Commerce | D48: Shipping Setup | E48: 12 | F48: =IFERROR(INDEX(Categories!$B$5:$B$27,MATCH(E48,Categories!$A$5:$A$27,0)),"") -> E-Commerce | G48: Shipping rules | H48: IT | I48: Level 1 | J48: =IFERROR(INDEX(Rates!$D$6:$D$15,MATCH(H48&"|"&I48,Rates!$C$6:$C$15,0)),0) -> 100 | K48: 3 | L48: =K48*J48 -> 300 | M48: Live carrier rates are more work than flat-rate zones.
A49: 45 | C49: E-Commerce | D49: Taxes Setup | E49: 12 | F49: =IFERROR(INDEX(Categories!$B$5:$B$27,MATCH(E49,Categories!$A$5:$A$27,0)),"") -> E-Commerce | G49: Tax config | H49: IT | I49: Level 1 | J49: =IFERROR(INDEX(Rates!$D$6:$D$15,MATCH(H49&"|"&I49,Rates!$C$6:$C$15,0)),0) -> 100 | K49: 2 | L49: =K49*J49 -> 200 | M49: Multi-state or international tax is a bigger scope.
A50: 46 | C50: Advanced | D50: Wix Dynamic Content (CMS) | E50: 14 | F50: =IFERROR(INDEX(Categories!$B$5:$B$27,MATCH(E50,Categories!$A$5:$A$27,0)),"") -> Frontend | G50: Wix CMS collections + repeaters | H50: IT | I50: Level 2 | J50: =IFERROR(INDEX(Rates!$D$6:$D$15,MATCH(H50&"|"&I50,Rates!$C$6:$C$15,0)),0) -> 120 | K50: 8 | L50: =K50*J50 -> 960 | M50: Wix CMS has collection and item limits. Check them against the client's data.
A51: 47 | C51: Advanced | D51: Custom Logic (Velo) | E51: 14 | F51: =IFERROR(INDEX(Categories!$B$5:$B$27,MATCH(E51,Categories!$A$5:$A$27,0)),"") -> Frontend | G51: Custom interactions using Velo | H51: IT | I51: Level 2 | J51: =IFERROR(INDEX(Rates!$D$6:$D$15,MATCH(H51&"|"&I51,Rates!$C$6:$C$15,0)),0) -> 120 | K51: 12 | L51: =K51*J51 -> 1440 | M51: Velo skills are less common. Confirm you have someone who can support it.
A52: 48 | C52: Advanced | D52: Filters & Search | E52: 14 | F52: =IFERROR(INDEX(Categories!$B$5:$B$27,MATCH(E52,Categories!$A$5:$A$27,0)),"") -> Frontend | G52: Dataset filtering/search | H52: IT | I52: Level 2 | J52: =IFERROR(INDEX(Rates!$D$6:$D$15,MATCH(H52&"|"&I52,Rates!$C$6:$C$15,0)),0) -> 120 | K52: 8 | L52: =K52*J52 -> 960 | M52: Dataset filtering performance degrades on large collections.
A53: 49 | C53: Advanced | D53: Basic Product Customization | E53: 14 | F53: =IFERROR(INDEX(Categories!$B$5:$B$27,MATCH(E53,Categories!$A$5:$A$27,0)),"") -> Frontend | G53: Product options or apps | H53: IT | I53: Level 2 | J53: =IFERROR(INDEX(Rates!$D$6:$D$15,MATCH(H53&"|"&I53,Rates!$C$6:$C$15,0)),0) -> 120 | K53: 10 | L53: =K53*J53 -> 1200 | M53: Excludes app costs. Wix product options are limited.
A54: 50 | C54: Performance | D54: Basic Optimization | E54: 18 | F54: =IFERROR(INDEX(Categories!$B$5:$B$27,MATCH(E54,Categories!$A$5:$A$27,0)),"") -> Performance & Security | G54: Image + layout optimization | H54: IT | I54: Level 1 | J54: =IFERROR(INDEX(Rates!$D$6:$D$15,MATCH(H54&"|"&I54,Rates!$C$6:$C$15,0)),0) -> 100 | K54: 4 | L54: =K54*J54 -> 400 | M54: Wix gives you little performance control. Never guarantee a score.
A55: 51 | C55: Analytics | D55: GA4 Setup | E55: 4 | F55: =IFERROR(INDEX(Categories!$B$5:$B$27,MATCH(E55,Categories!$A$5:$A$27,0)),"") -> Conversion Tracking | G55: Add GA4 | H55: IT | I55: Level 1 | J55: =IFERROR(INDEX(Rates!$D$6:$D$15,MATCH(H55&"|"&I55,Rates!$C$6:$C$15,0)),0) -> 100 | K55: 2 | L55: =K55*J55 -> 200 | M55: Assumes client already has a Google account. Access delays are common.
A56: 52 | C56: Analytics | D56: GTM Setup | E56: 4 | F56: =IFERROR(INDEX(Categories!$B$5:$B$27,MATCH(E56,Categories!$A$5:$A$27,0)),"") -> Conversion Tracking | G56: Add GTM | H56: IT | I56: Level 1 | J56: =IFERROR(INDEX(Rates!$D$6:$D$15,MATCH(H56&"|"&I56,Rates!$C$6:$C$15,0)),0) -> 100 | K56: 3 | L56: =K56*J56 -> 300 | M56: Tag count drives hours. Note how many tags are included.
A57: 53 | C57: Analytics | D57: Conversion Tracking | E57: 4 | F57: =IFERROR(INDEX(Categories!$B$5:$B$27,MATCH(E57,Categories!$A$5:$A$27,0)),"") -> Conversion Tracking | G57: Events + testing | H57: IT | I57: Level 1 | J57: =IFERROR(INDEX(Rates!$D$6:$D$15,MATCH(H57&"|"&I57,Rates!$C$6:$C$15,0)),0) -> 100 | K57: 5 | L57: =K57*J57 -> 500 | M57: Event count drives hours. Cap the number of events in the quote.
A58: 54 | C58: Blog | D58: Blog Setup | E58: 22 | F58: =IFERROR(INDEX(Categories!$B$5:$B$27,MATCH(E58,Categories!$A$5:$A$27,0)),"") -> SEO & Content | G58: Blog listing | H58: IT | I58: Level 1 | J58: =IFERROR(INDEX(Rates!$D$6:$D$15,MATCH(H58&"|"&I58,Rates!$C$6:$C$15,0)),0) -> 100 | K58: 2 | L58: =K58*J58 -> 200 | M58: Category filtering and pagination styling may add time.
A59: 55 | C59: Blog | D59: Single Post Template | E59: 22 | F59: =IFERROR(INDEX(Categories!$B$5:$B$27,MATCH(E59,Categories!$A$5:$A$27,0)),"") -> SEO & Content | G59: Default template | H59: IT | I59: Level 1 | J59: =IFERROR(INDEX(Rates!$D$6:$D$15,MATCH(H59&"|"&I59,Rates!$C$6:$C$15,0)),0) -> 100 | K59: 1 | L59: =K59*J59 -> 100
A60: 56 | C60: Blog | D60: Lead Capture Integration | E60: 22 | F60: =IFERROR(INDEX(Categories!$B$5:$B$27,MATCH(E60,Categories!$A$5:$A$27,0)),"") -> SEO & Content | G60: Newsletter form | H60: IT | I60: Level 1 | J60: =IFERROR(INDEX(Rates!$D$6:$D$15,MATCH(H60&"|"&I60,Rates!$C$6:$C$15,0)),0) -> 100 | K60: 2 | L60: =K60*J60 -> 200 | M60: Email platform connection (Mailchimp etc.) may need integration hours.
A61: 57 | C61: SEO | D61: Basic SEO Setup | E61: 22 | F61: =IFERROR(INDEX(Categories!$B$5:$B$27,MATCH(E61,Categories!$A$5:$A$27,0)),"") -> SEO & Content | G61: Titles + meta | H61: IT | I61: Level 1 | J61: =IFERROR(INDEX(Rates!$D$6:$D$15,MATCH(H61&"|"&I61,Rates!$C$6:$C$15,0)),0) -> 100 | K61: 2 | L61: =K61*J61 -> 200 | M61: Excludes keyword research and strategy, which are separate services.
A62: 58 | C62: SEO | D62: Schema (Basic) | E62: 24 | F62: =IFERROR(INDEX(Categories!$B$5:$B$27,MATCH(E62,Categories!$A$5:$A$27,0)),"") -> SEO on-page | G62: Wix SEO tools | H62: IT | I62: Level 1 | J62: =IFERROR(INDEX(Rates!$D$6:$D$15,MATCH(H62&"|"&I62,Rates!$C$6:$C$15,0)),0) -> 100 | K62: 2 | L62: =K62*J62 -> 200 | M62: Per schema type. Platform tools limit how far you can go.
A63: 59 | C63: SEO | D63: Sitemap (Auto) | E63: 24 | F63: =IFERROR(INDEX(Categories!$B$5:$B$27,MATCH(E63,Categories!$A$5:$A$27,0)),"") -> SEO on-page | G63: Auto-generated | H63: IT | I63: Level 1 | J63: =IFERROR(INDEX(Rates!$D$6:$D$15,MATCH(H63&"|"&I63,Rates!$C$6:$C$15,0)),0) -> 100 | K63: 0 | L63: =K63*J63 -> 0 | M63: Zero hours. Keep it as an 'included free' talking point or delete the row.
A64: 60 | C64: SEO | D64: URL Redirects | E64: 24 | F64: =IFERROR(INDEX(Categories!$B$5:$B$27,MATCH(E64,Categories!$A$5:$A$27,0)),"") -> SEO on-page | G64: Redirect manager | H64: IT | I64: Level 1 | J64: =IFERROR(INDEX(Rates!$D$6:$D$15,MATCH(H64&"|"&I64,Rates!$C$6:$C$15,0)),0) -> 100 | K64: 2 | L64: =K64*J64 -> 200 | M64: Large migrations need a URL mapping exercise first.
A65: 61 | C65: SEO | D65: Content Optimization | E65: 22 | F65: =IFERROR(INDEX(Categories!$B$5:$B$27,MATCH(E65,Categories!$A$5:$A$27,0)),"") -> SEO & Content | G65: On-page SEO | H65: Creative | I65: Level 1 | J65: =IFERROR(INDEX(Rates!$D$6:$D$15,MATCH(H65&"|"&I65,Rates!$C$6:$C$15,0)),0) -> 100 | K65: 3 | L65: =K65*J65 -> 300 | M65: Per page. Define how many revision rounds are included.
A66: 62 | C66: Environment Setup | D66: Wix Site Setup | E66: 13 | F66: =IFERROR(INDEX(Categories!$B$5:$B$27,MATCH(E66,Categories!$A$5:$A$27,0)),"") -> Environment Setup | G66: Create site | H66: IT | I66: Level 1 | J66: =IFERROR(INDEX(Rates!$D$6:$D$15,MATCH(H66&"|"&I66,Rates!$C$6:$C$15,0)),0) -> 100 | K66: 2 | L66: =K66*J66 -> 200 | M66: Excludes the Wix subscription.
A67: 63 | C67: Environment Setup | D67: Template & Design Setup | E67: 13 | F67: =IFERROR(INDEX(Categories!$B$5:$B$27,MATCH(E67,Categories!$A$5:$A$27,0)),"") -> Environment Setup | G67: Editor + styles | H67: IT | I67: Level 1 | J67: =IFERROR(INDEX(Rates!$D$6:$D$15,MATCH(H67&"|"&I67,Rates!$C$6:$C$15,0)),0) -> 100 | K67: 4 | L67: =K67*J67 -> 400 | M67: Wix templates cannot be swapped after launch. Choose carefully.
A68: 64 | C68: Environment Setup | D68: Domain Setup | E68: 13 | F68: =IFERROR(INDEX(Categories!$B$5:$B$27,MATCH(E68,Categories!$A$5:$A$27,0)),"") -> Environment Setup | G68: Connect domain | H68: IT | I68: Level 1 | J68: =IFERROR(INDEX(Rates!$D$6:$D$15,MATCH(H68&"|"&I68,Rates!$C$6:$C$15,0)),0) -> 100 | K68: 2 | L68: =K68*J68 -> 200 | M68: DNS propagation affects the schedule but is not billable work.
A69: 65 | C69: Content Entry | D69: Content Upload | E69: 3 | F69: =IFERROR(INDEX(Categories!$B$5:$B$27,MATCH(E69,Categories!$A$5:$A$27,0)),"") -> CMS & Content Prep | G69: Add content/products | H69: Project Coordinator | I69: Level 1 | J69: =IFERROR(INDEX(Rates!$D$6:$D$15,MATCH(H69&"|"&I69,Rates!$C$6:$C$15,0)),0) -> 0 | K69: 3 | L69: =K69*J69 -> 0 | M69: Per page or per batch, and often badly underestimated. Assumes final content from the client.
A70: 66 | C70: Content Entry | D70: Media Optimization | E70: 3 | F70: =IFERROR(INDEX(Categories!$B$5:$B$27,MATCH(E70,Categories!$A$5:$A$27,0)),"") -> CMS & Content Prep | G70: Image optimization | H70: IT | I70: Level 1 | J70: =IFERROR(INDEX(Rates!$D$6:$D$15,MATCH(H70&"|"&I70,Rates!$C$6:$C$15,0)),0) -> 100 | K70: 2 | L70: =K70*J70 -> 200 | M70: Scales with image count. A large gallery or catalog needs more.
A71: 67 | C71: Pre-Launch QA | D71: QA Review | E71: 25 | F71: =IFERROR(INDEX(Categories!$B$5:$B$27,MATCH(E71,Categories!$A$5:$A$27,0)),"") -> QA & Testing | G71: Test responsiveness + features | H71: QA Tester | I71: Level 1 | J71: =IFERROR(INDEX(Rates!$D$6:$D$15,MATCH(H71&"|"&I71,Rates!$C$6:$C$15,0)),0) -> 80 | K71: 4 | L71: =K71*J71 -> 320 | M71: Scales with page count and feature count. Thin for a large site.
... A73: 69 | C73: Post-Launch | D73: QA Fixes | E73: 25 | F73: =IFERROR(INDEX(Categories!$B$5:$B$27,MATCH(E73,Categories!$A$5:$A$27,0)),"") -> QA & Testing | G73: Bug fixes | H73: QA Tester | I73: Level 1 | J73: =IFERROR(INDEX(Rates!$D$6:$D$15,MATCH(H73&"|"&I73,Rates!$C$6:$C$15,0)),0) -> 80 | K73: 4 | L73: =K73*J73 -> 320 | M73: Define a support window, or this becomes unlimited free work.
A74: 70 | C74: Post-Launch | D74: Tracking Verification | E74: 4 | F74: =IFERROR(INDEX(Categories!$B$5:$B$27,MATCH(E74,Categories!$A$5:$A$27,0)),"") -> Conversion Tracking | G74: Verify analytics | H74: QA Tester | I74: Level 1 | J74: =IFERROR(INDEX(Rates!$D$6:$D$15,MATCH(H74&"|"&I74,Rates!$C$6:$C$15,0)),0) -> 80 | K74: 2 | L74: =K74*J74 -> 160
D76: TOTAL | K76: =SUM(K5:K74) -> 269 | L76: =SUM(L5:L74) -> 27780 | M76: Whole library total, not a project quote. Quote only the tasks a job needs.

Sheet PHP-HTML-CSS
A1: Task Pricing – PHP / HTML / CSS
A2: Base Hours unchanged. category_id has been remapped to the new Categories list.
A4: id | B4: Dependencies | C4: Module | D4: Name | E4: category_id | F4: Category | G4: Description | H4: Responsible | I4: Level | J4: Rate | K4: Base Hours | L4: Estimated Cost | M4: Hours – Things to Consider
A5: 1 | C5: Homepage – Standard | D5: Hero Section | E5: 14 | F5: =IFERROR(INDEX(Categories!$B$5:$B$27,MATCH(E5,Categories!$A$5:$A$27,0)),"") -> Frontend | G5: Hero section and headline | H5: IT | I5: Level 1 | J5: =IFERROR(INDEX(Rates!$D$6:$D$15,MATCH(H5&"|"&I5,Rates!$C$6:$C$15,0)),0) -> 100 | K5: 2 | L5: =K5*J5 -> 200
A6: 2 | C6: Homepage – Standard | D6: Services or Product Grid | E6: 14 | F6: =IFERROR(INDEX(Categories!$B$5:$B$27,MATCH(E6,Categories!$A$5:$A$27,0)),"") -> Frontend | G6: Custom grid layout for services/products | H6: IT | I6: Level 1 | J6: =IFERROR(INDEX(Rates!$D$6:$D$15,MATCH(H6&"|"&I6,Rates!$C$6:$C$15,0)),0) -> 100 | K6: 3 | L6: =K6*J6 -> 300 | M6: Assumes a fixed number of items. Dynamic, data-driven grids cost more.
A7: 3 | C7: Homepage – Standard | D7: Testimonials Slider (Dynamic) | E7: 15 | F7: =IFERROR(INDEX(Categories!$B$5:$B$27,MATCH(E7,Categories!$A$5:$A$27,0)),"") -> Integration | G7: Dynamic testimonials via DB/API | H7: IT | I7: Level 2 | J7: =IFERROR(INDEX(Rates!$D$6:$D$15,MATCH(H7&"|"&I7,Rates!$C$6:$C$15,0)),0) -> 120 | K7: 8 | L7: =K7*J7 -> 960 | M7: Depends on the review platform's API. Add hours for keys, rate limits, and caching.
A8: 4 | C8: Homepage – Standard | D8: Testimonials (Embed) | E8: 15 | F8: =IFERROR(INDEX(Categories!$B$5:$B$27,MATCH(E8,Categories!$A$5:$A$27,0)),"") -> Integration | G8: Embedded testimonials | H8: IT | I8: Level 1 | J8: =IFERROR(INDEX(Rates!$D$6:$D$15,MATCH(H8&"|"&I8,Rates!$C$6:$C$15,0)),0) -> 100 | K8: 3 | L8: =K8*J8 -> 300 | M8: Styling a third-party widget can take longer than expected if the platform limits CSS.
A9: 5 | C9: Homepage – Standard | D9: Team Preview | E9: 14 | F9: =IFERROR(INDEX(Categories!$B$5:$B$27,MATCH(E9,Categories!$A$5:$A$27,0)),"") -> Frontend | G9: Team members section | H9: IT | I9: Level 1 | J9: =IFERROR(INDEX(Rates!$D$6:$D$15,MATCH(H9&"|"&I9,Rates!$C$6:$C$15,0)),0) -> 100 | K9: 1.5 | L9: =K9*J9 -> 150 | M9: Bios and photo cropping are content work, not build work.
A10: 6 | C10: Homepage – Standard | D10: Footer Layout | E10: 14 | F10: =IFERROR(INDEX(Categories!$B$5:$B$27,MATCH(E10,Categories!$A$5:$A$27,0)),"") -> Frontend | G10: Footer with navigation and contact info | H10: IT | I10: Level 1 | J10: =IFERROR(INDEX(Rates!$D$6:$D$15,MATCH(H10&"|"&I10,Rates!$C$6:$C$15,0)),0) -> 100 | K10: 1.5 | L10: =K10*J10 -> 150 | M10: Mega-footers with multiple menus and a newsletter form run higher.
A11: 7 | C11: Homepage – Conversion | D11: Strong Hero Offer | E11: 14 | F11: =IFERROR(INDEX(Categories!$B$5:$B$27,MATCH(E11,Categories!$A$5:$A$27,0)),"") -> Frontend | G11: Hero with CTA | H11: IT | I11: Level 1 | J11: =IFERROR(INDEX(Rates!$D$6:$D$15,MATCH(H11&"|"&I11,Rates!$C$6:$C$15,0)),0) -> 100 | K11: 4 | L11: =K11*J11 -> 400
A12: 8 | C12: Homepage – Conversion | D12: Benefits/Features | E12: 14 | F12: =IFERROR(INDEX(Categories!$B$5:$B$27,MATCH(E12,Categories!$A$5:$A$27,0)),"") -> Frontend | G12: Feature sections | H12: IT | I12: Level 1 | J12: =IFERROR(INDEX(Rates!$D$6:$D$15,MATCH(H12&"|"&I12,Rates!$C$6:$C$15,0)),0) -> 100 | K12: 3 | L12: =K12*J12 -> 300 | M12: Icon sourcing or custom icons may need Creative hours on top.
A13: 9 | C13: Homepage – Conversion | D13: Social Proof / Trust Badges | E13: 14 | F13: =IFERROR(INDEX(Categories!$B$5:$B$27,MATCH(E13,Categories!$A$5:$A$27,0)),"") -> Frontend | G13: Logos and credibility indicators | H13: IT | I13: Level 1 | J13: =IFERROR(INDEX(Rates!$D$6:$D$15,MATCH(H13&"|"&I13,Rates!$C$6:$C$15,0)),0) -> 100 | K13: 2 | L13: =K13*J13 -> 200 | M13: Assumes client supplies logos in usable formats. Logo cleanup is Creative time.
A14: 10 | C14: Homepage – Conversion | D14: FAQ Section | E14: 14 | F14: =IFERROR(INDEX(Categories!$B$5:$B$27,MATCH(E14,Categories!$A$5:$A$27,0)),"") -> Frontend | G14: FAQ block | H14: IT | I14: Level 1 | J14: =IFERROR(INDEX(Rates!$D$6:$D$15,MATCH(H14&"|"&I14,Rates!$C$6:$C$15,0)),0) -> 100 | K14: 2 | L14: =K14*J14 -> 200 | M14: Add a little time if FAQ schema markup is also required.
A15: 11 | C15: Homepage – Standard | D15: Pricing Tables | E15: 14 | F15: =IFERROR(INDEX(Categories!$B$5:$B$27,MATCH(E15,Categories!$A$5:$A$27,0)),"") -> Frontend | G15: Pricing layout | H15: IT | I15: Level 1 | J15: =IFERROR(INDEX(Rates!$D$6:$D$15,MATCH(H15&"|"&I15,Rates!$C$6:$C$15,0)),0) -> 100 | K15: 4 | L15: =K15*J15 -> 400 | M15: Monthly/annual toggles or more than 3 plans push this higher.
A16: 12 | C16: Homepage – Standard | D16: Galleries | E16: 14 | F16: =IFERROR(INDEX(Categories!$B$5:$B$27,MATCH(E16,Categories!$A$5:$A$27,0)),"") -> Frontend | G16: Custom gallery | H16: IT | I16: Level 1 | J16: =IFERROR(INDEX(Rates!$D$6:$D$15,MATCH(H16&"|"&I16,Rates!$C$6:$C$15,0)),0) -> 100 | K16: 2 | L16: =K16*J16 -> 200 | M16: Per gallery. Image prep is billed separately.
A17: 13 | C17: Homepage – Standard | D17: Video Embeds | E17: 14 | F17: =IFERROR(INDEX(Categories!$B$5:$B$27,MATCH(E17,Categories!$A$5:$A$27,0)),"") -> Frontend | G17: Video embeds | H17: IT | I17: Level 1 | J17: =IFERROR(INDEX(Rates!$D$6:$D$15,MATCH(H17&"|"&I17,Rates!$C$6:$C$15,0)),0) -> 100 | K17: 1 | L17: =K17*J17 -> 100 | M17: Self-hosted video or custom players are a different, larger scope.
A18: 14 | C18: Homepage – Standard | D18: Payment / Contribution Module | E18: 15 | F18: =IFERROR(INDEX(Categories!$B$5:$B$27,MATCH(E18,Categories!$A$5:$A$27,0)),"") -> Integration | G18: Stripe/PayPal integration | H18: IT | I18: Level 2 | J18: =IFERROR(INDEX(Rates!$D$6:$D$15,MATCH(H18&"|"&I18,Rates!$C$6:$C$15,0)),0) -> 120 | K18: 6 | L18: =K18*J18 -> 720 | M18: Excludes merchant account setup. Test-mode and live-mode testing both take time.
A19: 15 | C19: Homepage – Standard | D19: Use Cases | E19: 14 | F19: =IFERROR(INDEX(Categories!$B$5:$B$27,MATCH(E19,Categories!$A$5:$A$27,0)),"") -> Frontend | G19: Use case sections | H19: IT | I19: Level 1 | J19: =IFERROR(INDEX(Rates!$D$6:$D$15,MATCH(H19&"|"&I19,Rates!$C$6:$C$15,0)),0) -> 100 | K19: 2 | L19: =K19*J19 -> 200
A20: 16 | C20: Homepage – Multi-Industry | D20: Industry Selector | E20: 14 | F20: =IFERROR(INDEX(Categories!$B$5:$B$27,MATCH(E20,Categories!$A$5:$A$27,0)),"") -> Frontend | G20: Dynamic selector | H20: IT | I20: Level 2 | J20: =IFERROR(INDEX(Rates!$D$6:$D$15,MATCH(H20&"|"&I20,Rates!$C$6:$C$15,0)),0) -> 120 | K20: 8 | L20: =K20*J20 -> 960 | M20: Hours scale with the number of industries. Confirm a cap in the quote.
A21: 17 | C21: Homepage – Multi-Industry | D21: Location Selector | E21: 14 | F21: =IFERROR(INDEX(Categories!$B$5:$B$27,MATCH(E21,Categories!$A$5:$A$27,0)),"") -> Frontend | G21: Location-based content | H21: IT | I21: Level 2 | J21: =IFERROR(INDEX(Rates!$D$6:$D$15,MATCH(H21&"|"&I21,Rates!$C$6:$C$15,0)),0) -> 120 | K21: 8 | L21: =K21*J21 -> 960 | M21: Hours scale with the number of locations. Confirm a cap in the quote.
A22: 18 | C22: Homepage – Multi-Industry | D22: Dynamic Content Sections | E22: 14 | F22: =IFERROR(INDEX(Categories!$B$5:$B$27,MATCH(E22,Categories!$A$5:$A$27,0)),"") -> Frontend | G22: Conditional rendering | H22: IT | I22: Level 2 | J22: =IFERROR(INDEX(Rates!$D$6:$D$15,MATCH(H22&"|"&I22,Rates!$C$6:$C$15,0)),0) -> 120 | K22: 10 | L22: =K22*J22 -> 1200 | M22: Each extra rule adds testing time, not just build time.
A23: 19 | C23: Homepage – Multi-Industry | D23: Interactive Location Finder | E23: 15 | F23: =IFERROR(INDEX(Categories!$B$5:$B$27,MATCH(E23,Categories!$A$5:$A$27,0)),"") -> Integration | G23: Map-based finder | H23: IT | I23: Level 2 | J23: =IFERROR(INDEX(Rates!$D$6:$D$15,MATCH(H23&"|"&I23,Rates!$C$6:$C$15,0)),0) -> 120 | K23: 12 | L23: =K23*J23 -> 1440 | M23: Excludes map API billing. Radius search and geolocation add hours.
A24: 20 | C24: Homepage – Multi-Industry | D24: Multi-Audience Messaging | E24: 14 | F24: =IFERROR(INDEX(Categories!$B$5:$B$27,MATCH(E24,Categories!$A$5:$A$27,0)),"") -> Frontend | G24: Personalized content | H24: IT | I24: Level 2 | J24: =IFERROR(INDEX(Rates!$D$6:$D$15,MATCH(H24&"|"&I24,Rates!$C$6:$C$15,0)),0) -> 120 | K24: 10 | L24: =K24*J24 -> 1200 | M24: Content writing for each segment is separate from the build.
A25: 21 | C25: Homepage – Advanced Dynamic | D25: Custom-Coded Blocks | E25: 14 | F25: =IFERROR(INDEX(Categories!$B$5:$B$27,MATCH(E25,Categories!$A$5:$A$27,0)),"") -> Frontend | G25: Reusable components | H25: IT | I25: Level 2 | J25: =IFERROR(INDEX(Rates!$D$6:$D$15,MATCH(H25&"|"&I25,Rates!$C$6:$C$15,0)),0) -> 120 | K25: 15 | L25: =K25*J25 -> 1800 | M25: Hours depend on how many blocks. Define the block count in the quote.
A26: 22 | C26: Homepage – Advanced Dynamic | D26: Search Bar with Filters | E26: 14 | F26: =IFERROR(INDEX(Categories!$B$5:$B$27,MATCH(E26,Categories!$A$5:$A$27,0)),"") -> Frontend | G26: Advanced filtering/search | H26: IT | I26: Level 2 | J26: =IFERROR(INDEX(Rates!$D$6:$D$15,MATCH(H26&"|"&I26,Rates!$C$6:$C$15,0)),0) -> 120 | K26: 18 | L26: =K26*J26 -> 2160 | M26: AJAX filtering, large datasets, and combined filters all add time.
A27: 23 | C27: Homepage – Advanced Dynamic | D27: API-Driven Content | E27: 14 | F27: =IFERROR(INDEX(Categories!$B$5:$B$27,MATCH(E27,Categories!$A$5:$A$27,0)),"") -> Frontend | G27: External API integrations | H27: IT | I27: Level 2 | J27: =IFERROR(INDEX(Rates!$D$6:$D$15,MATCH(H27&"|"&I27,Rates!$C$6:$C$15,0)),0) -> 120 | K27: 15 | L27: =K27*J27 -> 1800 | M27: Poorly documented or unstable third-party APIs are the biggest overrun risk.
A28: 24 | C28: Homepage – Advanced Dynamic | D28: Interactive Dashboard | E28: 5 | F28: =IFERROR(INDEX(Categories!$B$5:$B$27,MATCH(E28,Categories!$A$5:$A$27,0)),"") -> Custom Tools | G28: Charts and data dashboards | H28: IT | I28: Level 2 | J28: =IFERROR(INDEX(Rates!$D$6:$D$15,MATCH(H28&"|"&I28,Rates!$C$6:$C$15,0)),0) -> 120 | K28: 20 | L28: =K28*J28 -> 2400 | M28: Chart count, data sources, and export features drive the real number. Scope tightly.
A29: 25 | C29: Homepage – Creative | D29: Full-Screen Visuals | E29: 14 | F29: =IFERROR(INDEX(Categories!$B$5:$B$27,MATCH(E29,Categories!$A$5:$A$27,0)),"") -> Frontend | G29: Image-heavy layouts | H29: Creative | I29: Level 1 | J29: =IFERROR(INDEX(Rates!$D$6:$D$15,MATCH(H29&"|"&I29,Rates!$C$6:$C$15,0)),0) -> 100 | K29: 6 | L29: =K29*J29 -> 600 | M29: Image sourcing, licensing, and retouching may be billed separately.
A30: 26 | C30: Homepage – Creative | D30: Parallax Effects | E30: 14 | F30: =IFERROR(INDEX(Categories!$B$5:$B$27,MATCH(E30,Categories!$A$5:$A$27,0)),"") -> Frontend | G30: Scroll animations | H30: IT | I30: Level 2 | J30: =IFERROR(INDEX(Rates!$D$6:$D$15,MATCH(H30&"|"&I30,Rates!$C$6:$C$15,0)),0) -> 120 | K30: 5 | L30: =K30*J30 -> 600 | M30: Mobile performance testing usually takes as long as the build.
A31: 27 | C31: Homepage – Creative | D31: Hover Animations | E31: 14 | F31: =IFERROR(INDEX(Categories!$B$5:$B$27,MATCH(E31,Categories!$A$5:$A$27,0)),"") -> Frontend | G31: Custom interactions | H31: IT | I31: Level 1 | J31: =IFERROR(INDEX(Rates!$D$6:$D$15,MATCH(H31&"|"&I31,Rates!$C$6:$C$15,0)),0) -> 100 | K31: 4 | L31: =K31*J31 -> 400 | M31: Needs a touch-device fallback, which is easy to forget in the estimate.
... A35: 31 | C35: Homepage – Conversion | D35: Forms Spam Protection | E35: 18 | F35: =IFERROR(INDEX(Categories!$B$5:$B$27,MATCH(E35,Categories!$A$5:$A$27,0)),"") -> Performance & Security | G35: reCAPTCHA / validation | H35: IT | I35: Level 1 | J35: =IFERROR(INDEX(Rates!$D$6:$D$15,MATCH(H35&"|"&I35,Rates!$C$6:$C$15,0)),0) -> 100 | K35: 2 | L35: =K35*J35 -> 200 | M35: Covers all forms at once.
A36: 32 | C36: Homepage – Advanced Dynamic | D36: Multi-Step Wizard Form | E36: 14 | F36: =IFERROR(INDEX(Categories!$B$5:$B$27,MATCH(E36,Categories!$A$5:$A$27,0)),"") -> Frontend | G36: Custom multi-step form | H36: IT | I36: Level 2 | J36: =IFERROR(INDEX(Rates!$D$6:$D$15,MATCH(H36&"|"&I36,Rates!$C$6:$C$15,0)),0) -> 120 | K36: 18 | L36: =K36*J36 -> 2160
A37: 33 | C37: Core Page - Standard | D37: Standard Page (About, Services) | E37: 14 | F37: =IFERROR(INDEX(Categories!$B$5:$B$27,MATCH(E37,Categories!$A$5:$A$27,0)),"") -> Frontend | G37: Content page | H37: IT | I37: Level 1 | J37: =IFERROR(INDEX(Rates!$D$6:$D$15,MATCH(H37&"|"&I37,Rates!$C$6:$C$15,0)),0) -> 100 | K37: 8 | L37: =K37*J37 -> 800 | M37: Per page. Multiply by page count and confirm the total in the quote.
A38: 34 | C38: Core Page - Landing Page | D38: Landing Page | E38: 14 | F38: =IFERROR(INDEX(Categories!$B$5:$B$27,MATCH(E38,Categories!$A$5:$A$27,0)),"") -> Frontend | G38: Conversion-focused page | H38: IT | I38: Level 1 | J38: =IFERROR(INDEX(Rates!$D$6:$D$15,MATCH(H38&"|"&I38,Rates!$C$6:$C$15,0)),0) -> 100 | K38: 8 | L38: =K38*J38 -> 800 | M38: Per page. Second and later pages using the same layout should be cheaper.
A39: 35 | C39: Core Page - Contact Page | D39: Contact Page | E39: 14 | F39: =IFERROR(INDEX(Categories!$B$5:$B$27,MATCH(E39,Categories!$A$5:$A$27,0)),"") -> Frontend | G39: Form + contact details | H39: IT | I39: Level 1 | J39: =IFERROR(INDEX(Rates!$D$6:$D$15,MATCH(H39&"|"&I39,Rates!$C$6:$C$15,0)),0) -> 100 | K39: 6 | L39: =K39*J39 -> 600 | M39: Includes one form. Map embed and multi-location info may add time.
A40: 36 | C40: Core Page - Detail Pages | D40: Detail Page Template | E40: 14 | F40: =IFERROR(INDEX(Categories!$B$5:$B$27,MATCH(E40,Categories!$A$5:$A$27,0)),"") -> Frontend | G40: Dynamic template | H40: IT | I40: Level 1 | J40: =IFERROR(INDEX(Rates!$D$6:$D$15,MATCH(H40&"|"&I40,Rates!$C$6:$C$15,0)),0) -> 100 | K40: 6 | L40: =K40*J40 -> 600 | M40: Per template. Each additional content type usually needs its own template.
A41: 37 | C41: Forms – Standard | D41: Form Layout | E41: 14 | F41: =IFERROR(INDEX(Categories!$B$5:$B$27,MATCH(E41,Categories!$A$5:$A$27,0)),"") -> Frontend | G41: Frontend form UI | H41: IT | I41: Level 1 | J41: =IFERROR(INDEX(Rates!$D$6:$D$15,MATCH(H41&"|"&I41,Rates!$C$6:$C$15,0)),0) -> 100 | K41: 2 | L41: =K41*J41 -> 200 | M41: Frontend only. Validation and email are separate lines.
A42: 38 | C42: Forms – Standard | D42: Validation & Error Handling | E42: 14 | F42: =IFERROR(INDEX(Categories!$B$5:$B$27,MATCH(E42,Categories!$A$5:$A$27,0)),"") -> Frontend | G42: Client + server validation | H42: IT | I42: Level 1 | J42: =IFERROR(INDEX(Rates!$D$6:$D$15,MATCH(H42&"|"&I42,Rates!$C$6:$C$15,0)),0) -> 100 | K42: 2 | L42: =K42*J42 -> 200 | M42: Client-side and server-side are both needed. Do not skip server-side.
A43: 39 | C43: Forms – Standard | D43: Email Notification | E43: 14 | F43: =IFERROR(INDEX(Categories!$B$5:$B$27,MATCH(E43,Categories!$A$5:$A$27,0)),"") -> Frontend | G43: Send submission emails | H43: IT | I43: Level 1 | J43: =IFERROR(INDEX(Rates!$D$6:$D$15,MATCH(H43&"|"&I43,Rates!$C$6:$C$15,0)),0) -> 100 | K43: 2 | L43: =K43*J43 -> 200 | M43: Deliverability setup (SPF/DKIM) may add time and is easy to forget.
A44: 40 | C44: Forms – Multi-Step | D44: Multi-Step Layout | E44: 14 | F44: =IFERROR(INDEX(Categories!$B$5:$B$27,MATCH(E44,Categories!$A$5:$A$27,0)),"") -> Frontend | G44: Multi-step UI | H44: IT | I44: Level 2 | J44: =IFERROR(INDEX(Rates!$D$6:$D$15,MATCH(H44&"|"&I44,Rates!$C$6:$C$15,0)),0) -> 120 | K44: 4 | L44: =K44*J44 -> 480 | M44: Step count drives hours. Note the assumed number of steps.
A45: 41 | C45: Forms – Multi-Step | D45: Branch Logic Implementation | E45: 14 | F45: =IFERROR(INDEX(Categories!$B$5:$B$27,MATCH(E45,Categories!$A$5:$A$27,0)),"") -> Frontend | G45: Conditional logic | H45: IT | I45: Level 2 | J45: =IFERROR(INDEX(Rates!$D$6:$D$15,MATCH(H45&"|"&I45,Rates!$C$6:$C$15,0)),0) -> 120 | K45: 4 | L45: =K45*J45 -> 480 | M45: Testing every branch path often exceeds build time. Add QA hours.
A46: 42 | C46: Forms – Multi-Step | D46: Submission Handling | E46: 2 | F46: =IFERROR(INDEX(Categories!$B$5:$B$27,MATCH(E46,Categories!$A$5:$A$27,0)),"") -> Backend | G46: Process/store submissions | H46: IT | I46: Level 2 | J46: =IFERROR(INDEX(Rates!$D$6:$D$15,MATCH(H46&"|"&I46,Rates!$C$6:$C$15,0)),0) -> 120 | K46: 2 | L46: =K46*J46 -> 240 | M46: Partial-save and resume functionality would add substantially.
A47: 43 | C47: Forms – CRM Integration | D47: CRM API Setup | E47: 15 | F47: =IFERROR(INDEX(Categories!$B$5:$B$27,MATCH(E47,Categories!$A$5:$A$27,0)),"") -> Integration | G47: Connect to CRM | H47: IT | I47: Level 2 | J47: =IFERROR(INDEX(Rates!$D$6:$D$15,MATCH(H47&"|"&I47,Rates!$C$6:$C$15,0)),0) -> 120 | K47: 4 | L47: =K47*J47 -> 480 | M47: Assumes client provides CRM access and credentials. Delays here are common.
A48: 44 | C48: Forms – CRM Integration | D48: Data Mapping | E48: 15 | F48: =IFERROR(INDEX(Categories!$B$5:$B$27,MATCH(E48,Categories!$A$5:$A$27,0)),"") -> Integration | G48: Map fields | H48: IT | I48: Level 2 | J48: =IFERROR(INDEX(Rates!$D$6:$D$15,MATCH(H48&"|"&I48,Rates!$C$6:$C$15,0)),0) -> 120 | K48: 2 | L48: =K48*J48 -> 240 | M48: Hours rise with field count and custom CRM objects.
... A69: 65 | C69: E-Commerce | D69: Personalization | E69: 12 | F69: =IFERROR(INDEX(Categories!$B$5:$B$27,MATCH(E69,Categories!$A$5:$A$27,0)),"") -> E-Commerce | G69: Recommended products | H69: IT | I69: Level 2 | J69: =IFERROR(INDEX(Rates!$D$6:$D$15,MATCH(H69&"|"&I69,Rates!$C$6:$C$15,0)),0) -> 120 | K69: 8 | L69: =K69*J69 -> 960 | M69: Rule-based vs. algorithmic recommendations are very different scopes.
A70: 66 | C70: Configurator – Basic 2D | D70: Color Change Feature | E70: 5 | F70: =IFERROR(INDEX(Categories!$B$5:$B$27,MATCH(E70,Categories!$A$5:$A$27,0)),"") -> Custom Tools | G70: Dynamic UI updates | H70: IT | I70: Level 2 | J70: =IFERROR(INDEX(Rates!$D$6:$D$15,MATCH(H70&"|"&I70,Rates!$C$6:$C$15,0)),0) -> 120 | K70: 15 | L70: =K70*J70 -> 1800
A71: 67 | C71: Configurator – Basic 2D | D71: Shape Options | E71: 5 | F71: =IFERROR(INDEX(Categories!$B$5:$B$27,MATCH(E71,Categories!$A$5:$A$27,0)),"") -> Custom Tools | G71: Option selection | H71: IT | I71: Level 2 | J71: =IFERROR(INDEX(Rates!$D$6:$D$15,MATCH(H71&"|"&I71,Rates!$C$6:$C$15,0)),0) -> 120 | K71: 20 | L71: =K71*J71 -> 2400
A72: 68 | C72: Configurator – Basic 2D | D72: Static Preview Rendering | E72: 5 | F72: =IFERROR(INDEX(Categories!$B$5:$B$27,MATCH(E72,Categories!$A$5:$A$27,0)),"") -> Custom Tools | G72: Image generation | H72: IT | I72: Level 2 | J72: =IFERROR(INDEX(Rates!$D$6:$D$15,MATCH(H72&"|"&I72,Rates!$C$6:$C$15,0)),0) -> 120 | K72: 30 | L72: =K72*J72 -> 3600 | M72: Server-side rendering has hosting and performance implications worth pricing in.
A73: 69 | C73: Configurator – Advanced 2D | D73: Pattern Library | E73: 5 | F73: =IFERROR(INDEX(Categories!$B$5:$B$27,MATCH(E73,Categories!$A$5:$A$27,0)),"") -> Custom Tools | G73: Pattern system | H73: IT | I73: Level 2 | J73: =IFERROR(INDEX(Rates!$D$6:$D$15,MATCH(H73&"|"&I73,Rates!$C$6:$C$15,0)),0) -> 120 | K73: 30 | L73: =K73*J73 -> 3600 | M73: Pattern asset creation is Creative time and should be quoted separately.
A74: 70 | C74: Configurator – Advanced 2D | D74: Upload & Download Assets | E74: 5 | F74: =IFERROR(INDEX(Categories!$B$5:$B$27,MATCH(E74,Categories!$A$5:$A$27,0)),"") -> Custom Tools | G74: File handling | H74: IT | I74: Level 2 | J74: =IFERROR(INDEX(Rates!$D$6:$D$15,MATCH(H74&"|"&I74,Rates!$C$6:$C$15,0)),0) -> 120 | K74: 30 | L74: =K74*J74 -> 3600 | M74: File validation, size limits, and storage costs all need to be defined.
A75: 71 | C75: Configurator – Advanced 2D | D75: Screenshot Capture | E75: 5 | F75: =IFERROR(INDEX(Categories!$B$5:$B$27,MATCH(E75,Categories!$A$5:$A$27,0)),"") -> Custom Tools | G75: Capture previews | H75: IT | I75: Level 2 | J75: =IFERROR(INDEX(Rates!$D$6:$D$15,MATCH(H75&"|"&I75,Rates!$C$6:$C$15,0)),0) -> 120 | K75: 40 | L75: =K75*J75 -> 4800 | M75: Cross-browser behavior varies a lot. Budget extra QA.
A76: 72 | C76: Configurator – 3D | D76: WebGL Viewer | E76: 5 | F76: =IFERROR(INDEX(Categories!$B$5:$B$27,MATCH(E76,Categories!$A$5:$A$27,0)),"") -> Custom Tools | G76: 3D rendering | H76: IT | I76: Level 2 | J76: =IFERROR(INDEX(Rates!$D$6:$D$15,MATCH(H76&"|"&I76,Rates!$C$6:$C$15,0)),0) -> 120 | K76: 50 | L76: =K76*J76 -> 6000 | M76: Highest technical risk item on the sheet. Consider a paid discovery phase first.
A77: 73 | C77: Configurator – Full Builder | D77: Quote Generation | E77: 5 | F77: =IFERROR(INDEX(Categories!$B$5:$B$27,MATCH(E77,Categories!$A$5:$A$27,0)),"") -> Custom Tools | G77: Dynamic pricing | H77: IT | I77: Level 2 | J77: =IFERROR(INDEX(Rates!$D$6:$D$15,MATCH(H77&"|"&I77,Rates!$C$6:$C$15,0)),0) -> 120 | K77: 40 | L77: =K77*J77 -> 4800 | M77: Pricing rules come from the client and are often not ready. That delay is on them.
A78: 74 | C78: Configurator – Full Builder | D78: Saved Designs | E78: 5 | F78: =IFERROR(INDEX(Categories!$B$5:$B$27,MATCH(E78,Categories!$A$5:$A$27,0)),"") -> Custom Tools | G78: User saved states | H78: IT | I78: Level 2 | J78: =IFERROR(INDEX(Rates!$D$6:$D$15,MATCH(H78&"|"&I78,Rates!$C$6:$C$15,0)),0) -> 120 | K78: 40 | L78: =K78*J78 -> 4800 | M78: Overlaps with login and profile tasks. Avoid double-billing.
A79: 75 | C79: Configurator – Features | D79: Logo Upload | E79: 5 | F79: =IFERROR(INDEX(Categories!$B$5:$B$27,MATCH(E79,Categories!$A$5:$A$27,0)),"") -> Custom Tools | G79: File upload | H79: IT | I79: Level 2 | J79: =IFERROR(INDEX(Rates!$D$6:$D$15,MATCH(H79&"|"&I79,Rates!$C$6:$C$15,0)),0) -> 120 | K79: 12 | L79: =K79*J79 -> 1440 | M79: File type handling (SVG, PNG, transparency) is where the time goes.
A80: 76 | C80: Configurator – Features | D80: Size Calculator | E80: 5 | F80: =IFERROR(INDEX(Categories!$B$5:$B$27,MATCH(E80,Categories!$A$5:$A$27,0)),"") -> Custom Tools | G80: Calculation logic | H80: IT | I80: Level 2 | J80: =IFERROR(INDEX(Rates!$D$6:$D$15,MATCH(H80&"|"&I80,Rates!$C$6:$C$15,0)),0) -> 120 | K80: 15 | L80: =K80*J80 -> 1800 | M80: Formula complexity comes from the client. Get it in writing first.
A81: 77 | C81: Configurator – Features | D81: Shareable Link | E81: 5 | F81: =IFERROR(INDEX(Categories!$B$5:$B$27,MATCH(E81,Categories!$A$5:$A$27,0)),"") -> Custom Tools | G81: Share state via URL | H81: IT | I81: Level 2 | J81: =IFERROR(INDEX(Rates!$D$6:$D$15,MATCH(H81&"|"&I81,Rates!$C$6:$C$15,0)),0) -> 120 | K81: 12 | L81: =K81*J81 -> 1440
A82: 78 | C82: Configurator – Features | D82: Admin Dashboard | E82: 5 | F82: =IFERROR(INDEX(Categories!$B$5:$B$27,MATCH(E82,Categories!$A$5:$A$27,0)),"") -> Custom Tools | G82: Admin panel | H82: IT | I82: Level 2 | J82: =IFERROR(INDEX(Rates!$D$6:$D$15,MATCH(H82&"|"&I82,Rates!$C$6:$C$15,0)),0) -> 120 | K82: 40 | L82: =K82*J82 -> 4800 | M82: Reporting and export features can easily double this. Scope tightly.
A83: 79 | C83: Performance & Security | D83: SSL Setup | E83: 18 | F83: =IFERROR(INDEX(Categories!$B$5:$B$27,MATCH(E83,Categories!$A$5:$A$27,0)),"") -> Performance & Security | G83: SSL configuration | H83: IT | I83: Level 1 | J83: =IFERROR(INDEX(Rates!$D$6:$D$15,MATCH(H83&"|"&I83,Rates!$C$6:$C$15,0)),0) -> 100 | K83: 1 | L83: =K83*J83 -> 100 | M83: Assumes host provides free SSL. Custom or wildcard certs take longer.
A84: 80 | C84: Performance & Security | D84: Caching & Optimization | E84: 18 | F84: =IFERROR(INDEX(Categories!$B$5:$B$27,MATCH(E84,Categories!$A$5:$A$27,0)),"") -> Performance & Security | G84: Server + frontend optimization | H84: IT | I84: Level 2 | J84: =IFERROR(INDEX(Rates!$D$6:$D$15,MATCH(H84&"|"&I84,Rates!$C$6:$C$15,0)),0) -> 120 | K84: 10 | L84: =K84*J84 -> 1200 | M84: Full control here, so real gains are possible, unlike on hosted platforms.
A85: 81 | C85: Performance & Security | D85: Backup & Versioning | E85: 18 | F85: =IFERROR(INDEX(Categories!$B$5:$B$27,MATCH(E85,Categories!$A$5:$A$27,0)),"") -> Performance & Security | G85: Backup systems | H85: IT | I85: Level 1 | J85: =IFERROR(INDEX(Rates!$D$6:$D$15,MATCH(H85&"|"&I85,Rates!$C$6:$C$15,0)),0) -> 100 | K85: 4 | L85: =K85*J85 -> 400 | M85: No platform does this for you. Build it in or the client carries the risk.
A86: 82 | C86: Analytics & Tracking | D86: GA4 Setup | E86: 4 | F86: =IFERROR(INDEX(Categories!$B$5:$B$27,MATCH(E86,Categories!$A$5:$A$27,0)),"") -> Conversion Tracking | G86: Analytics setup | H86: IT | I86: Level 1 | J86: =IFERROR(INDEX(Rates!$D$6:$D$15,MATCH(H86&"|"&I86,Rates!$C$6:$C$15,0)),0) -> 100 | K86: 2 | L86: =K86*J86 -> 200 | M86: Assumes client already has a Google account. Access delays are common.
A87: 83 | C87: Analytics & Tracking | D87: GTM Setup | E87: 4 | F87: =IFERROR(INDEX(Categories!$B$5:$B$27,MATCH(E87,Categories!$A$5:$A$27,0)),"") -> Conversion Tracking | G87: Tag manager | H87: IT | I87: Level 1 | J87: =IFERROR(INDEX(Rates!$D$6:$D$15,MATCH(H87&"|"&I87,Rates!$C$6:$C$15,0)),0) -> 100 | K87: 3 | L87: =K87*J87 -> 300 | M87: Tag count drives hours. Note how many tags are included.
A88: 84 | C88: Analytics & Tracking | D88: Heatmaps | E88: 4 | F88: =IFERROR(INDEX(Categories!$B$5:$B$27,MATCH(E88,Categories!$A$5:$A$27,0)),"") -> Conversion Tracking | G88: User tracking | H88: IT | I88: Level 1 | J88: =IFERROR(INDEX(Rates!$D$6:$D$15,MATCH(H88&"|"&I88,Rates!$C$6:$C$15,0)),0) -> 100 | K88: 2 | L88: =K88*J88 -> 200 | M88: Excludes the heatmap tool subscription and any reporting or analysis.
A89: 85 | C89: Blog Setup | D89: Blog Listing | E89: 22 | F89: =IFERROR(INDEX(Categories!$B$5:$B$27,MATCH(E89,Categories!$A$5:$A$27,0)),"") -> SEO & Content | G89: Blog index | H89: IT | I89: Level 1 | J89: =IFERROR(INDEX(Rates!$D$6:$D$15,MATCH(H89&"|"&I89,Rates!$C$6:$C$15,0)),0) -> 100 | K89: 4 | L89: =K89*J89 -> 400
A90: 86 | C90: Blog Setup | D90: Single Article Template | E90: 22 | F90: =IFERROR(INDEX(Categories!$B$5:$B$27,MATCH(E90,Categories!$A$5:$A$27,0)),"") -> SEO & Content | G90: Blog post template | H90: IT | I90: Level 1 | J90: =IFERROR(INDEX(Rates!$D$6:$D$15,MATCH(H90&"|"&I90,Rates!$C$6:$C$15,0)),0) -> 100 | K90: 3 | L90: =K90*J90 -> 300
A91: 87 | C91: Blog Setup | D91: Lead Capture | E91: 22 | F91: =IFERROR(INDEX(Categories!$B$5:$B$27,MATCH(E91,Categories!$A$5:$A$27,0)),"") -> SEO & Content | G91: Newsletter form | H91: IT | I91: Level 1 | J91: =IFERROR(INDEX(Rates!$D$6:$D$15,MATCH(H91&"|"&I91,Rates!$C$6:$C$15,0)),0) -> 100 | K91: 2 | L91: =K91*J91 -> 200
A92: 88 | C92: SEO & Content | D92: SEO Setup | E92: 22 | F92: =IFERROR(INDEX(Categories!$B$5:$B$27,MATCH(E92,Categories!$A$5:$A$27,0)),"") -> SEO & Content | G92: On-page SEO | H92: IT | I92: Level 1 | J92: =IFERROR(INDEX(Rates!$D$6:$D$15,MATCH(H92&"|"&I92,Rates!$C$6:$C$15,0)),0) -> 100 | K92: 4 | L92: =K92*J92 -> 400 | M92: Excludes keyword research and strategy, which are separate services.
A93: 89 | C93: SEO & Content | D93: Schema Markup | E93: 24 | F93: =IFERROR(INDEX(Categories!$B$5:$B$27,MATCH(E93,Categories!$A$5:$A$27,0)),"") -> SEO on-page | G93: Structured data | H93: IT | I93: Level 2 | J93: =IFERROR(INDEX(Rates!$D$6:$D$15,MATCH(H93&"|"&I93,Rates!$C$6:$C$15,0)),0) -> 120 | K93: 4 | L93: =K93*J93 -> 480 | M93: Per schema type. Product, LocalBusiness, and FAQ schema each take their own time.
A94: 90 | C94: SEO & Content | D94: Sitemap Generation | E94: 24 | F94: =IFERROR(INDEX(Categories!$B$5:$B$27,MATCH(E94,Categories!$A$5:$A$27,0)),"") -> SEO on-page | G94: XML sitemap | H94: IT | I94: Level 1 | J94: =IFERROR(INDEX(Rates!$D$6:$D$15,MATCH(H94&"|"&I94,Rates!$C$6:$C$15,0)),0) -> 100 | K94: 2 | L94: =K94*J94 -> 200
A95: 91 | C95: SEO & Content | D95: Robots.txt Setup | E95: 24 | F95: =IFERROR(INDEX(Categories!$B$5:$B$27,MATCH(E95,Categories!$A$5:$A$27,0)),"") -> SEO on-page | G95: Crawl rules | H95: IT | I95: Level 1 | J95: =IFERROR(INDEX(Rates!$D$6:$D$15,MATCH(H95&"|"&I95,Rates!$C$6:$C$15,0)),0) -> 100 | K95: 1 | L95: =K95*J95 -> 100
A96: 92 | C96: SEO & Content | D96: Copy Optimization | E96: 22 | F96: =IFERROR(INDEX(Categories!$B$5:$B$27,MATCH(E96,Categories!$A$5:$A$27,0)),"") -> SEO & Content | G96: Improve content | H96: Creative | I96: Level 1 | J96: =IFERROR(INDEX(Rates!$D$6:$D$15,MATCH(H96&"|"&I96,Rates!$C$6:$C$15,0)),0) -> 100 | K96: 4 | L96: =K96*J96 -> 400 | M96: Per page. Define how many revision rounds are included.
A97: 93 | C97: SEO & Content | D97: New Copy (800 words) | E97: 22 | F97: =IFERROR(INDEX(Categories!$B$5:$B$27,MATCH(E97,Categories!$A$5:$A$27,0)),"") -> SEO & Content | G97: Content writing | H97: Creative | I97: Level 2 | J97: =IFERROR(INDEX(Rates!$D$6:$D$15,MATCH(H97&"|"&I97,Rates!$C$6:$C$15,0)),0) -> 130 | K97: 6 | L97: =K97*J97 -> 780 | M97: Per 800 words. Technical or specialized topics should bill higher.
A98: 94 | C98: SEO & Content | D98: URL Redirects | E98: 24 | F98: =IFERROR(INDEX(Categories!$B$5:$B$27,MATCH(E98,Categories!$A$5:$A$27,0)),"") -> SEO on-page | G98: 301 redirects | H98: IT | I98: Level 1 | J98: =IFERROR(INDEX(Rates!$D$6:$D$15,MATCH(H98&"|"&I98,Rates!$C$6:$C$15,0)),0) -> 100 | K98: 2 | L98: =K98*J98 -> 200 | M98: Large migrations need a URL mapping exercise first.
A99: 95 | C99: Environment Setup | D99: Hosting Setup | E99: 13 | F99: =IFERROR(INDEX(Categories!$B$5:$B$27,MATCH(E99,Categories!$A$5:$A$27,0)),"") -> Environment Setup | G99: Server setup | H99: IT | I99: Level 2 | J99: =IFERROR(INDEX(Rates!$D$6:$D$15,MATCH(H99&"|"&I99,Rates!$C$6:$C$15,0)),0) -> 120 | K99: 4 | L99: =K99*J99 -> 480 | M99: Raw server setup takes longer than managed hosting. Excludes hosting cost.
A100: 96 | C100: Environment Setup | D100: Base Project Setup | E100: 13 | F100: =IFERROR(INDEX(Categories!$B$5:$B$27,MATCH(E100,Categories!$A$5:$A$27,0)),"") -> Environment Setup | G100: PHP structure | H100: IT | I100: Level 1 | J100: =IFERROR(INDEX(Rates!$D$6:$D$15,MATCH(H100&"|"&I100,Rates!$C$6:$C$15,0)),0) -> 100 | K100: 3 | L100: =K100*J100 -> 300 | M100: Foundation work that every later task depends on. Do not skip it in the quote.
A101: 97 | C101: Environment Setup | D101: Routing Setup | E101: 2 | F101: =IFERROR(INDEX(Categories!$B$5:$B$27,MATCH(E101,Categories!$A$5:$A$27,0)),"") -> Backend | G101: URL routing | H101: IT | I101: Level 2 | J101: =IFERROR(INDEX(Rates!$D$6:$D$15,MATCH(H101&"|"&I101,Rates!$C$6:$C$15,0)),0) -> 120 | K101: 4 | L101: =K101*J101 -> 480 | M101: Foundation work. Clean URLs and SEO-friendly routes take longer than basic routing.
A102: 98 | C102: Environment Setup | D102: Database Setup | E102: 7 | F102: =IFERROR(INDEX(Categories!$B$5:$B$27,MATCH(E102,Categories!$A$5:$A$27,0)),"") -> Database | G102: DB schema | H102: IT | I102: Level 2 | J102: =IFERROR(INDEX(Rates!$D$6:$D$15,MATCH(H102&"|"&I102,Rates!$C$6:$C$15,0)),0) -> 120 | K102: 4 | L102: =K102*J102 -> 480 | M102: Excludes schema design, which is a separate line.
A103: 99 | C103: Environment Setup | D103: Auth System Setup | E103: 2 | F103: =IFERROR(INDEX(Categories!$B$5:$B$27,MATCH(E103,Categories!$A$5:$A$27,0)),"") -> Backend | G103: User auth system | H103: IT | I103: Level 2 | J103: =IFERROR(INDEX(Rates!$D$6:$D$15,MATCH(H103&"|"&I103,Rates!$C$6:$C$15,0)),0) -> 120 | K103: 6 | L103: =K103*J103 -> 720 | M103: Password reset, sessions, and security hardening should be confirmed in or out.
A104: 100 | C104: Environment Setup | D104: Dev Environment | E104: 13 | F104: =IFERROR(INDEX(Categories!$B$5:$B$27,MATCH(E104,Categories!$A$5:$A$27,0)),"") -> Environment Setup | G104: Local setup | H104: IT | I104: Level 1 | J104: =IFERROR(INDEX(Rates!$D$6:$D$15,MATCH(H104&"|"&I104,Rates!$C$6:$C$15,0)),0) -> 100 | K104: 3 | L104: =K104*J104 -> 300 | M104: Internal setup cost. Decide whether you bill this or absorb it.
A105: 101 | C105: Deployment | D105: Data Migration | E105: 6 | F105: =IFERROR(INDEX(Categories!$B$5:$B$27,MATCH(E105,Categories!$A$5:$A$27,0)),"") -> Data Migration | G105: Content migration | H105: IT | I105: Level 2 | J105: =IFERROR(INDEX(Rates!$D$6:$D$15,MATCH(H105&"|"&I105,Rates!$C$6:$C$15,0)),0) -> 120 | K105: 6 | L105: =K105*J105 -> 720 | M105: Biggest variable in the list. Depends entirely on the size and state of the old site.
A106: 102 | C106: Deployment | D106: Staging Setup | E106: 13 | F106: =IFERROR(INDEX(Categories!$B$5:$B$27,MATCH(E106,Categories!$A$5:$A$27,0)),"") -> Environment Setup | G106: Staging environment | H106: IT | I106: Level 2 | J106: =IFERROR(INDEX(Rates!$D$6:$D$15,MATCH(H106&"|"&I106,Rates!$C$6:$C$15,0)),0) -> 120 | K106: 4 | L106: =K106*J106 -> 480 | M106: No client-visible deliverable, so explain the value or absorb the cost.
A107: 103 | C107: Deployment | D107: Domain Setup | E107: 13 | F107: =IFERROR(INDEX(Categories!$B$5:$B$27,MATCH(E107,Categories!$A$5:$A$27,0)),"") -> Environment Setup | G107: DNS config | H107: IT | I107: Level 1 | J107: =IFERROR(INDEX(Rates!$D$6:$D$15,MATCH(H107&"|"&I107,Rates!$C$6:$C$15,0)),0) -> 100 | K107: 2 | L107: =K107*J107 -> 200 | M107: DNS propagation affects the schedule but is not billable work.
A108: 104 | C108: Deployment | D108: Production Deployment | E108: 8 | F108: =IFERROR(INDEX(Categories!$B$5:$B$27,MATCH(E108,Categories!$A$5:$A$27,0)),"") -> Deployment | G108: Launch | H108: IT | I108: Level 2 | J108: =IFERROR(INDEX(Rates!$D$6:$D$15,MATCH(H108&"|"&I108,Rates!$C$6:$C$15,0)),0) -> 120 | K108: 5 | L108: =K108*J108 -> 600 | M108: Schedule a rollback window. Launch-day issues are normal.
A109: 105 | C109: Deployment | D109: URL Sync | E109: 8 | F109: =IFERROR(INDEX(Categories!$B$5:$B$27,MATCH(E109,Categories!$A$5:$A$27,0)),"") -> Deployment | G109: URL updates | H109: IT | I109: Level 2 | J109: =IFERROR(INDEX(Rates!$D$6:$D$15,MATCH(H109&"|"&I109,Rates!$C$6:$C$15,0)),0) -> 120 | K109: 2 | L109: =K109*J109 -> 240
A110: 106 | C110: Deployment | D110: CDN Setup | E110: 18 | F110: =IFERROR(INDEX(Categories!$B$5:$B$27,MATCH(E110,Categories!$A$5:$A$27,0)),"") -> Performance & Security | G110: Cloudflare/CDN | H110: IT | I110: Level 2 | J110: =IFERROR(INDEX(Rates!$D$6:$D$15,MATCH(H110&"|"&I110,Rates!$C$6:$C$15,0)),0) -> 120 | K110: 4 | L110: =K110*J110 -> 480 | M110: Excludes CDN subscription costs.
A111: 107 | C111: Deployment | D111: SSL Fixes | E111: 8 | F111: =IFERROR(INDEX(Categories!$B$5:$B$27,MATCH(E111,Categories!$A$5:$A$27,0)),"") -> Deployment | G111: HTTPS fixes | H111: IT | I111: Level 1 | J111: =IFERROR(INDEX(Rates!$D$6:$D$15,MATCH(H111&"|"&I111,Rates!$C$6:$C$15,0)),0) -> 100 | K111: 2 | L111: =K111*J111 -> 200
A112: 108 | C112: Pre-Launch QA | D112: Final QA | E112: 25 | F112: =IFERROR(INDEX(Categories!$B$5:$B$27,MATCH(E112,Categories!$A$5:$A$27,0)),"") -> QA & Testing | G112: Full testing | H112: QA Tester | I112: Level 1 | J112: =IFERROR(INDEX(Rates!$D$6:$D$15,MATCH(H112&"|"&I112,Rates!$C$6:$C$15,0)),0) -> 80 | K112: 5 | L112: =K112*J112 -> 400 | M112: Scales with page count and feature count. Thin for a large site.
A113: 109 | C113: Post-Launch | D113: QA Fixes | E113: 25 | F113: =IFERROR(INDEX(Categories!$B$5:$B$27,MATCH(E113,Categories!$A$5:$A$27,0)),"") -> QA & Testing | G113: Bug fixes | H113: QA Tester | I113: Level 1 | J113: =IFERROR(INDEX(Rates!$D$6:$D$15,MATCH(H113&"|"&I113,Rates!$C$6:$C$15,0)),0) -> 80 | K113: 6 | L113: =K113*J113 -> 480 | M113: Define a support window, or this becomes unlimited free work.
A114: 110 | C114: Post-Launch | D114: Performance Check | E114: 18 | F114: =IFERROR(INDEX(Categories!$B$5:$B$27,MATCH(E114,Categories!$A$5:$A$27,0)),"") -> Performance & Security | G114: Speed testing | H114: QA Tester | I114: Level 1 | J114: =IFERROR(INDEX(Rates!$D$6:$D$15,MATCH(H114&"|"&I114,Rates!$C$6:$C$15,0)),0) -> 80 | K114: 3 | L114: =K114*J114 -> 240 | M114: Testing only. Any fixes found are billed under Performance & Security.
A115: 111 | C115: Post-Launch | D115: Tracking Verification | E115: 4 | F115: =IFERROR(INDEX(Categories!$B$5:$B$27,MATCH(E115,Categories!$A$5:$A$27,0)),"") -> Conversion Tracking | G115: Verify analytics | H115: QA Tester | I115: Level 1 | J115: =IFERROR(INDEX(Rates!$D$6:$D$15,MATCH(H115&"|"&I115,Rates!$C$6:$C$15,0)),0) -> 80 | K115: 2 | L115: =K115*J115 -> 160
A116: 112 | C116: Backend | D116: Database Setup & Configuration | E116: 7 | F116: =IFERROR(INDEX(Categories!$B$5:$B$27,MATCH(E116,Categories!$A$5:$A$27,0)),"") -> Database | G116: Create database, users, permissions, connection setup | H116: IT | I116: Level 2 | J116: =IFERROR(INDEX(Rates!$D$6:$D$15,MATCH(H116&"|"&I116,Rates!$C$6:$C$15,0)),0) -> 120 | K116: 6 | L116: =K116*J116 -> 720 | M116: Excludes schema design, which is a separate line.
A117: 113 | C117: Backend | D117: Database Schema Design | E117: 7 | F117: =IFERROR(INDEX(Categories!$B$5:$B$27,MATCH(E117,Categories!$A$5:$A$27,0)),"") -> Database | G117: Design tables, relationships, normalization | H117: IT | I117: Level 2 | J117: =IFERROR(INDEX(Rates!$D$6:$D$15,MATCH(H117&"|"&I117,Rates!$C$6:$C$15,0)),0) -> 120 | K117: 10 | L117: =K117*J117 -> 1200 | M117: Changes late in the project are expensive. Lock the schema before building.
A118: 114 | C118: Backend | D118: Data Modeling (Entities & Relationships) | E118: 7 | F118: =IFERROR(INDEX(Categories!$B$5:$B$27,MATCH(E118,Categories!$A$5:$A$27,0)),"") -> Database | G118: Define structure for features (users, products, etc.) | H118: IT | I118: Level 2 | J118: =IFERROR(INDEX(Rates!$D$6:$D$15,MATCH(H118&"|"&I118,Rates!$C$6:$C$15,0)),0) -> 120 | K118: 12 | L118: =K118*J118 -> 1440 | M118: Requires client input on their real data. Budget meeting time.
A119: 115 | C119: Backend | D119: Migrations / Versioning | E119: 7 | F119: =IFERROR(INDEX(Categories!$B$5:$B$27,MATCH(E119,Categories!$A$5:$A$27,0)),"") -> Database | G119: Setup schema version control and migrations | H119: IT | I119: Level 2 | J119: =IFERROR(INDEX(Rates!$D$6:$D$15,MATCH(H119&"|"&I119,Rates!$C$6:$C$15,0)),0) -> 120 | K119: 6 | L119: =K119*J119 -> 720 | M119: Pays for itself later, but clients rarely see the value. Explain it.
A120: 116 | C120: Backend | D120: ORM / Query Layer Setup | E120: 7 | F120: =IFERROR(INDEX(Categories!$B$5:$B$27,MATCH(E120,Categories!$A$5:$A$27,0)),"") -> Database | G120: Setup database abstraction or query handling | H120: IT | I120: Level 2 | J120: =IFERROR(INDEX(Rates!$D$6:$D$15,MATCH(H120&"|"&I120,Rates!$C$6:$C$15,0)),0) -> 120 | K120: 8 | L120: =K120*J120 -> 960 | M120: One-time foundation work. Reusable across projects.
A121: 117 | C121: Backend | D121: Seed Data / Initial Data Setup | E121: 7 | F121: =IFERROR(INDEX(Categories!$B$5:$B$27,MATCH(E121,Categories!$A$5:$A$27,0)),"") -> Database | G121: Populate initial data for testing/dev | H121: IT | I121: Level 2 | J121: =IFERROR(INDEX(Rates!$D$6:$D$15,MATCH(H121&"|"&I121,Rates!$C$6:$C$15,0)),0) -> 120 | K121: 4 | L121: =K121*J121 -> 480 | M121: Test data only. Real content entry is separate.
A122: 118 | C122: Backend | D122: Database Optimization | E122: 7 | F122: =IFERROR(INDEX(Categories!$B$5:$B$27,MATCH(E122,Categories!$A$5:$A$27,0)),"") -> Database | G122: Indexes, query optimization, performance tuning | H122: IT | I122: Level 2 | J122: =IFERROR(INDEX(Rates!$D$6:$D$15,MATCH(H122&"|"&I122,Rates!$C$6:$C$15,0)),0) -> 120 | K122: 8 | L122: =K122*J122 -> 960 | M122: Only meaningful once there is real data volume. Consider billing post-launch.
D124: TOTAL | K124: =SUM(K5:K122) -> 1003 | L124: =SUM(L5:L122) -> 116840 | M124: Whole library total, not a project quote. Quote only the tasks a job needs.

Sheet React-NextJS
A1: Task Pricing – React.js / Next.js
A2: Base Hours unchanged. Several rows on this tab were copied from the WordPress sheet - see the notes column.
A4: id | B4: Dependencies | C4: Module | D4: Name | E4: category_id | F4: Category | G4: Description | H4: Responsible | I4: Level | J4: Rate | K4: Base Hours | L4: Estimated Cost | M4: Hours – Things to Consider
A5: 1 | C5: Homepage – Standard | D5: Hero Section | E5: 14 | F5: =IFERROR(INDEX(Categories!$B$5:$B$27,MATCH(E5,Categories!$A$5:$A$27,0)),"") -> Frontend | G5: Hero section and headline | H5: IT | I5: Level 1 | J5: =IFERROR(INDEX(Rates!$D$6:$D$15,MATCH(H5&"|"&I5,Rates!$C$6:$C$15,0)),0) -> 100 | K5: 2 | L5: =K5*J5 -> 200
A6: 2 | C6: Homepage – Standard | D6: Services / Product Grid | E6: 14 | F6: =IFERROR(INDEX(Categories!$B$5:$B$27,MATCH(E6,Categories!$A$5:$A$27,0)),"") -> Frontend | G6: Grid for services/products | H6: IT | I6: Level 1 | J6: =IFERROR(INDEX(Rates!$D$6:$D$15,MATCH(H6&"|"&I6,Rates!$C$6:$C$15,0)),0) -> 100 | K6: 3 | L6: =K6*J6 -> 300 | M6: Assumes a fixed number of items. Dynamic, data-driven grids cost more.
A7: 3 | C7: Homepage – Standard | D7: Testimonials Slider (Dynamic) | E7: 15 | F7: =IFERROR(INDEX(Categories!$B$5:$B$27,MATCH(E7,Categories!$A$5:$A$27,0)),"") -> Integration | G7: API-driven testimonials | H7: IT | I7: Level 2 | J7: =IFERROR(INDEX(Rates!$D$6:$D$15,MATCH(H7&"|"&I7,Rates!$C$6:$C$15,0)),0) -> 120 | K7: 8 | L7: =K7*J7 -> 960 | M7: Depends on the review platform's API. Add hours for keys, rate limits, and caching.
A8: 4 | C8: Homepage – Standard | D8: Testimonials (Embed) | E8: 15 | F8: =IFERROR(INDEX(Categories!$B$5:$B$27,MATCH(E8,Categories!$A$5:$A$27,0)),"") -> Integration | G8: Embedded testimonials | H8: IT | I8: Level 1 | J8: =IFERROR(INDEX(Rates!$D$6:$D$15,MATCH(H8&"|"&I8,Rates!$C$6:$C$15,0)),0) -> 100 | K8: 3 | L8: =K8*J8 -> 300 | M8: Styling a third-party widget can take longer than expected if the platform limits CSS.
A9: 5 | C9: Homepage – Standard | D9: Team Preview | E9: 14 | F9: =IFERROR(INDEX(Categories!$B$5:$B$27,MATCH(E9,Categories!$A$5:$A$27,0)),"") -> Frontend | G9: Team section | H9: IT | I9: Level 1 | J9: =IFERROR(INDEX(Rates!$D$6:$D$15,MATCH(H9&"|"&I9,Rates!$C$6:$C$15,0)),0) -> 100 | K9: 1.5 | L9: =K9*J9 -> 150 | M9: Bios and photo cropping are content work, not build work.
A10: 6 | C10: Homepage – Standard | D10: Footer Layout | E10: 14 | F10: =IFERROR(INDEX(Categories!$B$5:$B$27,MATCH(E10,Categories!$A$5:$A$27,0)),"") -> Frontend | G10: Footer with nav/contact | H10: IT | I10: Level 1 | J10: =IFERROR(INDEX(Rates!$D$6:$D$15,MATCH(H10&"|"&I10,Rates!$C$6:$C$15,0)),0) -> 100 | K10: 1.5 | L10: =K10*J10 -> 150 | M10: Mega-footers with multiple menus and a newsletter form run higher.
A11: 7 | C11: Homepage – Conversion | D11: Strong Hero Offer | E11: 14 | F11: =IFERROR(INDEX(Categories!$B$5:$B$27,MATCH(E11,Categories!$A$5:$A$27,0)),"") -> Frontend | G11: Hero with CTA | H11: IT | I11: Level 1 | J11: =IFERROR(INDEX(Rates!$D$6:$D$15,MATCH(H11&"|"&I11,Rates!$C$6:$C$15,0)),0) -> 100 | K11: 4 | L11: =K11*J11 -> 400
A12: 8 | C12: Homepage – Conversion | D12: Benefits / Features | E12: 14 | F12: =IFERROR(INDEX(Categories!$B$5:$B$27,MATCH(E12,Categories!$A$5:$A$27,0)),"") -> Frontend | G12: Feature sections | H12: IT | I12: Level 1 | J12: =IFERROR(INDEX(Rates!$D$6:$D$15,MATCH(H12&"|"&I12,Rates!$C$6:$C$15,0)),0) -> 100 | K12: 3 | L12: =K12*J12 -> 300 | M12: Icon sourcing or custom icons may need Creative hours on top.
A13: 9 | C13: Homepage – Conversion | D13: Social Proof / Trust Badges | E13: 14 | F13: =IFERROR(INDEX(Categories!$B$5:$B$27,MATCH(E13,Categories!$A$5:$A$27,0)),"") -> Frontend | G13: Logos and trust elements | H13: IT | I13: Level 1 | J13: =IFERROR(INDEX(Rates!$D$6:$D$15,MATCH(H13&"|"&I13,Rates!$C$6:$C$15,0)),0) -> 100 | K13: 2 | L13: =K13*J13 -> 200 | M13: Assumes client supplies logos in usable formats. Logo cleanup is Creative time.
A14: 10 | C14: Homepage – Conversion | D14: FAQ Section | E14: 14 | F14: =IFERROR(INDEX(Categories!$B$5:$B$27,MATCH(E14,Categories!$A$5:$A$27,0)),"") -> Frontend | G14: FAQ block | H14: IT | I14: Level 1 | J14: =IFERROR(INDEX(Rates!$D$6:$D$15,MATCH(H14&"|"&I14,Rates!$C$6:$C$15,0)),0) -> 100 | K14: 2 | L14: =K14*J14 -> 200 | M14: Add a little time if FAQ schema markup is also required.
A15: 11 | C15: Homepage – Standard | D15: Pricing Tables | E15: 14 | F15: =IFERROR(INDEX(Categories!$B$5:$B$27,MATCH(E15,Categories!$A$5:$A$27,0)),"") -> Frontend | G15: Pricing layout | H15: IT | I15: Level 1 | J15: =IFERROR(INDEX(Rates!$D$6:$D$15,MATCH(H15&"|"&I15,Rates!$C$6:$C$15,0)),0) -> 100 | K15: 4 | L15: =K15*J15 -> 400 | M15: Monthly/annual toggles or more than 3 plans push this higher.
A16: 12 | C16: Homepage – Standard | D16: Galleries | E16: 14 | F16: =IFERROR(INDEX(Categories!$B$5:$B$27,MATCH(E16,Categories!$A$5:$A$27,0)),"") -> Frontend | G16: Image galleries | H16: IT | I16: Level 1 | J16: =IFERROR(INDEX(Rates!$D$6:$D$15,MATCH(H16&"|"&I16,Rates!$C$6:$C$15,0)),0) -> 100 | K16: 2 | L16: =K16*J16 -> 200 | M16: Per gallery. Image prep is billed separately.
A17: 13 | C17: Homepage – Standard | D17: Video Embeds | E17: 14 | F17: =IFERROR(INDEX(Categories!$B$5:$B$27,MATCH(E17,Categories!$A$5:$A$27,0)),"") -> Frontend | G17: Video embeds | H17: IT | I17: Level 1 | J17: =IFERROR(INDEX(Rates!$D$6:$D$15,MATCH(H17&"|"&I17,Rates!$C$6:$C$15,0)),0) -> 100 | K17: 1 | L17: =K17*J17 -> 100 | M17: Self-hosted video or custom players are a different, larger scope.
A18: 14 | C18: Homepage – Standard | D18: Payment / Contribution Module | E18: 15 | F18: =IFERROR(INDEX(Categories!$B$5:$B$27,MATCH(E18,Categories!$A$5:$A$27,0)),"") -> Integration | G18: Stripe/PayPal plugin-based | H18: IT | I18: Level 2 | J18: =IFERROR(INDEX(Rates!$D$6:$D$15,MATCH(H18&"|"&I18,Rates!$C$6:$C$15,0)),0) -> 120 | K18: 5 | L18: =K18*J18 -> 600 | M18: Excludes merchant account setup. Test-mode and live-mode testing both take time.
A19: 15 | C19: Homepage – Standard | D19: Use Cases | E19: 14 | F19: =IFERROR(INDEX(Categories!$B$5:$B$27,MATCH(E19,Categories!$A$5:$A$27,0)),"") -> Frontend | G19: Use case sections | H19: IT | I19: Level 1 | J19: =IFERROR(INDEX(Rates!$D$6:$D$15,MATCH(H19&"|"&I19,Rates!$C$6:$C$15,0)),0) -> 100 | K19: 2 | L19: =K19*J19 -> 200
A20: 16 | C20: Homepage – Multi-Industry | D20: Industry Selector | E20: 14 | F20: =IFERROR(INDEX(Categories!$B$5:$B$27,MATCH(E20,Categories!$A$5:$A$27,0)),"") -> Frontend | G20: Multi-industry selector | H20: IT | I20: Level 2 | J20: =IFERROR(INDEX(Rates!$D$6:$D$15,MATCH(H20&"|"&I20,Rates!$C$6:$C$15,0)),0) -> 120 | K20: 8 | L20: =K20*J20 -> 960 | M20: Hours scale with the number of industries. Confirm a cap in the quote.
A21: 17 | C21: Homepage – Multi-Industry | D21: Location Selector | E21: 14 | F21: =IFERROR(INDEX(Categories!$B$5:$B$27,MATCH(E21,Categories!$A$5:$A$27,0)),"") -> Frontend | G21: Location selector | H21: IT | I21: Level 2 | J21: =IFERROR(INDEX(Rates!$D$6:$D$15,MATCH(H21&"|"&I21,Rates!$C$6:$C$15,0)),0) -> 120 | K21: 8 | L21: =K21*J21 -> 960 | M21: Hours scale with the number of locations. Confirm a cap in the quote.
A22: 18 | C22: Homepage – Multi-Industry | D22: Dynamic Content Sections | E22: 14 | F22: =IFERROR(INDEX(Categories!$B$5:$B$27,MATCH(E22,Categories!$A$5:$A$27,0)),"") -> Frontend | G22: Conditional content | H22: IT | I22: Level 2 | J22: =IFERROR(INDEX(Rates!$D$6:$D$15,MATCH(H22&"|"&I22,Rates!$C$6:$C$15,0)),0) -> 120 | K22: 10 | L22: =K22*J22 -> 1200 | M22: Each extra rule adds testing time, not just build time.
A23: 19 | C23: Homepage – Multi-Industry | D23: Interactive Location Finder | E23: 15 | F23: =IFERROR(INDEX(Categories!$B$5:$B$27,MATCH(E23,Categories!$A$5:$A$27,0)),"") -> Integration | G23: Map-based finder | H23: IT | I23: Level 2 | J23: =IFERROR(INDEX(Rates!$D$6:$D$15,MATCH(H23&"|"&I23,Rates!$C$6:$C$15,0)),0) -> 120 | K23: 12 | L23: =K23*J23 -> 1440 | M23: Excludes map API billing. Radius search and geolocation add hours.
A24: 20 | C24: Homepage – Multi-Industry | D24: Multi-Audience Messaging | E24: 14 | F24: =IFERROR(INDEX(Categories!$B$5:$B$27,MATCH(E24,Categories!$A$5:$A$27,0)),"") -> Frontend | G24: Audience targeting | H24: IT | I24: Level 2 | J24: =IFERROR(INDEX(Rates!$D$6:$D$15,MATCH(H24&"|"&I24,Rates!$C$6:$C$15,0)),0) -> 120 | K24: 12 | L24: =K24*J24 -> 1440 | M24: Content writing for each segment is separate from the build.
A25: 21 | C25: Homepage – Advanced Dynamic | D25: Custom-Coded Blocks | E25: 14 | F25: =IFERROR(INDEX(Categories!$B$5:$B$27,MATCH(E25,Categories!$A$5:$A$27,0)),"") -> Frontend | G25: Reusable custom blocks | H25: IT | I25: Level 2 | J25: =IFERROR(INDEX(Rates!$D$6:$D$15,MATCH(H25&"|"&I25,Rates!$C$6:$C$15,0)),0) -> 120 | K25: 15 | L25: =K25*J25 -> 1800 | M25: Hours depend on how many blocks. Define the block count in the quote.
A26: 22 | C26: Homepage – Advanced Dynamic | D26: Search Bar with Filters | E26: 14 | F26: =IFERROR(INDEX(Categories!$B$5:$B$27,MATCH(E26,Categories!$A$5:$A$27,0)),"") -> Frontend | G26: Advanced filtering | H26: IT | I26: Level 2 | J26: =IFERROR(INDEX(Rates!$D$6:$D$15,MATCH(H26&"|"&I26,Rates!$C$6:$C$15,0)),0) -> 120 | K26: 18 | L26: =K26*J26 -> 2160 | M26: AJAX filtering, large datasets, and combined filters all add time.
A27: 23 | C27: Homepage – Advanced Dynamic | D27: API-Driven Content | E27: 14 | F27: =IFERROR(INDEX(Categories!$B$5:$B$27,MATCH(E27,Categories!$A$5:$A$27,0)),"") -> Frontend | G27: External API data | H27: IT | I27: Level 2 | J27: =IFERROR(INDEX(Rates!$D$6:$D$15,MATCH(H27&"|"&I27,Rates!$C$6:$C$15,0)),0) -> 120 | K27: 15 | L27: =K27*J27 -> 1800 | M27: Poorly documented or unstable third-party APIs are the biggest overrun risk.
A28: 24 | C28: Homepage – Advanced Dynamic | D28: Interactive Dashboard | E28: 5 | F28: =IFERROR(INDEX(Categories!$B$5:$B$27,MATCH(E28,Categories!$A$5:$A$27,0)),"") -> Custom Tools | G28: Data dashboards | H28: IT | I28: Level 2 | J28: =IFERROR(INDEX(Rates!$D$6:$D$15,MATCH(H28&"|"&I28,Rates!$C$6:$C$15,0)),0) -> 120 | K28: 18 | L28: =K28*J28 -> 2160 | M28: Chart count, data sources, and export features drive the real number. Scope tightly.
A29: 25 | C29: Homepage – Creative | D29: Full-Screen Visuals | E29: 14 | F29: =IFERROR(INDEX(Categories!$B$5:$B$27,MATCH(E29,Categories!$A$5:$A$27,0)),"") -> Frontend | G29: Image-heavy design | H29: Creative | I29: Level 1 | J29: =IFERROR(INDEX(Rates!$D$6:$D$15,MATCH(H29&"|"&I29,Rates!$C$6:$C$15,0)),0) -> 100 | K29: 6 | L29: =K29*J29 -> 600 | M29: Image sourcing, licensing, and retouching may be billed separately.
A30: 26 | C30: Homepage – Creative | D30: Parallax Effects | E30: 14 | F30: =IFERROR(INDEX(Categories!$B$5:$B$27,MATCH(E30,Categories!$A$5:$A$27,0)),"") -> Frontend | G30: Scroll animations | H30: IT | I30: Level 2 | J30: =IFERROR(INDEX(Rates!$D$6:$D$15,MATCH(H30&"|"&I30,Rates!$C$6:$C$15,0)),0) -> 120 | K30: 5 | L30: =K30*J30 -> 600 | M30: Mobile performance testing usually takes as long as the build.
A31: 27 | C31: Homepage – Creative | D31: Hover Animations | E31: 14 | F31: =IFERROR(INDEX(Categories!$B$5:$B$27,MATCH(E31,Categories!$A$5:$A$27,0)),"") -> Frontend | G31: Interactive hover states | H31: IT | I31: Level 1 | J31: =IFERROR(INDEX(Rates!$D$6:$D$15,MATCH(H31&"|"&I31,Rates!$C$6:$C$15,0)),0) -> 100 | K31: 4 | L31: =K31*J31 -> 400 | M31: Needs a touch-device fallback, which is easy to forget in the estimate.
... A35: 31 | C35: Homepage – Conversion | D35: Forms Spam Protection (reCAPTCHA) | E35: 18 | F35: =IFERROR(INDEX(Categories!$B$5:$B$27,MATCH(E35,Categories!$A$5:$A$27,0)),"") -> Performance & Security | G35: Spam prevention | H35: IT | I35: Level 1 | J35: =IFERROR(INDEX(Rates!$D$6:$D$15,MATCH(H35&"|"&I35,Rates!$C$6:$C$15,0)),0) -> 100 | K35: 1 | L35: =K35*J35 -> 100 | M35: Covers all forms at once.
A36: 32 | C36: Homepage – Advanced Dynamic | D36: Multi-Step Wizard Form | E36: 14 | F36: =IFERROR(INDEX(Categories!$B$5:$B$27,MATCH(E36,Categories!$A$5:$A$27,0)),"") -> Frontend | G36: Advanced multi-step form | H36: IT | I36: Level 2 | J36: =IFERROR(INDEX(Rates!$D$6:$D$15,MATCH(H36&"|"&I36,Rates!$C$6:$C$15,0)),0) -> 120 | K36: 20 | L36: =K36*J36 -> 2400
A37: 33 | C37: Core Page - Standard | D37: Standard Page (About, Services) | E37: 14 | F37: =IFERROR(INDEX(Categories!$B$5:$B$27,MATCH(E37,Categories!$A$5:$A$27,0)),"") -> Frontend | G37: Content page | H37: IT | I37: Level 1 | J37: =IFERROR(INDEX(Rates!$D$6:$D$15,MATCH(H37&"|"&I37,Rates!$C$6:$C$15,0)),0) -> 100 | K37: 8 | L37: =K37*J37 -> 800 | M37: Per page. Multiply by page count and confirm the total in the quote.
A38: 34 | C38: Core Page - Landing Page | D38: Conversion Page | E38: 14 | F38: =IFERROR(INDEX(Categories!$B$5:$B$27,MATCH(E38,Categories!$A$5:$A$27,0)),"") -> Frontend | G38: Landing page layout | H38: IT | I38: Level 1 | J38: =IFERROR(INDEX(Rates!$D$6:$D$15,MATCH(H38&"|"&I38,Rates!$C$6:$C$15,0)),0) -> 100 | K38: 8 | L38: =K38*J38 -> 800 | M38: Per page. Second and later pages using the same layout should be cheaper.
A39: 35 | C39: Core Page - Contact Page | D39: Contact Page | E39: 14 | F39: =IFERROR(INDEX(Categories!$B$5:$B$27,MATCH(E39,Categories!$A$5:$A$27,0)),"") -> Frontend | G39: Contact form + details | H39: IT | I39: Level 1 | J39: =IFERROR(INDEX(Rates!$D$6:$D$15,MATCH(H39&"|"&I39,Rates!$C$6:$C$15,0)),0) -> 100 | K39: 6 | L39: =K39*J39 -> 600 | M39: Includes one form. Map embed and multi-location info may add time.
A40: 36 | C40: Core Page - Detail Pages | D40: Detail Template (Blog/Service) | E40: 14 | F40: =IFERROR(INDEX(Categories!$B$5:$B$27,MATCH(E40,Categories!$A$5:$A$27,0)),"") -> Frontend | G40: Dynamic template | H40: IT | I40: Level 1 | J40: =IFERROR(INDEX(Rates!$D$6:$D$15,MATCH(H40&"|"&I40,Rates!$C$6:$C$15,0)),0) -> 100 | K40: 6 | L40: =K40*J40 -> 600
A41: 37 | C41: Forms – Standard | D41: Form Setup | E41: 14 | F41: =IFERROR(INDEX(Categories!$B$5:$B$27,MATCH(E41,Categories!$A$5:$A$27,0)),"") -> Frontend | G41: Layout, validation, email | H41: IT | I41: Level 1 | J41: =IFERROR(INDEX(Rates!$D$6:$D$15,MATCH(H41&"|"&I41,Rates!$C$6:$C$15,0)),0) -> 100 | K41: 3 | L41: =K41*J41 -> 300 | M41: Priced per form. Confirm the form count before quoting.
A42: 38 | C42: Forms – Multi-Step | D42: Multi-Step Layout | E42: 14 | F42: =IFERROR(INDEX(Categories!$B$5:$B$27,MATCH(E42,Categories!$A$5:$A$27,0)),"") -> Frontend | G42: Multi-step UI | H42: IT | I42: Level 2 | J42: =IFERROR(INDEX(Rates!$D$6:$D$15,MATCH(H42&"|"&I42,Rates!$C$6:$C$15,0)),0) -> 120 | K42: 4 | L42: =K42*J42 -> 480 | M42: Step count drives hours. Note the assumed number of steps.
A43: 39 | C43: Forms – Multi-Step | D43: Branch Logic Implementation | E43: 14 | F43: =IFERROR(INDEX(Categories!$B$5:$B$27,MATCH(E43,Categories!$A$5:$A$27,0)),"") -> Frontend | G43: Conditional logic | H43: IT | I43: Level 2 | J43: =IFERROR(INDEX(Rates!$D$6:$D$15,MATCH(H43&"|"&I43,Rates!$C$6:$C$15,0)),0) -> 120 | K43: 4 | L43: =K43*J43 -> 480 | M43: Testing every branch path often exceeds build time. Add QA hours.
A44: 40 | C44: Forms – Multi-Step | D44: Submission Handling | E44: 2 | F44: =IFERROR(INDEX(Categories!$B$5:$B$27,MATCH(E44,Categories!$A$5:$A$27,0)),"") -> Backend | G44: Store/process submissions | H44: IT | I44: Level 2 | J44: =IFERROR(INDEX(Rates!$D$6:$D$15,MATCH(H44&"|"&I44,Rates!$C$6:$C$15,0)),0) -> 120 | K44: 2 | L44: =K44*J44 -> 240 | M44: Partial-save and resume functionality would add substantially.
A45: 41 | C45: Forms – CRM Integration | D45: CRM API Setup | E45: 15 | F45: =IFERROR(INDEX(Categories!$B$5:$B$27,MATCH(E45,Categories!$A$5:$A$27,0)),"") -> Integration | G45: CRM connection | H45: IT | I45: Level 2 | J45: =IFERROR(INDEX(Rates!$D$6:$D$15,MATCH(H45&"|"&I45,Rates!$C$6:$C$15,0)),0) -> 120 | K45: 4 | L45: =K45*J45 -> 480 | M45: Assumes client provides CRM access and credentials. Delays here are common.
A46: 42 | C46: Forms – CRM Integration | D46: Data Mapping | E46: 15 | F46: =IFERROR(INDEX(Categories!$B$5:$B$27,MATCH(E46,Categories!$A$5:$A$27,0)),"") -> Integration | G46: Field mapping | H46: IT | I46: Level 2 | J46: =IFERROR(INDEX(Rates!$D$6:$D$15,MATCH(H46&"|"&I46,Rates!$C$6:$C$15,0)),0) -> 120 | K46: 2 | L46: =K46*J46 -> 240 | M46: Hours rise with field count and custom CRM objects.
A47: 43 | C47: Forms – CRM Integration | D47: Error Handling & Logging | E47: 15 | F47: =IFERROR(INDEX(Categories!$B$5:$B$27,MATCH(E47,Categories!$A$5:$A$27,0)),"") -> Integration | G47: Error handling | H47: IT | I47: Level 2 | J47: =IFERROR(INDEX(Rates!$D$6:$D$15,MATCH(H47&"|"&I47,Rates!$C$6:$C$15,0)),0) -> 120 | K47: 2 | L47: =K47*J47 -> 240 | M47: Retry logic and admin alerts would add hours.
A48: 44 | C48: Integrations | D48: Appointment System | E48: 15 | F48: =IFERROR(INDEX(Categories!$B$5:$B$27,MATCH(E48,Categories!$A$5:$A$27,0)),"") -> Integration | G48: Booking plugin | H48: IT | I48: Level 1 | J48: =IFERROR(INDEX(Rates!$D$6:$D$15,MATCH(H48&"|"&I48,Rates!$C$6:$C$15,0)),0) -> 100 | K48: 3 | L48: =K48*J48 -> 300 | M48: Excludes staff schedules, services, and availability data entry.
A49: 45 | C49: Integrations | D49: Live Chat Integration | E49: 15 | F49: =IFERROR(INDEX(Categories!$B$5:$B$27,MATCH(E49,Categories!$A$5:$A$27,0)),"") -> Integration | G49: Chat widget | H49: IT | I49: Level 1 | J49: =IFERROR(INDEX(Rates!$D$6:$D$15,MATCH(H49&"|"&I49,Rates!$C$6:$C$15,0)),0) -> 100 | K49: 2 | L49: =K49*J49 -> 200 | M49: Excludes the chat tool subscription.
A50: 46 | C50: Integrations | D50: API Integration Basic | E50: 15 | F50: =IFERROR(INDEX(Categories!$B$5:$B$27,MATCH(E50,Categories!$A$5:$A$27,0)),"") -> Integration | G50: Simple API | H50: IT | I50: Level 2 | J50: =IFERROR(INDEX(Rates!$D$6:$D$15,MATCH(H50&"|"&I50,Rates!$C$6:$C$15,0)),0) -> 120 | K50: 12 | L50: =K50*J50 -> 1440 | M50: Define 'basic' in writing: read-only, one endpoint, documented API.
A51: 47 | C51: Integrations | D51: API Integration Complex | E51: 15 | F51: =IFERROR(INDEX(Categories!$B$5:$B$27,MATCH(E51,Categories!$A$5:$A$27,0)),"") -> Integration | G51: Advanced API | H51: IT | I51: Level 2 | J51: =IFERROR(INDEX(Rates!$D$6:$D$15,MATCH(H51&"|"&I51,Rates!$C$6:$C$15,0)),0) -> 120 | K51: 25 | L51: =K51*J51 -> 3000 | M51: High overrun risk. Consider quoting a discovery block first, then the build.
A52: 48 | C52: Integrations | D52: Zapier Workflows | E52: 15 | F52: =IFERROR(INDEX(Categories!$B$5:$B$27,MATCH(E52,Categories!$A$5:$A$27,0)),"") -> Integration | G52: Automation | H52: IT | I52: Level 1 | J52: =IFERROR(INDEX(Rates!$D$6:$D$15,MATCH(H52&"|"&I52,Rates!$C$6:$C$15,0)),0) -> 100 | K52: 6 | L52: =K52*J52 -> 600 | M52: Note how many Zaps are included. Excludes the Zapier subscription.
... A59: 55 | C59: E-Commerce | D59: Product Template | E59: 12 | F59: =IFERROR(INDEX(Categories!$B$5:$B$27,MATCH(E59,Categories!$A$5:$A$27,0)),"") -> E-Commerce | G59: Product page template | H59: IT | I59: Level 2 | J59: =IFERROR(INDEX(Rates!$D$6:$D$15,MATCH(H59&"|"&I59,Rates!$C$6:$C$15,0)),0) -> 120 | K59: 7 | L59: =K59*J59 -> 840 | M59: One template. Simple and variable products may need different treatments.
A60: 56 | C60: E-Commerce | D60: Featured Products | E60: 12 | F60: =IFERROR(INDEX(Categories!$B$5:$B$27,MATCH(E60,Categories!$A$5:$A$27,0)),"") -> E-Commerce | G60: Homepage products | H60: IT | I60: Level 1 | J60: =IFERROR(INDEX(Rates!$D$6:$D$15,MATCH(H60&"|"&I60,Rates!$C$6:$C$15,0)),0) -> 100 | K60: 6 | L60: =K60*J60 -> 600
A61: 57 | C61: E-Commerce | D61: Sales Banners | E61: 12 | F61: =IFERROR(INDEX(Categories!$B$5:$B$27,MATCH(E61,Categories!$A$5:$A$27,0)),"") -> E-Commerce | G61: Promo banners | H61: Creative | I61: Level 1 | J61: =IFERROR(INDEX(Rates!$D$6:$D$15,MATCH(H61&"|"&I61,Rates!$C$6:$C$15,0)),0) -> 100 | K61: 5 | L61: =K61*J61 -> 500 | M61: Recurring campaign artwork is worth a separate maintenance line item.
A62: 58 | C62: E-Commerce | D62: Dynamic Product Feeds | E62: 12 | F62: =IFERROR(INDEX(Categories!$B$5:$B$27,MATCH(E62,Categories!$A$5:$A$27,0)),"") -> E-Commerce | G62: Product listings | H62: IT | I62: Level 2 | J62: =IFERROR(INDEX(Rates!$D$6:$D$15,MATCH(H62&"|"&I62,Rates!$C$6:$C$15,0)),0) -> 120 | K62: 8 | L62: =K62*J62 -> 960 | M62: Feeds to Google Merchant Center or Meta have their own spec requirements.
A63: 59 | C63: E-Commerce | D63: Category Highlights | E63: 12 | F63: =IFERROR(INDEX(Categories!$B$5:$B$27,MATCH(E63,Categories!$A$5:$A$27,0)),"") -> E-Commerce | G63: Product categories | H63: IT | I63: Level 1 | J63: =IFERROR(INDEX(Rates!$D$6:$D$15,MATCH(H63&"|"&I63,Rates!$C$6:$C$15,0)),0) -> 100 | K63: 6 | L63: =K63*J63 -> 600
A64: 60 | C64: E-Commerce | D64: Customer Reviews | E64: 12 | F64: =IFERROR(INDEX(Categories!$B$5:$B$27,MATCH(E64,Categories!$A$5:$A$27,0)),"") -> E-Commerce | G64: Reviews | H64: IT | I64: Level 2 | J64: =IFERROR(INDEX(Rates!$D$6:$D$15,MATCH(H64&"|"&I64,Rates!$C$6:$C$15,0)),0) -> 120 | K64: 6 | L64: =K64*J64 -> 720 | M64: Importing existing reviews would be extra.
A65: 61 | C65: E-Commerce | D65: Personalization Blocks | E65: 12 | F65: =IFERROR(INDEX(Categories!$B$5:$B$27,MATCH(E65,Categories!$A$5:$A$27,0)),"") -> E-Commerce | G65: Recommendations | H65: IT | I65: Level 2 | J65: =IFERROR(INDEX(Rates!$D$6:$D$15,MATCH(H65&"|"&I65,Rates!$C$6:$C$15,0)),0) -> 120 | K65: 6 | L65: =K65*J65 -> 720 | M65: Rule-based vs. algorithmic recommendations are very different scopes.
A66: 62 | C66: E-Commerce | D66: Cart Functionality | E66: 12 | F66: =IFERROR(INDEX(Categories!$B$5:$B$27,MATCH(E66,Categories!$A$5:$A$27,0)),"") -> E-Commerce | G66: Add to cart | H66: IT | I66: Level 2 | J66: =IFERROR(INDEX(Rates!$D$6:$D$15,MATCH(H66&"|"&I66,Rates!$C$6:$C$15,0)),0) -> 120 | K66: 5 | L66: =K66*J66 -> 600 | M66: Mini-cart and AJAX cart customization add hours.
A67: 63 | C67: E-Commerce | D67: Checkout Flow | E67: 12 | F67: =IFERROR(INDEX(Categories!$B$5:$B$27,MATCH(E67,Categories!$A$5:$A$27,0)),"") -> E-Commerce | G67: Checkout page | H67: IT | I67: Level 2 | J67: =IFERROR(INDEX(Rates!$D$6:$D$15,MATCH(H67&"|"&I67,Rates!$C$6:$C$15,0)),0) -> 120 | K67: 8 | L67: =K67*J67 -> 960 | M67: Custom fields, guest checkout, and one-page checkout all add time.
A68: 64 | C68: E-Commerce | D68: Shipping Rules | E68: 12 | F68: =IFERROR(INDEX(Categories!$B$5:$B$27,MATCH(E68,Categories!$A$5:$A$27,0)),"") -> E-Commerce | G68: Shipping setup | H68: IT | I68: Level 2 | J68: =IFERROR(INDEX(Rates!$D$6:$D$15,MATCH(H68&"|"&I68,Rates!$C$6:$C$15,0)),0) -> 120 | K68: 6 | L68: =K68*J68 -> 720 | M68: Live carrier rates are more work than flat-rate zones.
A69: 65 | C69: E-Commerce | D69: Payment Gateway Integration | E69: 12 | F69: =IFERROR(INDEX(Categories!$B$5:$B$27,MATCH(E69,Categories!$A$5:$A$27,0)),"") -> E-Commerce | G69: Stripe/PayPal | H69: IT | I69: Level 2 | J69: =IFERROR(INDEX(Rates!$D$6:$D$15,MATCH(H69&"|"&I69,Rates!$C$6:$C$15,0)),0) -> 120 | K69: 5 | L69: =K69*J69 -> 600 | M69: Excludes merchant account approval. Client delays are common.
A70: 66 | C70: E-Commerce | D70: Tax Calculator | E70: 12 | F70: =IFERROR(INDEX(Categories!$B$5:$B$27,MATCH(E70,Categories!$A$5:$A$27,0)),"") -> E-Commerce | G70: Tax logic | H70: IT | I70: Level 2 | J70: =IFERROR(INDEX(Rates!$D$6:$D$15,MATCH(H70&"|"&I70,Rates!$C$6:$C$15,0)),0) -> 120 | K70: 4 | L70: =K70*J70 -> 480 | M70: Multi-state or international tax is a bigger scope.
A71: 67 | C71: E-Commerce | D71: Product Variations Setup | E71: 12 | F71: =IFERROR(INDEX(Categories!$B$5:$B$27,MATCH(E71,Categories!$A$5:$A$27,0)),"") -> E-Commerce | G71: Configure product variations (size, color, attributes) | H71: IT | I71: Level 1 | J71: =IFERROR(INDEX(Rates!$D$6:$D$15,MATCH(H71&"|"&I71,Rates!$C$6:$C$15,0)),0) -> 100 | K71: 3 | L71: =K71*J71 -> 300 | M71: Setup only, not per-product entry. Multiply by product count separately.
A72: 68 | C72: 68: Variations | D72: Advanced Product Options (Plugin) | E72: 14 | F72: =IFERROR(INDEX(Categories!$B$5:$B$27,MATCH(E72,Categories!$A$5:$A$27,0)),"") -> Frontend | G72: Custom fields/options via plugin | H72: IT | I72: Level 1 | J72: =IFERROR(INDEX(Rates!$D$6:$D$15,MATCH(H72&"|"&I72,Rates!$C$6:$C$15,0)),0) -> 100 | K72: 6 | L72: =K72*J72 -> 600
A73: 69 | C73: 68: Options | D73: Product Add-Ons (Conditional Logic) | E73: 14 | F73: =IFERROR(INDEX(Categories!$B$5:$B$27,MATCH(E73,Categories!$A$5:$A$27,0)),"") -> Frontend | G73: Add-ons with logic via plugin | H73: IT | I73: Level 2 | J73: =IFERROR(INDEX(Rates!$D$6:$D$15,MATCH(H73&"|"&I73,Rates!$C$6:$C$15,0)),0) -> 120 | K73: 8 | L73: =K73*J73 -> 960
A74: 70 | C74: 62-66 Required | D74: Subscriptions Setup | E74: 14 | F74: =IFERROR(INDEX(Categories!$B$5:$B$27,MATCH(E74,Categories!$A$5:$A$27,0)),"") -> Frontend | G74: Recurring payments (plugin) | H74: IT | I74: Level 2 | J74: =IFERROR(INDEX(Rates!$D$6:$D$15,MATCH(H74&"|"&I74,Rates!$C$6:$C$15,0)),0) -> 120 | K74: 6 | L74: =K74*J74 -> 720 | M74: Failed-payment and renewal testing takes real time.
A75: 71 | C75: 62-66 Required | D75: Discount Rules / Coupons Setup | E75: 14 | F75: =IFERROR(INDEX(Categories!$B$5:$B$27,MATCH(E75,Categories!$A$5:$A$27,0)),"") -> Frontend | G75: Coupons and promos | H75: IT | I75: Level 1 | J75: =IFERROR(INDEX(Rates!$D$6:$D$15,MATCH(H75&"|"&I75,Rates!$C$6:$C$15,0)),0) -> 100 | K75: 4 | L75: =K75*J75 -> 400 | M75: Covers setup of the system, not ongoing campaign creation.
A76: 72 | C76: 71: Discounts | D76: Advanced Pricing Rules (Plugin) | E76: 14 | F76: =IFERROR(INDEX(Categories!$B$5:$B$27,MATCH(E76,Categories!$A$5:$A$27,0)),"") -> Frontend | G76: Dynamic/role pricing | H76: IT | I76: Level 2 | J76: =IFERROR(INDEX(Rates!$D$6:$D$15,MATCH(H76&"|"&I76,Rates!$C$6:$C$15,0)),0) -> 120 | K76: 8 | L76: =K76*J76 -> 960
A77: 73 | C77: 55-66 Required | D77: Product Bundles / Packages | E77: 14 | F77: =IFERROR(INDEX(Categories!$B$5:$B$27,MATCH(E77,Categories!$A$5:$A$27,0)),"") -> Frontend | G77: Bundled products | H77: IT | I77: Level 1 | J77: =IFERROR(INDEX(Rates!$D$6:$D$15,MATCH(H77&"|"&I77,Rates!$C$6:$C$15,0)),0) -> 100 | K77: 6 | L77: =K77*J77 -> 600
A78: 74 | C78: E-Commerce | D78: Wishlist Functionality | E78: 12 | F78: =IFERROR(INDEX(Categories!$B$5:$B$27,MATCH(E78,Categories!$A$5:$A$27,0)),"") -> E-Commerce | G78: Wishlist plugin | H78: IT | I78: Level 1 | J78: =IFERROR(INDEX(Rates!$D$6:$D$15,MATCH(H78&"|"&I78,Rates!$C$6:$C$15,0)),0) -> 100 | K78: 4 | L78: =K78*J78 -> 400
A79: 75 | C79: E-Commerce | D79: Product Filtering (Advanced) | E79: 12 | F79: =IFERROR(INDEX(Categories!$B$5:$B$27,MATCH(E79,Categories!$A$5:$A$27,0)),"") -> E-Commerce | G79: Advanced filters plugin | H79: IT | I79: Level 2 | J79: =IFERROR(INDEX(Rates!$D$6:$D$15,MATCH(H79&"|"&I79,Rates!$C$6:$C$15,0)),0) -> 120 | K79: 6 | L79: =K79*J79 -> 720
A80: 76 | C80: Configurator – Basic | D80: Color Change Feature | E80: 5 | F80: =IFERROR(INDEX(Categories!$B$5:$B$27,MATCH(E80,Categories!$A$5:$A$27,0)),"") -> Custom Tools | G80: Color switching | H80: IT | I80: Level 2 | J80: =IFERROR(INDEX(Rates!$D$6:$D$15,MATCH(H80&"|"&I80,Rates!$C$6:$C$15,0)),0) -> 120 | K80: 15 | L80: =K80*J80 -> 1800
A81: 77 | C81: Configurator – Basic | D81: Shape Options | E81: 5 | F81: =IFERROR(INDEX(Categories!$B$5:$B$27,MATCH(E81,Categories!$A$5:$A$27,0)),"") -> Custom Tools | G81: Shape selection | H81: IT | I81: Level 2 | J81: =IFERROR(INDEX(Rates!$D$6:$D$15,MATCH(H81&"|"&I81,Rates!$C$6:$C$15,0)),0) -> 120 | K81: 20 | L81: =K81*J81 -> 2400
A82: 78 | C82: Configurator – Basic | D82: Static Preview Rendering | E82: 5 | F82: =IFERROR(INDEX(Categories!$B$5:$B$27,MATCH(E82,Categories!$A$5:$A$27,0)),"") -> Custom Tools | G82: Preview images | H82: IT | I82: Level 2 | J82: =IFERROR(INDEX(Rates!$D$6:$D$15,MATCH(H82&"|"&I82,Rates!$C$6:$C$15,0)),0) -> 120 | K82: 30 | L82: =K82*J82 -> 3600 | M82: Server-side rendering has hosting and performance implications worth pricing in.
A83: 79 | C83: Configurator – Advanced | D83: Pattern Library | E83: 5 | F83: =IFERROR(INDEX(Categories!$B$5:$B$27,MATCH(E83,Categories!$A$5:$A$27,0)),"") -> Custom Tools | G83: Pattern system | H83: IT | I83: Level 2 | J83: =IFERROR(INDEX(Rates!$D$6:$D$15,MATCH(H83&"|"&I83,Rates!$C$6:$C$15,0)),0) -> 120 | K83: 30 | L83: =K83*J83 -> 3600 | M83: Pattern asset creation is Creative time and should be quoted separately.
A84: 80 | C84: Configurator – Advanced | D84: Upload & Download Assets | E84: 5 | F84: =IFERROR(INDEX(Categories!$B$5:$B$27,MATCH(E84,Categories!$A$5:$A$27,0)),"") -> Custom Tools | G84: File handling | H84: IT | I84: Level 2 | J84: =IFERROR(INDEX(Rates!$D$6:$D$15,MATCH(H84&"|"&I84,Rates!$C$6:$C$15,0)),0) -> 120 | K84: 30 | L84: =K84*J84 -> 3600 | M84: File validation, size limits, and storage costs all need to be defined.
A85: 81 | C85: Configurator – Advanced | D85: Screenshot Capture | E85: 5 | F85: =IFERROR(INDEX(Categories!$B$5:$B$27,MATCH(E85,Categories!$A$5:$A$27,0)),"") -> Custom Tools | G85: Capture designs | H85: IT | I85: Level 2 | J85: =IFERROR(INDEX(Rates!$D$6:$D$15,MATCH(H85&"|"&I85,Rates!$C$6:$C$15,0)),0) -> 120 | K85: 40 | L85: =K85*J85 -> 4800 | M85: Cross-browser behavior varies a lot. Budget extra QA.
A86: 82 | C86: Configurator – 3D | D86: Camera Controls | E86: 5 | F86: =IFERROR(INDEX(Categories!$B$5:$B$27,MATCH(E86,Categories!$A$5:$A$27,0)),"") -> Custom Tools | G86: 3D camera | H86: IT | I86: Level 2 | J86: =IFERROR(INDEX(Rates!$D$6:$D$15,MATCH(H86&"|"&I86,Rates!$C$6:$C$15,0)),0) -> 120 | K86: 40 | L86: =K86*J86 -> 4800 | M86: Mobile performance is the main risk on all WebGL work.
A87: 83 | C87: Configurator – 3D | D87: 3D Asset Integration | E87: 5 | F87: =IFERROR(INDEX(Categories!$B$5:$B$27,MATCH(E87,Categories!$A$5:$A$27,0)),"") -> Custom Tools | G87: 3D models | H87: IT | I87: Level 2 | J87: =IFERROR(INDEX(Rates!$D$6:$D$15,MATCH(H87&"|"&I87,Rates!$C$6:$C$15,0)),0) -> 120 | K87: 50 | L87: =K87*J87 -> 6000 | M87: Excludes 3D modeling. Confirm the client supplies optimized models.
A88: 84 | C88: Configurator – 3D | D88: Real-Time Rendering | E88: 5 | F88: =IFERROR(INDEX(Categories!$B$5:$B$27,MATCH(E88,Categories!$A$5:$A$27,0)),"") -> Custom Tools | G88: Real-time visuals | H88: IT | I88: Level 2 | J88: =IFERROR(INDEX(Rates!$D$6:$D$15,MATCH(H88&"|"&I88,Rates!$C$6:$C$15,0)),0) -> 120 | K88: 55 | L88: =K88*J88 -> 6600 | M88: Highest technical risk item on the sheet. Consider a paid discovery phase first.
A89: 85 | C89: Configurator – Full Builder | D89: Template Setup | E89: 5 | F89: =IFERROR(INDEX(Categories!$B$5:$B$27,MATCH(E89,Categories!$A$5:$A$27,0)),"") -> Custom Tools | G89: Custom builder | H89: IT | I89: Level 2 | J89: =IFERROR(INDEX(Rates!$D$6:$D$15,MATCH(H89&"|"&I89,Rates!$C$6:$C$15,0)),0) -> 120 | K89: 80 | L89: =K89*J89 -> 9600 | M89: 80-hour items should be split into phases with milestone billing.
A90: 86 | C90: Configurator – Full Builder | D90: Measurement Tools | E90: 5 | F90: =IFERROR(INDEX(Categories!$B$5:$B$27,MATCH(E90,Categories!$A$5:$A$27,0)),"") -> Custom Tools | G90: Dimension tools | H90: IT | I90: Level 2 | J90: =IFERROR(INDEX(Rates!$D$6:$D$15,MATCH(H90&"|"&I90,Rates!$C$6:$C$15,0)),0) -> 120 | K90: 80 | L90: =K90*J90 -> 9600 | M90: Unit conversion and accuracy requirements need to be written down.
A91: 87 | C91: Configurator – Full Builder | D91: Quote Generation | E91: 5 | F91: =IFERROR(INDEX(Categories!$B$5:$B$27,MATCH(E91,Categories!$A$5:$A$27,0)),"") -> Custom Tools | G91: Dynamic pricing | H91: IT | I91: Level 2 | J91: =IFERROR(INDEX(Rates!$D$6:$D$15,MATCH(H91&"|"&I91,Rates!$C$6:$C$15,0)),0) -> 120 | K91: 80 | L91: =K91*J91 -> 9600 | M91: Pricing rules come from the client and are often not ready. That delay is on them.
A92: 88 | C92: Configurator – Full Builder | D92: Saved Designs | E92: 5 | F92: =IFERROR(INDEX(Categories!$B$5:$B$27,MATCH(E92,Categories!$A$5:$A$27,0)),"") -> Custom Tools | G92: User saves | H92: IT | I92: Level 2 | J92: =IFERROR(INDEX(Rates!$D$6:$D$15,MATCH(H92&"|"&I92,Rates!$C$6:$C$15,0)),0) -> 120 | K92: 80 | L92: =K92*J92 -> 9600 | M92: Overlaps with login and profile tasks. Avoid double-billing.
A93: 89 | C93: Configurator – Features | D93: Logo Upload | E93: 5 | F93: =IFERROR(INDEX(Categories!$B$5:$B$27,MATCH(E93,Categories!$A$5:$A$27,0)),"") -> Custom Tools | G93: Upload logos | H93: IT | I93: Level 2 | J93: =IFERROR(INDEX(Rates!$D$6:$D$15,MATCH(H93&"|"&I93,Rates!$C$6:$C$15,0)),0) -> 120 | K93: 12 | L93: =K93*J93 -> 1440 | M93: File type handling (SVG, PNG, transparency) is where the time goes.
A94: 90 | C94: Configurator – Features | D94: Size Calculator | E94: 5 | F94: =IFERROR(INDEX(Categories!$B$5:$B$27,MATCH(E94,Categories!$A$5:$A$27,0)),"") -> Custom Tools | G94: Size logic | H94: IT | I94: Level 2 | J94: =IFERROR(INDEX(Rates!$D$6:$D$15,MATCH(H94&"|"&I94,Rates!$C$6:$C$15,0)),0) -> 120 | K94: 15 | L94: =K94*J94 -> 1800 | M94: Formula complexity comes from the client. Get it in writing first.
A95: 91 | C95: Configurator – Features | D95: Shareable Link | E95: 5 | F95: =IFERROR(INDEX(Categories!$B$5:$B$27,MATCH(E95,Categories!$A$5:$A$27,0)),"") -> Custom Tools | G95: Share links | H95: IT | I95: Level 2 | J95: =IFERROR(INDEX(Rates!$D$6:$D$15,MATCH(H95&"|"&I95,Rates!$C$6:$C$15,0)),0) -> 120 | K95: 12 | L95: =K95*J95 -> 1440
A96: 92 | C96: Configurator – Features | D96: Admin Dashboard | E96: 5 | F96: =IFERROR(INDEX(Categories!$B$5:$B$27,MATCH(E96,Categories!$A$5:$A$27,0)),"") -> Custom Tools | G96: Admin tools | H96: IT | I96: Level 2 | J96: =IFERROR(INDEX(Rates!$D$6:$D$15,MATCH(H96&"|"&I96,Rates!$C$6:$C$15,0)),0) -> 120 | K96: 44 | L96: =K96*J96 -> 5280 | M96: Reporting and export features can easily double this. Scope tightly.
A97: 93 | C97: Performance & Security | D97: SSL Configuration | E97: 18 | F97: =IFERROR(INDEX(Categories!$B$5:$B$27,MATCH(E97,Categories!$A$5:$A$27,0)),"") -> Performance & Security | G97: SSL setup | H97: IT | I97: Level 1 | J97: =IFERROR(INDEX(Rates!$D$6:$D$15,MATCH(H97&"|"&I97,Rates!$C$6:$C$15,0)),0) -> 100 | K97: 1 | L97: =K97*J97 -> 100 | M97: Assumes host provides free SSL. Custom or wildcard certs take longer.
A98: 94 | C98: Performance & Security | D98: Caching & Optimization | E98: 18 | F98: =IFERROR(INDEX(Categories!$B$5:$B$27,MATCH(E98,Categories!$A$5:$A$27,0)),"") -> Performance & Security | G98: Caching + speed | H98: IT | I98: Level 2 | J98: =IFERROR(INDEX(Rates!$D$6:$D$15,MATCH(H98&"|"&I98,Rates!$C$6:$C$15,0)),0) -> 120 | K98: 8 | L98: =K98*J98 -> 960 | M98: ISR, SSR, and caching strategy decisions belong in Discovery, not the build.
A99: 95 | C99: Performance & Security | D99: Backup & Versioning | E99: 18 | F99: =IFERROR(INDEX(Categories!$B$5:$B$27,MATCH(E99,Categories!$A$5:$A$27,0)),"") -> Performance & Security | G99: Backups | H99: IT | I99: Level 1 | J99: =IFERROR(INDEX(Rates!$D$6:$D$15,MATCH(H99&"|"&I99,Rates!$C$6:$C$15,0)),0) -> 100 | K99: 2 | L99: =K99*J99 -> 200 | M99: Setup only. Ongoing backup monitoring belongs in Maintenance & Support.
A100: 96 | C100: Analytics & Tracking | D100: GA4 Setup | E100: 4 | F100: =IFERROR(INDEX(Categories!$B$5:$B$27,MATCH(E100,Categories!$A$5:$A$27,0)),"") -> Conversion Tracking | G100: Analytics | H100: IT | I100: Level 1 | J100: =IFERROR(INDEX(Rates!$D$6:$D$15,MATCH(H100&"|"&I100,Rates!$C$6:$C$15,0)),0) -> 100 | K100: 2 | L100: =K100*J100 -> 200 | M100: Assumes client already has a Google account. Access delays are common.
A101: 97 | C101: Analytics & Tracking | D101: GTM Setup | E101: 4 | F101: =IFERROR(INDEX(Categories!$B$5:$B$27,MATCH(E101,Categories!$A$5:$A$27,0)),"") -> Conversion Tracking | G101: Tag manager | H101: IT | I101: Level 1 | J101: =IFERROR(INDEX(Rates!$D$6:$D$15,MATCH(H101&"|"&I101,Rates!$C$6:$C$15,0)),0) -> 100 | K101: 3 | L101: =K101*J101 -> 300 | M101: Tag count drives hours. Note how many tags are included.
A102: 98 | C102: Analytics & Tracking | D102: Heatmaps | E102: 4 | F102: =IFERROR(INDEX(Categories!$B$5:$B$27,MATCH(E102,Categories!$A$5:$A$27,0)),"") -> Conversion Tracking | G102: Heatmaps | H102: IT | I102: Level 1 | J102: =IFERROR(INDEX(Rates!$D$6:$D$15,MATCH(H102&"|"&I102,Rates!$C$6:$C$15,0)),0) -> 100 | K102: 1 | L102: =K102*J102 -> 100 | M102: Excludes the heatmap tool subscription and any reporting or analysis.
A103: 99 | C103: Analytics & Tracking | D103: Conversion Tracking (Basic) | E103: 4 | F103: =IFERROR(INDEX(Categories!$B$5:$B$27,MATCH(E103,Categories!$A$5:$A$27,0)),"") -> Conversion Tracking | G103: Form tracking | H103: IT | I103: Level 1 | J103: =IFERROR(INDEX(Rates!$D$6:$D$15,MATCH(H103&"|"&I103,Rates!$C$6:$C$15,0)),0) -> 100 | K103: 6 | L103: =K103*J103 -> 600 | M103: Form submissions only. Advanced event tracking is a separate line.
A104: 100 | C104: Analytics & Tracking | D104: Conversion Tracking (Moderate) | E104: 4 | F104: =IFERROR(INDEX(Categories!$B$5:$B$27,MATCH(E104,Categories!$A$5:$A$27,0)),"") -> Conversion Tracking | G104: Events + testing | H104: IT | I104: Level 2 | J104: =IFERROR(INDEX(Rates!$D$6:$D$15,MATCH(H104&"|"&I104,Rates!$C$6:$C$15,0)),0) -> 120 | K104: 8 | L104: =K104*J104 -> 960 | M104: Capped at 8 events. Price extra events individually.
A105: 101 | C105: Blog Setup | D105: Blog Listing Page | E105: 22 | F105: =IFERROR(INDEX(Categories!$B$5:$B$27,MATCH(E105,Categories!$A$5:$A$27,0)),"") -> SEO & Content | G105: Blog index | H105: IT | I105: Level 1 | J105: =IFERROR(INDEX(Rates!$D$6:$D$15,MATCH(H105&"|"&I105,Rates!$C$6:$C$15,0)),0) -> 100 | K105: 2 | L105: =K105*J105 -> 200 | M105: Category filtering and pagination styling may add time.
A106: 102 | C106: Blog Setup | D106: Single Article Template | E106: 22 | F106: =IFERROR(INDEX(Categories!$B$5:$B$27,MATCH(E106,Categories!$A$5:$A$27,0)),"") -> SEO & Content | G106: Post template | H106: IT | I106: Level 1 | J106: =IFERROR(INDEX(Rates!$D$6:$D$15,MATCH(H106&"|"&I106,Rates!$C$6:$C$15,0)),0) -> 100 | K106: 2 | L106: =K106*J106 -> 200
A107: 103 | C107: Blog Setup | D107: Lead Capture Integration | E107: 22 | F107: =IFERROR(INDEX(Categories!$B$5:$B$27,MATCH(E107,Categories!$A$5:$A$27,0)),"") -> SEO & Content | G107: Newsletter form | H107: IT | I107: Level 1 | J107: =IFERROR(INDEX(Rates!$D$6:$D$15,MATCH(H107&"|"&I107,Rates!$C$6:$C$15,0)),0) -> 100 | K107: 2 | L107: =K107*J107 -> 200 | M107: Email platform connection (Mailchimp etc.) may need integration hours.
A108: 104 | C108: SEO & Content | D108: SEO Tools Setup | E108: 22 | F108: =IFERROR(INDEX(Categories!$B$5:$B$27,MATCH(E108,Categories!$A$5:$A$27,0)),"") -> SEO & Content | G108: SEO plugin config | H108: IT | I108: Level 1 | J108: =IFERROR(INDEX(Rates!$D$6:$D$15,MATCH(H108&"|"&I108,Rates!$C$6:$C$15,0)),0) -> 100 | K108: 3 | L108: =K108*J108 -> 300 | M108: No SEO plugin here. Metadata is coded per route, which takes longer than WordPress.
